Workbook

Sheet Day1 28.09.2026
A1: Order ID | B1: Customer ID | C1: Order Date | D1: Ship Date | E1: City | F1: State | G1: Sales Channel | H1: Payment Method | I1: Product Category | J1: Product Name | K1: Brand | L1: Units Sold | M1: Unit Price | N1: Discount % | O1: Net Sales | P1: Total Price | Q1: Sale Status uses of IF | R1: Sale Status1 uses of IFS | S1: Sale Status2 uses of NESTED IF
A2: 10001 | B2: 1102 | C2: 45197 | D2: 45203 | E2: Chennai | F2: Delhi | G2: Mobile App | H2: Credit Card | I2: Home & Kitchen | J2: Mixer Grinder | K2: BrandA | L2: 7 | M2: 2843.87 | N2: 0 | O2: 19907.09 | P2: =L2*M2 -> 19907.09 | Q2: =IF(O2>=15000,"high","low") -> high | R2: {=_xlfn.IFS(O2>=20000,"high",O2>=15000,"medium",O2<15000,"low")} -> medium | S2: =IF(O2>=20000,"high",IF(O2>=15000,"mid","low")) -> mid
A3: 10002 | B3: 1435 | C3: 45199 | D3: 45203 | E3: Pune | F3: Tamil Nadu | G3: Website | H3: Debit Card | I3: Sports | J3: Football | K3: BrandD | L3: 9 | M3: 2525.23 | N3: 5 | O3: 21590.72 | P3: =L3*M3 -> 22727.07 | Q3: =IF(O3>=15000,"high","low") -> high | R3: {=_xlfn.IFS(O3>=20000,"high",O3>=15000,"medium",O3<15000,"low")} -> high | S3: =IF(O3>=20000,"high",IF(O3>=15000,"mid","low")) -> high | U3: COUNT
A4: 10003 | B4: 1860 | C4: 45109 | D4: 45114 | E4: Chennai | F4: West Bengal | G4: Marketplace | H4: Debit Card | I4: Fashion | J4: Sneakers | K4: BrandE | L4: 6 | M4: 3474.34 | N4: 15 | O4: 17719.13 | P4: =L4*M4 -> 20846.04 | Q4: =IF(O4>=15000,"high","low") -> high | R4: {=_xlfn.IFS(O4>=20000,"high",O4>=15000,"medium",O4<15000,"low")} -> medium | S4: =IF(O4>=20000,"high",IF(O4>=15000,"mid","low")) -> mid
A5: 10004 | B5: 1270 | C5: 45079 | D5: 45087 | E5: Bengaluru | F5: West Bengal | G5: Website | H5: Cash on Delivery | I5: Sports | J5: Yoga Mat | K5: BrandA | L5: 1 | M5: 1008.79 | N5: 15 | O5: 857.47 | P5: =L5*M5 -> 1008.79 | Q5: =IF(O5>=15000,"high","low") -> low | R5: {=_xlfn.IFS(O5>=20000,"high",O5>=15000,"medium",O5<15000,"low")} -> low | S5: =IF(O5>=20000,"high",IF(O5>=15000,"mid","low")) -> low
A6: 10005 | B6: 1106 | C6: 45241 | D6: 45244 | E6: Kolkata | F6: Karnataka | G6: Marketplace | H6: Credit Card | I6: Fashion | J6: Jacket | K6: BrandA | L6: 7 | M6: 3511.47 | N6: 20 | O6: 19664.23 | P6: =L6*M6 -> 24580.29 | Q6: =IF(O6>=15000,"high","low") -> high | R6: {=_xlfn.IFS(O6>=20000,"high",O6>=15000,"medium",O6<15000,"low")} -> medium | S6: =IF(O6>=20000,"high",IF(O6>=15000,"mid","low")) -> mid
A7: 10006 | B7: 1071 | C7: 45260 | D7: 45263 | E7: Hyderabad | F7: Telangana | G7: Website | H7: Net Banking | I7: Home & Kitchen | J7: Bedsheet | K7: BrandE | L7: 3 | M7: 3189.55 | N7: 10 | O7: 8611.78 | P7: =L7*M7 -> 9568.65 | Q7: =IF(O7>=15000,"high","low") -> low | R7: {=_xlfn.IFS(O7>=20000,"high",O7>=15000,"medium",O7<15000,"low")} -> low | S7: =IF(O7>=20000,"high",IF(O7>=15000,"mid","low")) -> low | U7: COUNTA
A8: 10007 | B8: 1700 | C8: 45050 | D8: 45054 | E8: Bengaluru | F8: Telangana | G8: Mobile App | H8: UPI | I8: Fashion | J8: Sneakers | K8: BrandC | L8: 5 | M8: 3030.42 | N8: 10 | O8: 13636.89 | P8: =L8*M8 -> 15152.1 | Q8: =IF(O8>=15000,"high","low") -> low | R8: {=_xlfn.IFS(O8>=20000,"high",O8>=15000,"medium",O8<15000,"low")} -> low | S8: =IF(O8>=20000,"high",IF(O8>=15000,"mid","low")) -> low
A9: 10008 | B9: 1020 | C9: 45040 | D9: 45041 | E9: Mumbai | F9: Delhi | G9: Website | H9: Credit Card | I9: Fashion | J9: Sneakers | K9: BrandB | L9: 4 | M9: 2310.83 | N9: 10 | O9: 8318.99 | P9: =L9*M9 -> 9243.32 | Q9: =IF(O9>=15000,"high","low") -> low | R9: {=_xlfn.IFS(O9>=20000,"high",O9>=15000,"medium",O9<15000,"low")} -> low | S9: =IF(O9>=20000,"high",IF(O9>=15000,"mid","low")) -> low
A10: 10009 | B10: 1614 | C10: 45204 | D10: 45213 | E10: Chennai | F10: West Bengal | G10: Website | H10: Debit Card | I10: Fashion | J10: T-Shirt | K10: BrandD | L10: 5 | M10: 1098.04 | N10: 15 | O10: 4666.67 | P10: =L10*M10 -> 5490.2 | Q10: =IF(O10>=15000,"high","low") -> low | R10: {=_xlfn.IFS(O10>=20000,"high",O10>=15000,"medium",O10<15000,"low")} -> low | S10: =IF(O10>=20000,"high",IF(O10>=15000,"mid","low")) -> low
A11: 10010 | B11: 1121 | C11: 45139 | D11: 45147 | E11: Bengaluru | F11: Karnataka | G11: Website | H11: Cash on Delivery | I11: Electronics | J11: Headphones | K11: BrandB | L11: 5 | M11: 1780.66 | N11: 20 | O11: 7122.64 | P11: =L11*M11 -> 8903.3 | Q11: =IF(O11>=15000,"high","low") -> low | R11: {=_xlfn.IFS(O11>=20000,"high",O11>=15000,"medium",O11<15000,"low")} -> low | S11: =IF(O11>=20000,"high",IF(O11>=15000,"mid","low")) -> low | U11: COUNTBLANK
A12: 10011 | B12: 1466 | C12: 45098 | D12: 45106 | E12: Bengaluru | F12: Karnataka | G12: Mobile App | H12: Cash on Delivery | I12: Electronics | J12: Headphones | K12: BrandE | L12: 6 | M12: 3205.25 | N12: 0 | O12: 19231.5 | P12: =L12*M12 -> 19231.5 | Q12: =IF(O12>=15000,"high","low") -> high | R12: {=_xlfn.IFS(O12>=20000,"high",O12>=15000,"medium",O12<15000,"low")} -> medium | S12: =IF(O12>=20000,"high",IF(O12>=15000,"mid","low")) -> mid
A13: 10012 | B13: 1214 | C13: 45214 | D13: 45220 | E13: Mumbai | F13: Tamil Nadu | G13: Website | H13: UPI | I13: Electronics | J13: Smartwatch | K13: BrandA | L13: 6 | M13: 272.35 | N13: 5 | O13: 1552.39 | P13: =L13*M13 -> 1634.1 | Q13: =IF(O13>=15000,"high","low") -> low | R13: {=_xlfn.IFS(O13>=20000,"high",O13>=15000,"medium",O13<15000,"low")} -> low | S13: =IF(O13>=20000,"high",IF(O13>=15000,"mid","low")) -> low
A14: 10013 | B14: 1330 | C14: 45100 | D14: 45107 | E14: Delhi | F14: Tamil Nadu | G14: Mobile App | H14: Cash on Delivery | I14: Home & Kitchen | J14: Bedsheet | K14: BrandA | L14: 8 | M14: 3160.9 | N14: 0 | O14: 25287.2 | P14: =L14*M14 -> 25287.2 | Q14: =IF(O14>=15000,"high","low") -> high | R14: {=_xlfn.IFS(O14>=20000,"high",O14>=15000,"medium",O14<15000,"low")} -> high | S14: =IF(O14>=20000,"high",IF(O14>=15000,"mid","low")) -> high
A15: 10014 | B15: 1458 | C15: 45039 | D15: 45045 | E15: Kolkata | F15: Karnataka | G15: Marketplace | H15: Cash on Delivery | I15: Sports | J15: Yoga Mat | K15: BrandD | L15: 8 | M15: 1074.27 | N15: 15 | O15: 7305.04 | P15: =L15*M15 -> 8594.16 | Q15: =IF(O15>=15000,"high","low") -> low | R15: {=_xlfn.IFS(O15>=20000,"high",O15>=15000,"medium",O15<15000,"low")} -> low | S15: =IF(O15>=20000,"high",IF(O15>=15000,"mid","low")) -> low
A16: 10015 | B16: 1087 | C16: 45048 | D16: 45057 | E16: Hyderabad | F16: Tamil Nadu | G16: Website | H16: Credit Card | I16: Beauty | J16: Shampoo | K16: BrandA | L16: 9 | M16: 705.59 | N16: 10 | O16: 5715.28 | P16: =L16*M16 -> 6350.31 | Q16: =IF(O16>=15000,"high","low") -> low | R16: {=_xlfn.IFS(O16>=20000,"high",O16>=15000,"medium",O16<15000,"low")} -> low | S16: =IF(O16>=20000,"high",IF(O16>=15000,"mid","low")) -> low
A17: 10016 | B17: 1372 | C17: 44958 | D17: 44961 | E17: Pune | F17: West Bengal | G17: Mobile App | H17: Net Banking | I17: Fashion | J17: Jacket | K17: BrandA | L17: 8 | M17: 595.45 | N17: 5 | O17: 4525.42 | P17: =L17*M17 -> 4763.6 | Q17: =IF(O17>=15000,"high","low") -> low | R17: {=_xlfn.IFS(O17>=20000,"high",O17>=15000,"medium",O17<15000,"low")} -> low | S17: =IF(O17>=20000,"high",IF(O17>=15000,"mid","low")) -> low
A18: 10017 | B18: 1099 | C18: 45148 | D18: 45151 | E18: Delhi | F18: Maharashtra | G18: Mobile App | H18: UPI | I18: Fashion | J18: Jacket | K18: BrandD | L18: 2 | M18: 254.91 | N18: 15 | O18: 433.35 | P18: =L18*M18 -> 509.82 | Q18: =IF(O18>=15000,"high","low") -> low | R18: {=_xlfn.IFS(O18>=20000,"high",O18>=15000,"medium",O18<15000,"low")} -> low | S18: =IF(O18>=20000,"high",IF(O18>=15000,"mid","low")) -> low
A19: 10018 | B19: 1871 | C19: 45045 | D19: 45048 | E19: Chennai | F19: West Bengal | G19: Website | H19: Credit Card | I19: Home & Kitchen | J19: Curtains | K19: BrandD | L19: 1 | M19: 2165.81 | N19: 15 | O19: 1840.94 | P19: =L19*M19 -> 2165.81 | Q19: =IF(O19>=15000,"high","low") -> low | R19: {=_xlfn.IFS(O19>=20000,"high",O19>=15000,"medium",O19<15000,"low")} -> low | S19: =IF(O19>=20000,"high",IF(O19>=15000,"mid","low")) -> low
A20: 10019 | B20: 1663 | C20: 44965 | D20: 44968 | E20: Bengaluru | F20: Karnataka | G20: Marketplace | H20: Net Banking | I20: Fashion | J20: Jacket | K20: BrandE | L20: 2 | M20: 990.3 | N20: 15 | O20: 1683.51 | P20: =L20*M20 -> 1980.6 | Q20: =IF(O20>=15000,"high","low") -> low | R20: {=_xlfn.IFS(O20>=20000,"high",O20>=15000,"medium",O20<15000,"low")} -> low | S20: =IF(O20>=20000,"high",IF(O20>=15000,"mid","low")) -> low
A21: 10020 | B21: 1130 | C21: 45194 | D21: 45203 | E21: Mumbai | F21: Karnataka | G21: Mobile App | H21: Credit Card | I21: Electronics | J21: Smartwatch | K21: BrandA | L21: 2 | M21: 3959.31 | N21: 5 | O21: 7522.69 | P21: =L21*M21 -> 7918.62 | Q21: =IF(O21>=15000,"high","low") -> low | R21: {=_xlfn.IFS(O21>=20000,"high",O21>=15000,"medium",O21<15000,"low")} -> low | S21: =IF(O21>=20000,"high",IF(O21>=15000,"mid","low")) -> low
A22: 10021 | B22: 1661 | C22: 45159 | D22: 45163 | E22: Mumbai | F22: West Bengal | G22: Website | H22: Credit Card | I22: Beauty | J22: Lipstick | K22: BrandA | L22: 3 | M22: 2361.58 | N22: 5 | O22: 6730.5 | P22: =L22*M22 -> 7084.74 | Q22: =IF(O22>=15000,"high","low") -> low | R22: {=_xlfn.IFS(O22>=20000,"high",O22>=15000,"medium",O22<15000,"low")} -> low | S22: =IF(O22>=20000,"high",IF(O22>=15000,"mid","low")) -> low
A23: 10022 | B23: 1308 | C23: 44944 | D23: 44951 | E23: Kolkata | F23: Tamil Nadu | G23: Marketplace | H23: Cash on Delivery | I23: Books | J23: Fiction Novel | K23: BrandE | L23: 7 | M23: 680.86 | N23: 20 | O23: 3812.82 | P23: =L23*M23 -> 4766.02 | Q23: =IF(O23>=15000,"high","low") -> low | R23: {=_xlfn.IFS(O23>=20000,"high",O23>=15000,"medium",O23<15000,"low")} -> low | S23: =IF(O23>=20000,"high",IF(O23>=15000,"mid","low")) -> low
... A501: 10500 | B501: 1569 | C501: 44972 | D501: 44977 | E501: Chennai | F501: Delhi | G501: Marketplace | H501: Net Banking | I501: Fashion | J501: Jeans | K501: BrandE | L501: 1 | M501: 2432.17 | N501: 20 | O501: 1945.74 | P501: =L501*M501 -> 2432.17 | Q501: =IF(O501>=15000,"high","low") -> low | R501: {=_xlfn.IFS(O501>=20000,"high",O501>=15000,"medium",O501<15000,"low")} -> low | S501: =IF(O501>=20000,"high",IF(O501>=15000,"mid","low")) -> low

Sheet Day2 29.09.2026
A1: Order ID | B1: Customer ID | C1: Order Date | D1: Ship Date | E1: City | F1: State | G1: Sales Channel | H1: Payment Method | I1: Product Category | J1: Product Name | K1: Brand | L1: Units Sold | M1: Unit Price | N1: Discount % | O1: Net Sales | P1: Total Price | Q1: Total Units Sold(SUM) | T1: Mobile App | U1: Home & Kitchen | V1: Credit Card | W1: BrandA
A2: 10001 | B2: 1102 | C2: 45197 | D2: 45203 | E2: Chennai | F2: Delhi | G2: Mobile App | H2: Credit Card | I2: Home & Kitchen | J2: Mixer Grinder | K2: BrandA | L2: 7 | M2: 2843.87 | N2: 0 | O2: 19907.09 | P2: =L2*M2 -> 19907.09 | Q2: =SUM(L2:L501) -> 2553 | T2: Website | U2: Sports | V2: Debit Card | W2: BrandD | Y2: AVERAGEA
A3: 10002 | B3: 1435 | C3: 45199 | D3: 45203 | E3: Pune | F3: Tamil Nadu | G3: Website | H3: Debit Card | I3: Sports | J3: Football | K3: BrandD | L3: 9 | M3: 2525.23 | N3: 5 | O3: 21590.72 | P3: =L3*M3 -> 22727.07 | T3: Marketplace | U3: Fashion | V3: Cash on Delivery | W3: BrandE
A4: 10003 | B4: 1860 | C4: 45109 | D4: 45114 | E4: Chennai | F4: West Bengal | G4: Marketplace | H4: Debit Card | I4: Fashion | J4: Sneakers | K4: BrandE | L4: 6 | M4: 3474.34 | N4: 15 | O4: 17719.13 | P4: =L4*M4 -> 20846.04 | U4: Electronics | V4: Net Banking | W4: BrandC | Y4: 5 | Z4: =AVERAGEA(Y4:Y12) -> 2.3333333
A5: 10004 | B5: 1270 | C5: 45079 | D5: 45087 | E5: Bengaluru | F5: West Bengal | G5: Website | H5: Cash on Delivery | I5: Sports | J5: Yoga Mat | K5: BrandA | L5: 1 | M5: 1008.79 | N5: 15 | O5: 857.47 | P5: =L5*M5 -> 1008.79 | U5: Beauty | V5: UPI | W5: BrandB | Y5: 9
A6: 10005 | B6: 1106 | C6: 45241 | D6: 45244 | E6: Kolkata | F6: Karnataka | G6: Marketplace | H6: Credit Card | I6: Fashion | J6: Jacket | K6: BrandA | L6: 7 | M6: 3511.47 | N6: 20 | O6: 19664.23 | P6: =L6*M6 -> 24580.29 | Q6: SUMIF | U6: Books | Y6: 2
A7: 10006 | B7: 1071 | C7: 45260 | D7: 45263 | E7: Hyderabad | F7: Telangana | G7: Website | H7: Net Banking | I7: Home & Kitchen | J7: Bedsheet | K7: BrandE | L7: 3 | M7: 3189.55 | N7: 10 | O7: 8611.78 | P7: =L7*M7 -> 9568.65 | Q7: Product Category | Y7: K
A8: 10007 | B8: 1700 | C8: 45050 | D8: 45054 | E8: Bengaluru | F8: Telangana | G8: Mobile App | H8: UPI | I8: Fashion | J8: Sneakers | K8: BrandC | L8: 5 | M8: 3030.42 | N8: 10 | O8: 13636.89 | P8: =L8*M8 -> 15152.1 | Q8: Sports | R8: =SUMIF(I2:I501,Q8,L2:L501) -> 377 | Y8: G
A9: 10008 | B9: 1020 | C9: 45040 | D9: 45041 | E9: Mumbai | F9: Delhi | G9: Website | H9: Credit Card | I9: Fashion | J9: Sneakers | K9: BrandB | L9: 4 | M9: 2310.83 | N9: 10 | O9: 8318.99 | P9: =L9*M9 -> 9243.32 | Y9: 5
A10: 10009 | B10: 1614 | C10: 45204 | D10: 45213 | E10: Chennai | F10: West Bengal | G10: Website | H10: Debit Card | I10: Fashion | J10: T-Shirt | K10: BrandD | L10: 5 | M10: 1098.04 | N10: 15 | O10: 4666.67 | P10: =L10*M10 -> 5490.2 | Q10: Sales Channel | R10: Net Sales | Y10: @
A11: 10010 | B11: 1121 | C11: 45139 | D11: 45147 | E11: Bengaluru | F11: Karnataka | G11: Website | H11: Cash on Delivery | I11: Electronics | J11: Headphones | K11: BrandB | L11: 5 | M11: 1780.66 | N11: 20 | O11: 7122.64 | P11: =L11*M11 -> 8903.3 | Q11: Mobile App | R11: =SUMIF(G2:G501,Q11,O2:O501) -> 1576040.5 | Y11: 0
A12: 10011 | B12: 1466 | C12: 45098 | D12: 45106 | E12: Bengaluru | F12: Karnataka | G12: Mobile App | H12: Cash on Delivery | I12: Electronics | J12: Headphones | K12: BrandE | L12: 6 | M12: 3205.25 | N12: 0 | O12: 19231.5 | P12: =L12*M12 -> 19231.5 | Y12: *jk
A13: 10012 | B13: 1214 | C13: 45214 | D13: 45220 | E13: Mumbai | F13: Tamil Nadu | G13: Website | H13: UPI | I13: Electronics | J13: Smartwatch | K13: BrandA | L13: 6 | M13: 272.35 | N13: 5 | O13: 1552.39 | P13: =L13*M13 -> 1634.1
A14: 10013 | B14: 1330 | C14: 45100 | D14: 45107 | E14: Delhi | F14: Tamil Nadu | G14: Mobile App | H14: Cash on Delivery | I14: Home & Kitchen | J14: Bedsheet | K14: BrandA | L14: 8 | M14: 3160.9 | N14: 0 | O14: 25287.2 | P14: =L14*M14 -> 25287.2
A15: 10014 | B15: 1458 | C15: 45039 | D15: 45045 | E15: Kolkata | F15: Karnataka | G15: Marketplace | H15: Cash on Delivery | I15: Sports | J15: Yoga Mat | K15: BrandD | L15: 8 | M15: 1074.27 | N15: 15 | O15: 7305.04 | P15: =L15*M15 -> 8594.16 | Q15: SUMIFS
A16: 10015 | B16: 1087 | C16: 45048 | D16: 45057 | E16: Hyderabad | F16: Tamil Nadu | G16: Website | H16: Credit Card | I16: Beauty | J16: Shampoo | K16: BrandA | L16: 9 | M16: 705.59 | N16: 10 | O16: 5715.28 | P16: =L16*M16 -> 6350.31
A17: 10016 | B17: 1372 | C17: 44958 | D17: 44961 | E17: Pune | F17: West Bengal | G17: Mobile App | H17: Net Banking | I17: Fashion | J17: Jacket | K17: BrandA | L17: 8 | M17: 595.45 | N17: 5 | O17: 4525.42 | P17: =L17*M17 -> 4763.6 | Q17: Sales Channel | R17: Product Category | S17: Total Units Sold(SUMIFS)
A18: 10017 | B18: 1099 | C18: 45148 | D18: 45151 | E18: Delhi | F18: Maharashtra | G18: Mobile App | H18: UPI | I18: Fashion | J18: Jacket | K18: BrandD | L18: 2 | M18: 254.91 | N18: 15 | O18: 433.35 | P18: =L18*M18 -> 509.82 | Q18: Website | R18: Electronics | S18: =SUMIFS(L2:L501,G2:G501,Q18,I2:I501,R18) -> 206
A19: 10018 | B19: 1871 | C19: 45045 | D19: 45048 | E19: Chennai | F19: West Bengal | G19: Website | H19: Credit Card | I19: Home & Kitchen | J19: Curtains | K19: BrandD | L19: 1 | M19: 2165.81 | N19: 15 | O19: 1840.94 | P19: =L19*M19 -> 2165.81
A20: 10019 | B20: 1663 | C20: 44965 | D20: 44968 | E20: Bengaluru | F20: Karnataka | G20: Marketplace | H20: Net Banking | I20: Fashion | J20: Jacket | K20: BrandE | L20: 2 | M20: 990.3 | N20: 15 | O20: 1683.51 | P20: =L20*M20 -> 1980.6 | Q20: Payment Method | R20: Brand | S20: Net Sales
A21: 10020 | B21: 1130 | C21: 45194 | D21: 45203 | E21: Mumbai | F21: Karnataka | G21: Mobile App | H21: Credit Card | I21: Electronics | J21: Smartwatch | K21: BrandA | L21: 2 | M21: 3959.31 | N21: 5 | O21: 7522.69 | P21: =L21*M21 -> 7918.62 | Q21: Net Banking | R21: BrandE | S21: =SUMIFS(O2:O501,H2:H501,Q21,K2:K501,R21) -> 163401.52
A22: 10021 | B22: 1661 | C22: 45159 | D22: 45163 | E22: Mumbai | F22: West Bengal | G22: Website | H22: Credit Card | I22: Beauty | J22: Lipstick | K22: BrandA | L22: 3 | M22: 2361.58 | N22: 5 | O22: 6730.5 | P22: =L22*M22 -> 7084.74
A23: 10022 | B23: 1308 | C23: 44944 | D23: 44951 | E23: Kolkata | F23: Tamil Nadu | G23: Marketplace | H23: Cash on Delivery | I23: Books | J23: Fiction Novel | K23: BrandE | L23: 7 | M23: 680.86 | N23: 20 | O23: 3812.82 | P23: =L23*M23 -> 4766.02 | Q23: Grand Total | R23: =SUM(P2:P501) -> 5134263.8
A24: 10023 | B24: 1769 | C24: 45075 | D24: 45084 | E24: Delhi | F24: Tamil Nadu | G24: Mobile App | H24: Net Banking | I24: Fashion | J24: Sneakers | K24: BrandC | L24: 2 | M24: 2801.74 | N24: 20 | O24: 4482.78 | P24: =L24*M24 -> 5603.48
A25: 10024 | B25: 1343 | C25: 45075 | D25: 45082 | E25: Pune | F25: Telangana | G25: Mobile App | H25: UPI | I25: Electronics | J25: Smartwatch | K25: BrandC | L25: 1 | M25: 3606.31 | N25: 0 | O25: 3606.31 | P25: =L25*M25 -> 3606.31 | Q25: Using ARRAY
A26: 10025 | B26: 1491 | C26: 45052 | D26: 45061 | E26: Kolkata | F26: Karnataka | G26: Marketplace | H26: UPI | I26: Books | J26: Comics | K26: BrandC | L26: 6 | M26: 3018.94 | N26: 5 | O26: 17207.96 | P26: =L26*M26 -> 18113.64 | Q26: Grand Total | R26: =SUMPRODUCT(L2:L501,M2:M501) -> 5134263.8
A27: 10026 | B27: 1413 | C27: 45228 | D27: 45231 | E27: Bengaluru | F27: Delhi | G27: Marketplace | H27: Net Banking | I27: Beauty | J27: Perfume | K27: BrandE | L27: 9 | M27: 444.29 | N27: 5 | O27: 3798.68 | P27: =L27*M27 -> 3998.61 | Q27: Total Discount Amount | R27: =SUMPRODUCT(L2:L501,M2:M501,N2:N501)/100 -> 519774.77
A28: 10027 | B28: 1805 | C28: 45286 | D28: 45290 | E28: Kolkata | F28: Telangana | G28: Website | H28: Cash on Delivery | I28: Books | J28: Fiction Novel | K28: BrandA | L28: 3 | M28: 3599.15 | N28: 5 | O28: 10257.58 | P28: =L28*M28 -> 10797.45 | Q28: Using AVERAGEIF
A29: 10028 | B29: 1385 | C29: 45164 | D29: 45172 | E29: Hyderabad | F29: Tamil Nadu | G29: Website | H29: Debit Card | I29: Electronics | J29: Smartwatch | K29: BrandE | L29: 6 | M29: 3206.63 | N29: 20 | O29: 15391.82 | P29: =L29*M29 -> 19239.78 | Q29: Brand | R29: Avg. Net Sales
A30: 10029 | B30: 1191 | C30: 45061 | D30: 45067 | E30: Mumbai | F30: West Bengal | G30: Mobile App | H30: Credit Card | I30: Sports | J30: Football | K30: BrandE | L30: 3 | M30: 759.47 | N30: 15 | O30: 1936.65 | P30: =L30*M30 -> 2278.41 | Q30: BrandB | R30: =AVERAGEIF(K2:K501,Q30,O2:O501) -> 9778.0083
A31: 10030 | B31: 1955 | C31: 45077 | D31: 45082 | E31: Mumbai | F31: Tamil Nadu | G31: Marketplace | H31: Cash on Delivery | I31: Sports | J31: Cricket Bat | K31: BrandC | L31: 1 | M31: 349.38 | N31: 10 | O31: 314.44 | P31: =L31*M31 -> 349.38
A32: 10031 | B32: 1276 | C32: 45162 | D32: 45166 | E32: Chennai | F32: West Bengal | G32: Marketplace | H32: Net Banking | I32: Books | J32: Textbook | K32: BrandB | L32: 5 | M32: 2295.65 | N32: 20 | O32: 9182.6 | P32: =L32*M32 -> 11478.25 | Q32: Using AVERAGEIFS
A33: 10032 | B33: 1160 | C33: 45150 | D33: 45158 | E33: Chennai | F33: Telangana | G33: Marketplace | H33: Credit Card | I33: Home & Kitchen | J33: Bedsheet | K33: BrandA | L33: 4 | M33: 750.74 | N33: 5 | O33: 2852.81 | P33: =L33*M33 -> 3002.96 | Q33: Brand | R33: Sales Channel | S33: Avg. Net Sales
A34: 10033 | B34: 1459 | C34: 45129 | D34: 45130 | E34: Pune | F34: Karnataka | G34: Mobile App | H34: UPI | I34: Books | J34: Comics | K34: BrandC | L34: 7 | M34: 3363.18 | N34: 20 | O34: 18833.81 | P34: =L34*M34 -> 23542.26 | Q34: BrandC | R34: Website | S34: =AVERAGEIFS(O2:O501,K2:K501,Q34,G2:G501,R34) -> 7414.8813
A35: 10034 | B35: 1313 | C35: 45182 | D35: 45191 | E35: Bengaluru | F35: Tamil Nadu | G35: Marketplace | H35: Debit Card | I35: Fashion | J35: T-Shirt | K35: BrandB | L35: 6 | M35: 1529.59 | N35: 0 | O35: 9177.54 | P35: =L35*M35 -> 9177.54
A36: 10035 | B36: 1021 | C36: 45012 | D36: 45013 | E36: Hyderabad | F36: West Bengal | G36: Marketplace | H36: UPI | I36: Fashion | J36: T-Shirt | K36: BrandB | L36: 7 | M36: 3664.64 | N36: 5 | O36: 24369.86 | P36: =L36*M36 -> 25652.48
A37: 10036 | B37: 1252 | C37: 45076 | D37: 45084 | E37: Delhi | F37: Karnataka | G37: Mobile App | H37: Net Banking | I37: Sports | J37: Football | K37: BrandD | L37: 5 | M37: 2327.9 | N37: 0 | O37: 11639.5 | P37: =L37*M37 -> 11639.5
A38: 10037 | B38: 1747 | C38: 45161 | D38: 45165 | E38: Kolkata | F38: Delhi | G38: Website | H38: Credit Card | I38: Home & Kitchen | J38: Curtains | K38: BrandA | L38: 4 | M38: 853.29 | N38: 5 | O38: 3242.5 | P38: =L38*M38 -> 3413.16
A39: 10038 | B39: 1856 | C39: 45271 | D39: 45280 | E39: Pune | F39: West Bengal | G39: Website | H39: Net Banking | I39: Electronics | J39: Laptop | K39: BrandB | L39: 7 | M39: 687.46 | N39: 20 | O39: 3849.78 | P39: =L39*M39 -> 4812.22
A40: 10039 | B40: 1560 | C40: 44948 | D40: 44953 | E40: Bengaluru | F40: Telangana | G40: Mobile App | H40: Credit Card | I40: Fashion | J40: T-Shirt | K40: BrandC | L40: 7 | M40: 2369.42 | N40: 15 | O40: 14098.05 | P40: =L40*M40 -> 16585.94
A41: 10040 | B41: 1474 | C41: 45274 | D41: 45277 | E41: Chennai | F41: Delhi | G41: Marketplace | H41: Cash on Delivery | I41: Sports | J41: Football | K41: BrandD | L41: 6 | M41: 3083.25 | N41: 10 | O41: 16649.55 | P41: =L41*M41 -> 18499.5
A42: 10041 | B42: 1058 | C42: 45211 | D42: 45220 | E42: Kolkata | F42: Delhi | G42: Mobile App | H42: Debit Card | I42: Beauty | J42: Face Cream | K42: BrandA | L42: 8 | M42: 3158.8 | N42: 0 | O42: 25270.4 | P42: =L42*M42 -> 25270.4
A43: 10042 | B43: 1510 | C43: 45195 | D43: 45204 | E43: Chennai | F43: Maharashtra | G43: Website | H43: Cash on Delivery | I43: Sports | J43: Football | K43: BrandE | L43: 4 | M43: 1211.67 | N43: 20 | O43: 3877.34 | P43: =L43*M43 -> 4846.68
A44: 10043 | B44: 1681 | C44: 45184 | D44: 45188 | E44: Kolkata | F44: Tamil Nadu | G44: Website | H44: Cash on Delivery | I44: Fashion | J44: T-Shirt | K44: BrandC | L44: 5 | M44: 936.35 | N44: 15 | O44: 3979.49 | P44: =L44*M44 -> 4681.75
A45: 10044 | B45: 1475 | C45: 44955 | D45: 44959 | E45: Delhi | F45: West Bengal | G45: Mobile App | H45: Net Banking | I45: Fashion | J45: T-Shirt | K45: BrandB | L45: 4 | M45: 214.51 | N45: 20 | O45: 686.43 | P45: =L45*M45 -> 858.04
A46: 10045 | B46: 1699 | C46: 45139 | D46: 45147 | E46: Bengaluru | F46: Delhi | G46: Mobile App | H46: Debit Card | I46: Sports | J46: Cricket Bat | K46: BrandB | L46: 1 | M46: 2764.92 | N46: 0 | O46: 2764.92 | P46: =L46*M46 -> 2764.92
... A501: 10500 | B501: 1569 | C501: 44972 | D501: 44977 | E501: Chennai | F501: Delhi | G501: Marketplace | H501: Net Banking | I501: Fashion | J501: Jeans | K501: BrandE | L501: 1 | M501: 2432.17 | N501: 20 | O501: 1945.74 | P501: =L501*M501 -> 2432.17

Sheet Day3 30.09.2026
A1: Order ID | B1: Customer ID | C1: Order Date | D1: Ship Date | E1: City | F1: State | G1: Sales Channel | H1: Payment Method | I1: Product Category | J1: Product Name | K1: Brand | L1: Units Sold | M1: Unit Price | N1: Discount % | O1: Net Sales | P1: Total Price | R1: High Value Order | S1: Bulk Order | U1: Priority Channel | W1: Sales Status | Y1: Website Order | AA1: Website Order | AD1: Category | AF1: Order Type
A2: 10001 | B2: 1102 | C2: 45197 | D2: 45203 | E2: Chennai | F2: Delhi | G2: Mobile App | H2: Credit Card | I2: Home & Kitchen | J2: Mixer Grinder | K2: BrandA | L2: 7 | M2: 2843.87 | N2: 0 | O2: 19907.09 | P2: =L2*M2 -> 19907.09 | R2: =IF(AND(L2>5,O2>10000),"YES","NO") -> YES | S2: =IF(AND(L2>=8,N2>=10),"YES","NO") -> NO | U2: =IF(OR(G2="Mobile App",G2="Website"),"YES","NO") -> YES | W2: =IF(AND(L2<3,O2<=1000),"Special Attention","No") -> No | Y2: =IF(NOT(G2="Website"),"No","yes") -> No | AA2: =IF(G2<>"Website","No","Yes") -> No | AD2: =IF(AND(O2>15000,OR(I2="Electronics",I2="Beauty")),"Premium","Regular") -> Regular | AF2: =IF(AND(L2>=8,N2<>0),"Non Disc","Discounted") -> Discounted
A3: 10002 | B3: 1435 | C3: 45199 | D3: 45203 | E3: Pune | F3: Tamil Nadu | G3: Website | H3: Debit Card | I3: Sports | J3: Football | K3: BrandD | L3: 9 | M3: 2525.23 | N3: 5 | O3: 21590.72 | P3: =L3*M3 -> 22727.07 | R3: =IF(AND(L3>5,O3>10000),"YES","NO") -> YES | S3: =IF(AND(L3>=8,N3>=10),"YES","NO") -> NO | U3: =IF(OR(G3="Mobile App",G3="Website"),"YES","NO") -> YES | W3: =IF(AND(L3<3,O3<=1000),"Special Attention","No") -> No | Y3: =IF(NOT(G3="Website"),"No","yes") -> yes | AA3: =IF(G3<>"Website","No","Yes") -> Yes | AD3: =IF(AND(O3>15000,OR(I3="Electronics",I3="Beauty")),"Premium","Regular") -> Regular | AF3: =IF(AND(L3>=8,N3<>0),"Non Disc","Discounted") -> Non Disc
A4: 10003 | B4: 1860 | C4: 45109 | D4: 45114 | E4: Chennai | F4: West Bengal | G4: Marketplace | H4: Debit Card | I4: Fashion | J4: Sneakers | K4: BrandE | L4: 6 | M4: 3474.34 | N4: 15 | O4: 17719.13 | P4: =L4*M4 -> 20846.04 | R4: =IF(AND(L4>5,O4>10000),"YES","NO") -> YES | S4: =IF(AND(L4>=8,N4>=10),"YES","NO") -> NO | U4: =IF(OR(G4="Mobile App",G4="Website"),"YES","NO") -> NO | W4: =IF(AND(L4<3,O4<=1000),"Special Attention","No") -> No | Y4: =IF(NOT(G4="Website"),"No","yes") -> No | AA4: =IF(G4<>"Website","No","Yes") -> No | AD4: =IF(AND(O4>15000,OR(I4="Electronics",I4="Beauty")),"Premium","Regular") -> Regular | AF4: =IF(AND(L4>=8,N4<>0),"Non Disc","Discounted") -> Discounted
A5: 10004 | B5: 1270 | C5: 45079 | D5: 45087 | E5: Bengaluru | F5: West Bengal | G5: Website | H5: Cash on Delivery | I5: Sports | J5: Yoga Mat | K5: BrandA | L5: 1 | M5: 1008.79 | N5: 15 | O5: 857.47 | P5: =L5*M5 -> 1008.79 | R5: =IF(AND(L5>5,O5>10000),"YES","NO") -> NO | S5: =IF(AND(L5>=8,N5>=10),"YES","NO") -> NO | U5: =IF(OR(G5="Mobile App",G5="Website"),"YES","NO") -> YES | W5: =IF(AND(L5<3,O5<=1000),"Special Attention","No") -> Special Attention | Y5: =IF(NOT(G5="Website"),"No","yes") -> yes | AA5: =IF(G5<>"Website","No","Yes") -> Yes | AD5: =IF(AND(O5>15000,OR(I5="Electronics",I5="Beauty")),"Premium","Regular") -> Regular | AF5: =IF(AND(L5>=8,N5<>0),"Non Disc","Discounted") -> Discounted
A6: 10005 | B6: 1106 | C6: 45241 | D6: 45244 | E6: Kolkata | F6: Karnataka | G6: Marketplace | H6: Credit Card | I6: Fashion | J6: Jacket | K6: BrandA | L6: 7 | M6: 3511.47 | N6: 20 | O6: 19664.23 | P6: =L6*M6 -> 24580.29 | Q6: Uses of "AND" | R6: =IF(AND(L6>5,O6>10000),"YES","NO") -> YES | S6: =IF(AND(L6>=8,N6>=10),"YES","NO") -> NO | T6: Uses of "OR" | U6: =IF(OR(G6="Mobile App",G6="Website"),"YES","NO") -> NO | V6: Uses of "AND" | W6: =IF(AND(L6<3,O6<=1000),"Special Attention","No") -> No | X6: Uses of "NOT" | Y6: =IF(NOT(G6="Website"),"No","yes") -> No | Z6: Uses of "<>" | AA6: =IF(G6<>"Website","No","Yes") -> No | AB6: Uses of "AND","OR" | AD6: =IF(AND(O6>15000,OR(I6="Electronics",I6="Beauty")),"Premium","Regular") -> Regular | AE6: Uses of "AND","OR" | AF6: =IF(AND(L6>=8,N6<>0),"Non Disc","Discounted") -> Discounted
A7: 10006 | B7: 1071 | C7: 45260 | D7: 45263 | E7: Hyderabad | F7: Telangana | G7: Website | H7: Net Banking | I7: Home & Kitchen | J7: Bedsheet | K7: BrandE | L7: 3 | M7: 3189.55 | N7: 10 | O7: 8611.78 | P7: =L7*M7 -> 9568.65 | R7: =IF(AND(L7>5,O7>10000),"YES","NO") -> NO | S7: =IF(AND(L7>=8,N7>=10),"YES","NO") -> NO | U7: =IF(OR(G7="Mobile App",G7="Website"),"YES","NO") -> YES | W7: =IF(AND(L7<3,O7<=1000),"Special Attention","No") -> No | Y7: =IF(NOT(G7="Website"),"No","yes") -> yes | AA7: =IF(G7<>"Website","No","Yes") -> Yes | AD7: =IF(AND(O7>15000,OR(I7="Electronics",I7="Beauty")),"Premium","Regular") -> Regular | AF7: =IF(AND(L7>=8,N7<>0),"Non Disc","Discounted") -> Discounted
A8: 10007 | B8: 1700 | C8: 45050 | D8: 45054 | E8: Bengaluru | F8: Telangana | G8: Mobile App | H8: UPI | I8: Fashion | J8: Sneakers | K8: BrandC | L8: 5 | M8: 3030.42 | N8: 10 | O8: 13636.89 | P8: =L8*M8 -> 15152.1 | R8: =IF(AND(L8>5,O8>10000),"YES","NO") -> NO | S8: =IF(AND(L8>=8,N8>=10),"YES","NO") -> NO | U8: =IF(OR(G8="Mobile App",G8="Website"),"YES","NO") -> YES | W8: =IF(AND(L8<3,O8<=1000),"Special Attention","No") -> No | Y8: =IF(NOT(G8="Website"),"No","yes") -> No | AA8: =IF(G8<>"Website","No","Yes") -> No | AD8: =IF(AND(O8>15000,OR(I8="Electronics",I8="Beauty")),"Premium","Regular") -> Regular | AF8: =IF(AND(L8>=8,N8<>0),"Non Disc","Discounted") -> Discounted
A9: 10008 | B9: 1020 | C9: 45040 | D9: 45041 | E9: Mumbai | F9: Delhi | G9: Website | H9: Credit Card | I9: Fashion | J9: Sneakers | K9: BrandB | L9: 4 | M9: 2310.83 | N9: 10 | O9: 8318.99 | P9: =L9*M9 -> 9243.32 | R9: =IF(AND(L9>5,O9>10000),"YES","NO") -> NO | S9: =IF(AND(L9>=8,N9>=10),"YES","NO") -> NO | U9: =IF(OR(G9="Mobile App",G9="Website"),"YES","NO") -> YES | W9: =IF(AND(L9<3,O9<=1000),"Special Attention","No") -> No | Y9: =IF(NOT(G9="Website"),"No","yes") -> yes | AA9: =IF(G9<>"Website","No","Yes") -> Yes | AD9: =IF(AND(O9>15000,OR(I9="Electronics",I9="Beauty")),"Premium","Regular") -> Regular | AF9: =IF(AND(L9>=8,N9<>0),"Non Disc","Discounted") -> Discounted
A10: 10009 | B10: 1614 | C10: 45204 | D10: 45213 | E10: Chennai | F10: West Bengal | G10: Website | H10: Debit Card | I10: Fashion | J10: T-Shirt | K10: BrandD | L10: 5 | M10: 1098.04 | N10: 15 | O10: 4666.67 | P10: =L10*M10 -> 5490.2 | R10: =IF(AND(L10>5,O10>10000),"YES","NO") -> NO | S10: =IF(AND(L10>=8,N10>=10),"YES","NO") -> NO | U10: =IF(OR(G10="Mobile App",G10="Website"),"YES","NO") -> YES | W10: =IF(AND(L10<3,O10<=1000),"Special Attention","No") -> No | Y10: =IF(NOT(G10="Website"),"No","yes") -> yes | AA10: =IF(G10<>"Website","No","Yes") -> Yes | AD10: =IF(AND(O10>15000,OR(I10="Electronics",I10="Beauty")),"Premium","Regular") -> Regular | AF10: =IF(AND(L10>=8,N10<>0),"Non Disc","Discounted") -> Discounted
A11: 10010 | B11: 1121 | C11: 45139 | D11: 45147 | E11: Bengaluru | F11: Karnataka | G11: Website | H11: Cash on Delivery | I11: Electronics | J11: Headphones | K11: BrandB | L11: 5 | M11: 1780.66 | N11: 20 | O11: 7122.64 | P11: =L11*M11 -> 8903.3 | R11: =IF(AND(L11>5,O11>10000),"YES","NO") -> NO | S11: =IF(AND(L11>=8,N11>=10),"YES","NO") -> NO | U11: =IF(OR(G11="Mobile App",G11="Website"),"YES","NO") -> YES | W11: =IF(AND(L11<3,O11<=1000),"Special Attention","No") -> No | Y11: =IF(NOT(G11="Website"),"No","yes") -> yes | AA11: =IF(G11<>"Website","No","Yes") -> Yes | AD11: =IF(AND(O11>15000,OR(I11="Electronics",I11="Beauty")),"Premium","Regular") -> Regular | AF11: =IF(AND(L11>=8,N11<>0),"Non Disc","Discounted") -> Discounted
A12: 10011 | B12: 1466 | C12: 45098 | D12: 45106 | E12: Bengaluru | F12: Karnataka | G12: Mobile App | H12: Cash on Delivery | I12: Electronics | J12: Headphones | K12: BrandE | L12: 6 | M12: 3205.25 | N12: 0 | O12: 19231.5 | P12: =L12*M12 -> 19231.5 | R12: =IF(AND(L12>5,O12>10000),"YES","NO") -> YES | S12: =IF(AND(L12>=8,N12>=10),"YES","NO") -> NO | U12: =IF(OR(G12="Mobile App",G12="Website"),"YES","NO") -> YES | W12: =IF(AND(L12<3,O12<=1000),"Special Attention","No") -> No | Y12: =IF(NOT(G12="Website"),"No","yes") -> No | AA12: =IF(G12<>"Website","No","Yes") -> No | AD12: =IF(AND(O12>15000,OR(I12="Electronics",I12="Beauty")),"Premium","Regular") -> Premium | AF12: =IF(AND(L12>=8,N12<>0),"Non Disc","Discounted") -> Discounted
A13: 10012 | B13: 1214 | C13: 45214 | D13: 45220 | E13: Mumbai | F13: Tamil Nadu | G13: Website | H13: UPI | I13: Electronics | J13: Smartwatch | K13: BrandA | L13: 6 | M13: 272.35 | N13: 5 | O13: 1552.39 | P13: =L13*M13 -> 1634.1 | R13: =IF(AND(L13>5,O13>10000),"YES","NO") -> NO | S13: =IF(AND(L13>=8,N13>=10),"YES","NO") -> NO | U13: =IF(OR(G13="Mobile App",G13="Website"),"YES","NO") -> YES | W13: =IF(AND(L13<3,O13<=1000),"Special Attention","No") -> No | Y13: =IF(NOT(G13="Website"),"No","yes") -> yes | AA13: =IF(G13<>"Website","No","Yes") -> Yes | AD13: =IF(AND(O13>15000,OR(I13="Electronics",I13="Beauty")),"Premium","Regular") -> Regular | AF13: =IF(AND(L13>=8,N13<>0),"Non Disc","Discounted") -> Discounted
A14: 10013 | B14: 1330 | C14: 45100 | D14: 45107 | E14: Delhi | F14: Tamil Nadu | G14: Mobile App | H14: Cash on Delivery | I14: Home & Kitchen | J14: Bedsheet | K14: BrandA | L14: 8 | M14: 3160.9 | N14: 0 | O14: 25287.2 | P14: =L14*M14 -> 25287.2 | R14: =IF(AND(L14>5,O14>10000),"YES","NO") -> YES | S14: =IF(AND(L14>=8,N14>=10),"YES","NO") -> NO | U14: =IF(OR(G14="Mobile App",G14="Website"),"YES","NO") -> YES | W14: =IF(AND(L14<3,O14<=1000),"Special Attention","No") -> No | Y14: =IF(NOT(G14="Website"),"No","yes") -> No | AA14: =IF(G14<>"Website","No","Yes") -> No | AD14: =IF(AND(O14>15000,OR(I14="Electronics",I14="Beauty")),"Premium","Regular") -> Regular | AF14: =IF(AND(L14>=8,N14<>0),"Non Disc","Discounted") -> Discounted
A15: 10014 | B15: 1458 | C15: 45039 | D15: 45045 | E15: Kolkata | F15: Karnataka | G15: Marketplace | H15: Cash on Delivery | I15: Sports | J15: Yoga Mat | K15: BrandD | L15: 8 | M15: 1074.27 | N15: 15 | O15: 7305.04 | P15: =L15*M15 -> 8594.16 | R15: =IF(AND(L15>5,O15>10000),"YES","NO") -> NO | S15: =IF(AND(L15>=8,N15>=10),"YES","NO") -> YES | U15: =IF(OR(G15="Mobile App",G15="Website"),"YES","NO") -> NO | W15: =IF(AND(L15<3,O15<=1000),"Special Attention","No") -> No | Y15: =IF(NOT(G15="Website"),"No","yes") -> No | AA15: =IF(G15<>"Website","No","Yes") -> No | AD15: =IF(AND(O15>15000,OR(I15="Electronics",I15="Beauty")),"Premium","Regular") -> Regular | AF15: =IF(AND(L15>=8,N15<>0),"Non Disc","Discounted") -> Non Disc
A16: 10015 | B16: 1087 | C16: 45048 | D16: 45057 | E16: Hyderabad | F16: Tamil Nadu | G16: Website | H16: Credit Card | I16: Beauty | J16: Shampoo | K16: BrandA | L16: 9 | M16: 705.59 | N16: 10 | O16: 5715.28 | P16: =L16*M16 -> 6350.31 | R16: =IF(AND(L16>5,O16>10000),"YES","NO") -> NO | S16: =IF(AND(L16>=8,N16>=10),"YES","NO") -> YES | U16: =IF(OR(G16="Mobile App",G16="Website"),"YES","NO") -> YES | W16: =IF(AND(L16<3,O16<=1000),"Special Attention","No") -> No | Y16: =IF(NOT(G16="Website"),"No","yes") -> yes | AA16: =IF(G16<>"Website","No","Yes") -> Yes | AD16: =IF(AND(O16>15000,OR(I16="Electronics",I16="Beauty")),"Premium","Regular") -> Regular | AF16: =IF(AND(L16>=8,N16<>0),"Non Disc","Discounted") -> Non Disc
A17: 10016 | B17: 1372 | C17: 44958 | D17: 44961 | E17: Pune | F17: West Bengal | G17: Mobile App | H17: Net Banking | I17: Fashion | J17: Jacket | K17: BrandA | L17: 8 | M17: 595.45 | N17: 5 | O17: 4525.42 | P17: =L17*M17 -> 4763.6 | R17: =IF(AND(L17>5,O17>10000),"YES","NO") -> NO | S17: =IF(AND(L17>=8,N17>=10),"YES","NO") -> NO | U17: =IF(OR(G17="Mobile App",G17="Website"),"YES","NO") -> YES | W17: =IF(AND(L17<3,O17<=1000),"Special Attention","No") -> No | Y17: =IF(NOT(G17="Website"),"No","yes") -> No | AA17: =IF(G17<>"Website","No","Yes") -> No | AD17: =IF(AND(O17>15000,OR(I17="Electronics",I17="Beauty")),"Premium","Regular") -> Regular | AF17: =IF(AND(L17>=8,N17<>0),"Non Disc","Discounted") -> Non Disc
A18: 10017 | B18: 1099 | C18: 45148 | D18: 45151 | E18: Delhi | F18: Maharashtra | G18: Mobile App | H18: UPI | I18: Fashion | J18: Jacket | K18: BrandD | L18: 2 | M18: 254.91 | N18: 15 | O18: 433.35 | P18: =L18*M18 -> 509.82 | R18: =IF(AND(L18>5,O18>10000),"YES","NO") -> NO | S18: =IF(AND(L18>=8,N18>=10),"YES","NO") -> NO | U18: =IF(OR(G18="Mobile App",G18="Website"),"YES","NO") -> YES | W18: =IF(AND(L18<3,O18<=1000),"Special Attention","No") -> Special Attention | Y18: =IF(NOT(G18="Website"),"No","yes") -> No | AA18: =IF(G18<>"Website","No","Yes") -> No | AD18: =IF(AND(O18>15000,OR(I18="Electronics",I18="Beauty")),"Premium","Regular") -> Regular | AF18: =IF(AND(L18>=8,N18<>0),"Non Disc","Discounted") -> Discounted
... A501: 10500 | B501: 1569 | C501: 44972 | D501: 44977 | E501: Chennai | F501: Delhi | G501: Marketplace | H501: Net Banking | I501: Fashion | J501: Jeans | K501: BrandE | L501: 1 | M501: 2432.17 | N501: 20 | O501: 1945.74 | P501: =L501*M501 -> 2432.17 | R501: =IF(AND(L501>5,O501>10000),"YES","NO") -> NO | S501: =IF(AND(L501>=8,N501>=10),"YES","NO") -> NO | U501: =IF(OR(G501="Mobile App",G501="Website"),"YES","NO") -> NO | W501: =IF(AND(L501<3,O501<=1000),"Special Attention","No") -> No | Y501: =IF(NOT(G501="Website"),"No","yes") -> No | AA501: =IF(G501<>"Website","No","Yes") -> No | AD501: =IF(AND(O501>15000,OR(I501="Electronics",I501="Beauty")),"Premium","Regular") -> Regular | AF501: =IF(AND(L501>=8,N501<>0),"Non Disc","Discounted") -> Discounted

Sheet Day4 01.10.2026 s&f
A1: Order ID | B1: Customer ID | C1: Order Date | D1: Ship Date | E1: City | F1: State | G1: Sales Channel | H1: Payment Method | I1: Product Category | J1: Product Name | K1: Brand | L1: Units Sold | M1: Unit Price | N1: Discount % | O1: Net Sales | R1: City
A2: 10045 | B2: 1699 | C2: 45139 | D2: 45147 | E2: Bengaluru | F2: Delhi | G2: Mobile App | H2: Debit Card | I2: Sports | J2: Cricket Bat | K2: BrandB | L2: 1 | M2: 2764.92 | N2: 0 | O2: 2764.92 | R2: Bengaluru | U2: Order ID | V2: Customer ID | W2: Order Date | X2: Ship Date | Y2: City | Z2: State | AA2: Sales Channel | AB2: Payment Method | AC2: Product Category | AD2: Product Name | AE2: Brand | AF2: Units Sold | AG2: Unit Price | AH2: Discount % | AI2: Net Sales
A3: 10295 | B3: 1637 | C3: 45280 | D3: 45284 | E3: Bengaluru | F3: Tamil Nadu | G3: Website | H3: Net Banking | I3: Fashion | J3: T-Shirt | K3: BrandE | L3: 1 | M3: 619.73 | N3: 0 | O3: 619.73 | U3: 10045 | V3: 1699 | W3: 45139 | X3: 45147 | Y3: Bengaluru | Z3: Delhi | AA3: Mobile App | AB3: Debit Card | AC3: Sports | AD3: Cricket Bat | AE3: BrandB | AF3: 1 | AG3: 2764.92 | AH3: 0 | AI3: 2764.92
A4: 10004 | B4: 1270 | C4: 45079 | D4: 45087 | E4: Bengaluru | F4: West Bengal | G4: Website | H4: Cash on Delivery | I4: Sports | J4: Yoga Mat | K4: BrandA | L4: 1 | M4: 1008.79 | N4: 15 | O4: 857.47 | U4: 10295 | V4: 1637 | W4: 45280 | X4: 45284 | Y4: Bengaluru | Z4: Tamil Nadu | AA4: Website | AB4: Net Banking | AC4: Fashion | AD4: T-Shirt | AE4: BrandE | AF4: 1 | AG4: 619.73 | AH4: 0 | AI4: 619.73
A5: 10309 | B5: 1400 | C5: 44928 | D5: 44936 | E5: Bengaluru | F5: West Bengal | G5: Marketplace | H5: UPI | I5: Electronics | J5: Smartwatch | K5: BrandB | L5: 1 | M5: 2740.46 | N5: 10 | O5: 2466.41 | U5: 10004 | V5: 1270 | W5: 45079 | X5: 45087 | Y5: Bengaluru | Z5: West Bengal | AA5: Website | AB5: Cash on Delivery | AC5: Sports | AD5: Yoga Mat | AE5: BrandA | AF5: 1 | AG5: 1008.79 | AH5: 15 | AI5: 857.47
A6: 10345 | B6: 1935 | C6: 44984 | D6: 44993 | E6: Bengaluru | F6: West Bengal | G6: Marketplace | H6: Net Banking | I6: Sports | J6: Yoga Mat | K6: BrandC | L6: 1 | M6: 3625.42 | N6: 10 | O6: 3262.88 | U6: 10309 | V6: 1400 | W6: 44928 | X6: 44936 | Y6: Bengaluru | Z6: West Bengal | AA6: Marketplace | AB6: UPI | AC6: Electronics | AD6: Smartwatch | AE6: BrandB | AF6: 1 | AG6: 2740.46 | AH6: 10 | AI6: 2466.41
A7: 10019 | B7: 1663 | C7: 44965 | D7: 44968 | E7: Bengaluru | F7: Karnataka | G7: Marketplace | H7: Net Banking | I7: Fashion | J7: Jacket | K7: BrandE | L7: 2 | M7: 990.3 | N7: 15 | O7: 1683.51 | U7: 10345 | V7: 1935 | W7: 44984 | X7: 44993 | Y7: Bengaluru | Z7: West Bengal | AA7: Marketplace | AB7: Net Banking | AC7: Sports | AD7: Yoga Mat | AE7: BrandC | AF7: 1 | AG7: 3625.42 | AH7: 10 | AI7: 3262.88
A8: 10317 | B8: 1981 | C8: 45051 | D8: 45056 | E8: Bengaluru | F8: Karnataka | G8: Website | H8: Debit Card | I8: Electronics | J8: Laptop | K8: BrandB | L8: 2 | M8: 788.72 | N8: 20 | O8: 1261.95 | U8: 10019 | V8: 1663 | W8: 44965 | X8: 44968 | Y8: Bengaluru | Z8: Karnataka | AA8: Marketplace | AB8: Net Banking | AC8: Fashion | AD8: Jacket | AE8: BrandE | AF8: 2 | AG8: 990.3 | AH8: 15 | AI8: 1683.51
A9: 10331 | B9: 1763 | C9: 45203 | D9: 45207 | E9: Bengaluru | F9: Karnataka | G9: Mobile App | H9: Cash on Delivery | I9: Home & Kitchen | J9: Curtains | K9: BrandB | L9: 2 | M9: 2481.1 | N9: 15 | O9: 4217.87 | U9: 10317 | V9: 1981 | W9: 45051 | X9: 45056 | Y9: Bengaluru | Z9: Karnataka | AA9: Website | AB9: Debit Card | AC9: Electronics | AD9: Laptop | AE9: BrandB | AF9: 2 | AG9: 788.72 | AH9: 20 | AI9: 1261.95
A10: 10190 | B10: 1857 | C10: 45185 | D10: 45187 | E10: Bengaluru | F10: Maharashtra | G10: Marketplace | H10: Debit Card | I10: Electronics | J10: Smartwatch | K10: BrandA | L10: 2 | M10: 1372.59 | N10: 5 | O10: 2607.92 | U10: 10331 | V10: 1763 | W10: 45203 | X10: 45207 | Y10: Bengaluru | Z10: Karnataka | AA10: Mobile App | AB10: Cash on Delivery | AC10: Home & Kitchen | AD10: Curtains | AE10: BrandB | AF10: 2 | AG10: 2481.1 | AH10: 15 | AI10: 4217.87
A11: 10477 | B11: 1279 | C11: 45229 | D11: 45230 | E11: Bengaluru | F11: Maharashtra | G11: Marketplace | H11: UPI | I11: Fashion | J11: T-Shirt | K11: BrandC | L11: 2 | M11: 2962.4 | N11: 0 | O11: 5924.8 | U11: 10190 | V11: 1857 | W11: 45185 | X11: 45187 | Y11: Bengaluru | Z11: Maharashtra | AA11: Marketplace | AB11: Debit Card | AC11: Electronics | AD11: Smartwatch | AE11: BrandA | AF11: 2 | AG11: 1372.59 | AH11: 5 | AI11: 2607.92
A12: 10224 | B12: 1795 | C12: 45100 | D12: 45106 | E12: Bengaluru | F12: Tamil Nadu | G12: Marketplace | H12: Debit Card | I12: Books | J12: Fiction Novel | K12: BrandA | L12: 2 | M12: 1448.65 | N12: 20 | O12: 2317.84 | U12: 10477 | V12: 1279 | W12: 45229 | X12: 45230 | Y12: Bengaluru | Z12: Maharashtra | AA12: Marketplace | AB12: UPI | AC12: Fashion | AD12: T-Shirt | AE12: BrandC | AF12: 2 | AG12: 2962.4 | AH12: 0 | AI12: 5924.8
A13: 10194 | B13: 1690 | C13: 45180 | D13: 45182 | E13: Bengaluru | F13: Telangana | G13: Website | H13: Debit Card | I13: Books | J13: Comics | K13: BrandC | L13: 2 | M13: 894.01 | N13: 15 | O13: 1519.82 | U13: 10224 | V13: 1795 | W13: 45100 | X13: 45106 | Y13: Bengaluru | Z13: Tamil Nadu | AA13: Marketplace | AB13: Debit Card | AC13: Books | AD13: Fiction Novel | AE13: BrandA | AF13: 2 | AG13: 1448.65 | AH13: 20 | AI13: 2317.84
A14: 10239 | B14: 1384 | C14: 45146 | D14: 45149 | E14: Bengaluru | F14: Telangana | G14: Website | H14: Debit Card | I14: Electronics | J14: Laptop | K14: BrandB | L14: 2 | M14: 3960.56 | N14: 10 | O14: 7129.01 | U14: 10194 | V14: 1690 | W14: 45180 | X14: 45182 | Y14: Bengaluru | Z14: Telangana | AA14: Website | AB14: Debit Card | AC14: Books | AD14: Comics | AE14: BrandC | AF14: 2 | AG14: 894.01 | AH14: 15 | AI14: 1519.82
... A60: 10379 | B60: 1658 | C60: 45262 | D60: 45270 | E60: Chennai | F60: Delhi | G60: Website | H60: Cash on Delivery | I60: Sports | J60: Dumbbells | K60: BrandC | L60: 1 | M60: 3910.66 | N60: 5 | O60: 3715.13 | U60: 10353 | V60: 1952 | W60: 44968 | X60: 44972 | Y60: Bengaluru | Z60: West Bengal | AA60: Marketplace | AB60: UPI | AC60: Books | AD60: Biography | AE60: BrandE | AF60: 9 | AG60: 1375.31 | AH60: 15 | AI60: 10521.12
A61: 10500 | B61: 1569 | C61: 44972 | D61: 44977 | E61: Chennai | F61: Delhi | G61: Marketplace | H61: Net Banking | I61: Fashion | J61: Jeans | K61: BrandE | L61: 1 | M61: 2432.17 | N61: 20 | O61: 1945.74
A62: 10111 | B62: 1461 | C62: 44950 | D62: 44959 | E62: Chennai | F62: Maharashtra | G62: Marketplace | H62: Cash on Delivery | I62: Electronics | J62: Smartphone | K62: BrandE | L62: 1 | M62: 1820.02 | N62: 10 | O62: 1638.02
A63: 10130 | B63: 1156 | C63: 44929 | D63: 44938 | E63: Chennai | F63: Telangana | G63: Mobile App | H63: Net Banking | I63: Books | J63: Textbook | K63: BrandE | L63: 1 | M63: 2534.47 | N63: 5 | O63: 2407.75
A64: 10350 | B64: 1640 | C64: 45180 | D64: 45185 | E64: Chennai | F64: Telangana | G64: Mobile App | H64: UPI | I64: Books | J64: Textbook | K64: BrandA | L64: 1 | M64: 3708.38 | N64: 20 | O64: 2966.7
A65: 10018 | B65: 1871 | C65: 45045 | D65: 45048 | E65: Chennai | F65: West Bengal | G65: Website | H65: Credit Card | I65: Home & Kitchen | J65: Curtains | K65: BrandD | L65: 1 | M65: 2165.81 | N65: 15 | O65: 1840.94
A66: 10065 | B66: 1273 | C66: 45054 | D66: 45058 | E66: Chennai | F66: Karnataka | G66: Mobile App | H66: Net Banking | I66: Home & Kitchen | J66: Bedsheet | K66: BrandC | L66: 2 | M66: 2773.21 | N66: 10 | O66: 4991.78
A67: 10261 | B67: 1826 | C67: 44933 | D67: 44936 | E67: Chennai | F67: Maharashtra | G67: Website | H67: Debit Card | I67: Fashion | J67: Sneakers | K67: BrandE | L67: 2 | M67: 533.25 | N67: 0 | O67: 1066.5
A68: 10285 | B68: 1001 | C68: 45104 | D68: 45109 | E68: Chennai | F68: Tamil Nadu | G68: Mobile App | H68: UPI | I68: Beauty | J68: Lipstick | K68: BrandA | L68: 2 | M68: 702.07 | N68: 10 | O68: 1263.73
A69: 10332 | B69: 1954 | C69: 44946 | D69: 44955 | E69: Chennai | F69: Tamil Nadu | G69: Mobile App | H69: Net Banking | I69: Books | J69: Biography | K69: BrandA | L69: 2 | M69: 1335.36 | N69: 5 | O69: 2537.18
A70: 10386 | B70: 1119 | C70: 45146 | D70: 45154 | E70: Chennai | F70: Tamil Nadu | G70: Website | H70: UPI | I70: Electronics | J70: Smartphone | K70: BrandD | L70: 2 | M70: 1984.38 | N70: 10 | O70: 3571.88
A71: 10108 | B71: 1815 | C71: 45037 | D71: 45045 | E71: Chennai | F71: West Bengal | G71: Website | H71: Credit Card | I71: Sports | J71: Yoga Mat | K71: BrandA | L71: 2 | M71: 564.31 | N71: 15 | O71: 959.33
A72: 10192 | B72: 1891 | C72: 45039 | D72: 45042 | E72: Chennai | F72: West Bengal | G72: Marketplace | H72: Cash on Delivery | I72: Beauty | J72: Perfume | K72: BrandA | L72: 2 | M72: 487.23 | N72: 15 | O72: 828.29
... A501: 10407 | B501: 1877 | C501: 45088 | D501: 45090 | E501: Pune | F501: Tamil Nadu | G501: Website | H501: Debit Card | I501: Beauty | J501: Shampoo | K501: BrandE | L501: 9 | M501: 3216.56 | N501: 20 | O501: 23159.23

Sheet Day4 01.10.2026 s&f1
A1: Payment Method | C1: Order ID | D1: Customer ID | E1: Order Date | F1: Ship Date | G1: City | H1: State | I1: Sales Channel | J1: Payment Method | K1: Product Category | L1: Product Name | M1: Brand | N1: Units Sold | O1: Unit Price | P1: Discount % | Q1: Net Sales
A2: Debit Card | C2: 10045 | D2: 1699 | E2: 45139 | F2: 45147 | G2: Bengaluru | H2: Delhi | I2: Mobile App | J2: Debit Card | K2: Sports | L2: Cricket Bat | M2: BrandB | N2: 1 | O2: 2764.92 | P2: 0 | Q2: 2764.92
C3: 10317 | D3: 1981 | E3: 45051 | F3: 45056 | G3: Bengaluru | H3: Karnataka | I3: Website | J3: Debit Card | K3: Electronics | L3: Laptop | M3: BrandB | N3: 2 | O3: 788.72 | P3: 20 | Q3: 1261.95
C4: 10190 | D4: 1857 | E4: 45185 | F4: 45187 | G4: Bengaluru | H4: Maharashtra | I4: Marketplace | J4: Debit Card | K4: Electronics | L4: Smartwatch | M4: BrandA | N4: 2 | O4: 1372.59 | P4: 5 | Q4: 2607.92
C5: 10224 | D5: 1795 | E5: 45100 | F5: 45106 | G5: Bengaluru | H5: Tamil Nadu | I5: Marketplace | J5: Debit Card | K5: Books | L5: Fiction Novel | M5: BrandA | N5: 2 | O5: 1448.65 | P5: 20 | Q5: 2317.84
C6: 10194 | D6: 1690 | E6: 45180 | F6: 45182 | G6: Bengaluru | H6: Telangana | I6: Website | J6: Debit Card | K6: Books | L6: Comics | M6: BrandC | N6: 2 | O6: 894.01 | P6: 15 | Q6: 1519.82
C7: 10239 | D7: 1384 | E7: 45146 | F7: 45149 | G7: Bengaluru | H7: Telangana | I7: Website | J7: Debit Card | K7: Electronics | L7: Laptop | M7: BrandB | N7: 2 | O7: 3960.56 | P7: 10 | Q7: 7129.01
C8: 10176 | D8: 1942 | E8: 45166 | F8: 45168 | G8: Bengaluru | H8: West Bengal | I8: Marketplace | J8: Debit Card | K8: Fashion | L8: Jacket | M8: BrandC | N8: 5 | O8: 1551.83 | P8: 5 | Q8: 7371.19
C9: 10159 | D9: 1929 | E9: 45109 | F9: 45113 | G9: Bengaluru | H9: Delhi | I9: Website | J9: Debit Card | K9: Electronics | L9: Smartphone | M9: BrandC | N9: 6 | O9: 3800.77 | P9: 0 | Q9: 22804.62
C10: 10034 | D10: 1313 | E10: 45182 | F10: 45191 | G10: Bengaluru | H10: Tamil Nadu | I10: Marketplace | J10: Debit Card | K10: Fashion | L10: T-Shirt | M10: BrandB | N10: 6 | O10: 1529.59 | P10: 0 | Q10: 9177.54
C11: 10349 | D11: 1871 | E11: 45174 | F11: 45177 | G11: Bengaluru | H11: West Bengal | I11: Marketplace | J11: Debit Card | K11: Home & Kitchen | L11: Curtains | M11: BrandB | N11: 6 | O11: 3281.72 | P11: 5 | Q11: 18705.8
C12: 10482 | D12: 1606 | E12: 45153 | F12: 45162 | G12: Bengaluru | H12: Maharashtra | I12: Website | J12: Debit Card | K12: Books | L12: Biography | M12: BrandE | N12: 7 | O12: 2172.24 | P12: 20 | Q12: 12164.54
C13: 10454 | D13: 1959 | E13: 45251 | F13: 45255 | G13: Bengaluru | H13: Telangana | I13: Mobile App | J13: Debit Card | K13: Books | L13: Fiction Novel | M13: BrandD | N13: 9 | O13: 3191.56 | P13: 20 | Q13: 22979.23
C14: 10261 | D14: 1826 | E14: 44933 | F14: 44936 | G14: Chennai | H14: Maharashtra | I14: Website | J14: Debit Card | K14: Fashion | L14: Sneakers | M14: BrandE | N14: 2 | O14: 533.25 | P14: 0 | Q14: 1066.5
... C88: 10407 | D88: 1877 | E88: 45088 | F88: 45090 | G88: Pune | H88: Tamil Nadu | I88: Website | J88: Debit Card | K88: Beauty | L88: Shampoo | M88: BrandE | N88: 9 | O88: 3216.56 | P88: 20 | Q88: 23159.23

Sheet Day5 05.10.2026
A1: Order ID | B1: Customer ID | C1: Order Date | D1: Ship Date | E1: City | F1: State | G1: Sales Channel | H1: Payment Method | I1: Product Category | J1: Product Name | K1: Brand | L1: Units Sold | M1: Unit Price | N1: Discount % | O1: Net Sales | Q1: Sales Channel | T1: Sales Channel
A2: 10001 | B2: 1102 | C2: 45197 | D2: 45203 | E2: Chennai | F2: Delhi | G2: Mobile App | H2: Credit Card | I2: Home & Kitchen | J2: Mixer Grinder | K2: BrandA | L2: 7 | M2: 2843.87 | N2: 0 | O2: 19907.09 | Q2: Marketplace | T2: Mobile App
A3: 10002 | B3: 1435 | C3: 45199 | D3: 45203 | E3: Pune | F3: Tamil Nadu | G3: Website | H3: Debit Card | I3: Sports | J3: Football | K3: BrandD | L3: 9 | M3: 2525.23 | N3: 5 | O3: 21590.72 | T3: Website
A4: 10003 | B4: 1860 | C4: 45109 | D4: 45114 | E4: Chennai | F4: West Bengal | G4: Marketplace | H4: Debit Card | I4: Fashion | J4: Sneakers | K4: BrandE | L4: 6 | M4: 3474.34 | N4: 15 | O4: 17719.13 | T4: Marketplace
A5: 10004 | B5: 1270 | C5: 45079 | D5: 45087 | E5: Bengaluru | F5: West Bengal | G5: Website | H5: Cash on Delivery | I5: Sports | J5: Yoga Mat | K5: BrandA | L5: 1 | M5: 1008.79 | N5: 15 | O5: 857.47
A6: 10005 | B6: 1106 | C6: 45241 | D6: 45244 | E6: Kolkata | F6: Karnataka | G6: Marketplace | H6: Credit Card | I6: Fashion | J6: Jacket | K6: BrandA | L6: 7 | M6: 3511.47 | N6: 20 | O6: 19664.23
A7: 10006 | B7: 1071 | C7: 45260 | D7: 45263 | E7: Hyderabad | F7: Telangana | G7: Website | H7: Net Banking | I7: Home & Kitchen | J7: Bedsheet | K7: BrandE | L7: 3 | M7: 3189.55 | N7: 10 | O7: 8611.78
A8: 10007 | B8: 1700 | C8: 45050 | D8: 45054 | E8: Bengaluru | F8: Telangana | G8: Mobile App | H8: UPI | I8: Fashion | J8: Sneakers | K8: BrandC | L8: 5 | M8: 3030.42 | N8: 10 | O8: 13636.89
A9: 10008 | B9: 1020 | C9: 45040 | D9: 45041 | E9: Mumbai | F9: Delhi | G9: Website | H9: Credit Card | I9: Fashion | J9: Sneakers | K9: BrandB | L9: 4 | M9: 2310.83 | N9: 10 | O9: 8318.99
A10: 10009 | B10: 1614 | C10: 45204 | D10: 45213 | E10: Chennai | F10: West Bengal | G10: Website | H10: Debit Card | I10: Fashion | J10: T-Shirt | K10: BrandD | L10: 5 | M10: 1098.04 | N10: 15 | O10: 4666.67
A11: 10010 | B11: 1121 | C11: 45139 | D11: 45147 | E11: Bengaluru | F11: Karnataka | G11: Website | H11: Cash on Delivery | I11: Electronics | J11: Headphones | K11: BrandB | L11: 5 | M11: 1780.66 | N11: 20 | O11: 7122.64
A12: 10011 | B12: 1466 | C12: 45098 | D12: 45106 | E12: Bengaluru | F12: Karnataka | G12: Mobile App | H12: Cash on Delivery | I12: Electronics | J12: Headphones | K12: BrandE | L12: 6 | M12: 3205.25 | N12: 0 | O12: 19231.5
A13: 10012 | B13: 1214 | C13: 45214 | D13: 45220 | E13: Mumbai | F13: Tamil Nadu | G13: Website | H13: UPI | I13: Electronics | J13: Smartwatch | K13: BrandA | L13: 6 | M13: 272.35 | N13: 5 | O13: 1552.39
A14: 10013 | B14: 1330 | C14: 45100 | D14: 45107 | E14: Delhi | F14: Tamil Nadu | G14: Mobile App | H14: Cash on Delivery | I14: Home & Kitchen | J14: Bedsheet | K14: BrandA | L14: 8 | M14: 3160.9 | N14: 0 | O14: 25287.2
A15: 10014 | B15: 1458 | C15: 45039 | D15: 45045 | E15: Kolkata | F15: Karnataka | G15: Marketplace | H15: Cash on Delivery | I15: Sports | J15: Yoga Mat | K15: BrandD | L15: 8 | M15: 1074.27 | N15: 15 | O15: 7305.04
A16: 10015 | B16: 1087 | C16: 45048 | D16: 45057 | E16: Hyderabad | F16: Tamil Nadu | G16: Website | H16: Credit Card | I16: Beauty | J16: Shampoo | K16: BrandA | L16: 9 | M16: 705.59 | N16: 10 | O16: 5715.28
... A501: 10500 | B501: 1569 | C501: 44972 | D501: 44977 | E501: Chennai | F501: Delhi | G501: Marketplace | H501: Net Banking | I501: Fashion | J501: Jeans | K501: BrandE | L501: 1 | M501: 2432.17 | N501: 20 | O501: 1945.74

Sheet Day6.10.26 Flashfill,Text fr. 
A1: Order ID | B1: Customer ID | C1: Order Date | D1: Ship Date | E1: City | F1: State | G1: Sales Channel | H1: Payment Method | I1: Product Category | J1: Product Name | K1: Brand | L1: Units Sold | M1: Unit Price | N1: Discount % | O1: Net Sales | P1: Brand FLASH FILL Using (CTRL+E) | Q1: Right Values | R1: Middle Values | S1: Len of productname | T1: Trim | U1: Len | V1: upper | W1: lower | X1: proper | Y1: concat | Z1: concat using range | AA1: concatenate | AB1: Text Join | AC1: find the position | AD1: search | AE1: replace | AF1: text split
A2: 10001 | B2: 1102 | C2: 45197 | D2: 45203 | E2: Chennai | F2: Delhi | G2: Mobile App | H2: Credit Card | I2: Home & Kitchen | J2: Mixer Grinder | K2: BrandA | L2: 7 | M2: 2843.87 | N2: 0 | O2: 19907.09 | P2: BrandA | Q2: =RIGHT(H2,3) -> ard | R2: =MID(J2,2,4) -> ixer | S2: =LEN(J2) -> 16 | T2: =TRIM(J2) -> Mixer Grinder | U2: =LEN(T2) -> 13 | V2: =UPPER(T2) -> MIXER GRINDER | W2: =LOWER(V2) -> mixer grinder | X2: =PROPER(W2) -> Mixer Grinder | Y2: =_xlfn.CONCAT(F2," ",L2) -> Delhi 7 | Z2: =_xlfn.CONCAT(K2:L2) -> BrandA7 | AA2: =CONCATENATE(K2," ",L2) -> BrandA 7 | AB2: =_xlfn.TEXTJOIN(" ",TRUE,F2:G2) -> Delhi Mobile App | AC2: =FIND("e",G2) -> 6 | AD2: =SEARCH("M",AB2) -> 7 | AE2: =REPLACE(AB2,5,3,"p") -> Delhpobile App | AF2: delhi | AG2: mobile | AH2: app
A3: 10002 | B3: 1435 | C3: 45199 | D3: 45203 | E3: Pune | F3: Tamil Nadu | G3: Website | H3: Debit Card | I3: Sports | J3: Football | K3: BrandD | L3: 9 | M3: 2525.23 | N3: 5 | O3: 21590.72 | P3: BrandD | Q3: =RIGHT(H3,3) -> ard | R3: =MID(J3,2,4) -> ootb | S3: =LEN(J3) -> 12 | T3: =TRIM(J3) -> Football | U3: =LEN(T3) -> 8 | V3: =UPPER(T3) -> FOOTBALL | W3: =LOWER(V3) -> football | X3: =PROPER(W3) -> Football | Y3: =_xlfn.CONCAT(F3," ",L3) -> Tamil Nadu 9 | Z3: =_xlfn.CONCAT(K3:L3) -> BrandD9 | AA3: =CONCATENATE(K3," ",L3) -> BrandD 9 | AB3: =_xlfn.TEXTJOIN(" ",TRUE,F3:G3) -> Tamil Nadu Website | AC3: =FIND("e",G3) -> 2 | AD3: =SEARCH("M",AB3) -> 3 | AE3: =REPLACE(AB3,5,3,"p") -> Tamipadu Website | AF3: tamil nadu | AG3: website | AH3: website
A4: 10003 | B4: 1860 | C4: 45109 | D4: 45114 | E4: Chennai | F4: West Bengal | G4: Marketplace | H4: Debit Card | I4: Fashion | J4: Sneakers | K4: BrandE | L4: 6 | M4: 3474.34 | N4: 15 | O4: 17719.13 | P4: BrandE | Q4: =RIGHT(H4,3) -> ard | R4: =MID(J4,2,4) -> S | S4: =LEN(J4) -> 12 | T4: =TRIM(J4) -> Sneakers | U4: =LEN(T4) -> 8 | V4: =UPPER(T4) -> SNEAKERS | W4: =LOWER(V4) -> sneakers | X4: =PROPER(W4) -> Sneakers | Y4: =_xlfn.CONCAT(F4," ",L4) -> West Bengal 6 | Z4: =_xlfn.CONCAT(K4:L4) -> BrandE6 | AA4: =CONCATENATE(K4," ",L4) -> BrandE 6 | AB4: =_xlfn.TEXTJOIN(" ",TRUE,F4:G4) -> West Bengal Marketplace | AC4: =FIND("e",G4) -> 5 | AD4: =SEARCH("M",AB4) -> 13 | AE4: =REPLACE(AB4,5,3,"p") -> Westpngal Marketplace | AF4: west bengal | AG4: marketplace | AH4: marketplace
A5: 10004 | B5: 1270 | C5: 45079 | D5: 45087 | E5: Bengaluru | F5: West Bengal | G5: Website | H5: Cash on Delivery | I5: Sports | J5: Yoga Mat | K5: BrandA | L5: 1 | M5: 1008.79 | N5: 15 | O5: 857.47 | P5: BrandA | Q5: =RIGHT(H5,3) -> ery | R5: =MID(J5,2,4) -> oga | S5: =LEN(J5) -> 8 | T5: =TRIM(J5) -> Yoga Mat | U5: =LEN(T5) -> 8 | V5: =UPPER(T5) -> YOGA MAT | W5: =LOWER(V5) -> yoga mat | X5: =PROPER(W5) -> Yoga Mat | Y5: =_xlfn.CONCAT(F5," ",L5) -> West Bengal 1 | Z5: =_xlfn.CONCAT(K5:L5) -> BrandA1 | AA5: =CONCATENATE(K5," ",L5) -> BrandA 1 | AB5: =_xlfn.TEXTJOIN(" ",TRUE,F5:G5) -> West Bengal Website | AC5: =FIND("e",G5) -> 2 | AD5: =SEARCH("M",AB5) -> #VALUE! | AE5: =REPLACE(AB5,5,3,"p") -> Westpngal Website | AF5: west bengal | AG5: website | AH5: website
A6: 10005 | B6: 1106 | C6: 45241 | D6: 45244 | E6: Kolkata | F6: Karnataka | G6: Marketplace | H6: Credit Card | I6: Fashion | J6: Jacket | K6: BrandA | L6: 7 | M6: 3511.47 | N6: 20 | O6: 19664.23 | P6: BrandA | Q6: =RIGHT(H6,3) -> ard | R6: =MID(J6,2,4) -> acke | S6: =LEN(J6) -> 6 | T6: =TRIM(J6) -> Jacket | U6: =LEN(T6) -> 6 | V6: =UPPER(T6) -> JACKET | W6: =LOWER(V6) -> jacket | X6: =PROPER(W6) -> Jacket | Y6: =_xlfn.CONCAT(F6," ",L6) -> Karnataka 7 | Z6: =_xlfn.CONCAT(K6:L6) -> BrandA7 | AA6: =CONCATENATE(K6," ",L6) -> BrandA 7 | AB6: =_xlfn.TEXTJOIN(" ",TRUE,F6:G6) -> Karnataka Marketplace | AC6: =FIND("e",G6) -> 5 | AD6: =SEARCH("M",AB6) -> 11 | AE6: =REPLACE(AB6,5,3,"p") -> Karnpka Marketplace | AF6: karnataka | AG6: marketplace | AH6: marketplace
A7: 10006 | B7: 1071 | C7: 45260 | D7: 45263 | E7: Hyderabad | F7: Telangana | G7: Website | H7: Net Banking | I7: Home & Kitchen | J7: Bedsheet | K7: BrandE | L7: 3 | M7: 3189.55 | N7: 10 | O7: 8611.78 | P7: BrandE | Q7: =RIGHT(H7,3) -> ing | R7: =MID(J7,2,4) -> edsh | S7: =LEN(J7) -> 8 | T7: =TRIM(J7) -> Bedsheet | U7: =LEN(T7) -> 8 | V7: =UPPER(T7) -> BEDSHEET | W7: =LOWER(V7) -> bedsheet | X7: =PROPER(W7) -> Bedsheet | Y7: =_xlfn.CONCAT(F7," ",L7) -> Telangana 3 | Z7: =_xlfn.CONCAT(K7:L7) -> BrandE3 | AA7: =CONCATENATE(K7," ",L7) -> BrandE 3 | AB7: =_xlfn.TEXTJOIN(" ",TRUE,F7:G7) -> Telangana Website | AC7: =FIND("e",G7) -> 2 | AD7: =SEARCH("M",AB7) -> #VALUE! | AE7: =REPLACE(AB7,5,3,"p") -> Telapna Website | AF7: telangana | AG7: website | AH7: website
A8: 10007 | B8: 1700 | C8: 45050 | D8: 45054 | E8: Bengaluru | F8: Telangana | G8: Mobile App | H8: UPI | I8: Fashion | J8: Sneakers | K8: BrandC | L8: 5 | M8: 3030.42 | N8: 10 | O8: 13636.89 | P8: BrandC | Q8: =RIGHT(H8,3) -> UPI | R8: =MID(J8,2,4) -> neak | S8: =LEN(J8) -> 8 | T8: =TRIM(J8) -> Sneakers | U8: =LEN(T8) -> 8 | V8: =UPPER(T8) -> SNEAKERS | W8: =LOWER(V8) -> sneakers | X8: =PROPER(W8) -> Sneakers | Y8: =_xlfn.CONCAT(F8," ",L8) -> Telangana 5 | Z8: =_xlfn.CONCAT(K8:L8) -> BrandC5 | AA8: =CONCATENATE(K8," ",L8) -> BrandC 5 | AB8: =_xlfn.TEXTJOIN(" ",TRUE,F8:G8) -> Telangana Mobile App | AC8: =FIND("e",G8) -> 6 | AD8: =SEARCH("M",AB8) -> 11 | AE8: =REPLACE(AB8,5,3,"p") -> Telapna Mobile App | AF8: telangana | AG8: mobile | AH8: app
A9: 10008 | B9: 1020 | C9: 45040 | D9: 45041 | E9: Mumbai | F9: Delhi | G9: Website | H9: Credit Card | I9: Fashion | J9: Sneakers | K9: BrandB | L9: 4 | M9: 2310.83 | N9: 10 | O9: 8318.99 | P9: BrandB | Q9: =RIGHT(H9,3) -> ard | R9: =MID(J9,2,4) -> neak | S9: =LEN(J9) -> 8 | T9: =TRIM(J9) -> Sneakers | U9: =LEN(T9) -> 8 | V9: =UPPER(T9) -> SNEAKERS | W9: =LOWER(V9) -> sneakers | X9: =PROPER(W9) -> Sneakers | Y9: =_xlfn.CONCAT(F9," ",L9) -> Delhi 4 | Z9: =_xlfn.CONCAT(K9:L9) -> BrandB4 | AA9: =CONCATENATE(K9," ",L9) -> BrandB 4 | AB9: =_xlfn.TEXTJOIN(" ",TRUE,F9:G9) -> Delhi Website | AC9: =FIND("e",G9) -> 2 | AD9: =SEARCH("M",AB9) -> #VALUE! | AE9: =REPLACE(AB9,5,3,"p") -> Delhpebsite | AF9: delhi | AG9: website | AH9: website
A10: 10009 | B10: 1614 | C10: 45204 | D10: 45213 | E10: Chennai | F10: West Bengal | G10: Website | H10: Debit Card | I10: Fashion | J10: T-Shirt | K10: BrandD | L10: 5 | M10: 1098.04 | N10: 15 | O10: 4666.67 | P10: BrandD | Q10: =RIGHT(H10,3) -> ard | R10: =MID(J10,2,4) -> -Shi | S10: =LEN(J10) -> 7 | T10: =TRIM(J10) -> T-Shirt | U10: =LEN(T10) -> 7 | V10: =UPPER(T10) -> T-SHIRT | W10: =LOWER(V10) -> t-shirt | X10: =PROPER(W10) -> T-Shirt | Y10: =_xlfn.CONCAT(F10," ",L10) -> West Bengal 5 | Z10: =_xlfn.CONCAT(K10:L10) -> BrandD5 | AA10: =CONCATENATE(K10," ",L10) -> BrandD 5 | AB10: =_xlfn.TEXTJOIN(" ",TRUE,F10:G10) -> West Bengal Website | AC10: =FIND("e",G10) -> 2 | AD10: =SEARCH("M",AB10) -> #VALUE! | AE10: =REPLACE(AB10,5,3,"p") -> Westpngal Website | AF10: west bengal | AG10: website | AH10: website
A11: 10010 | B11: 1121 | C11: 45139 | D11: 45147 | E11: Bengaluru | F11: Karnataka | G11: Website | H11: Cash on Delivery | I11: Electronics | J11: Headphones | K11: BrandB | L11: 5 | M11: 1780.66 | N11: 20 | O11: 7122.64 | P11: BrandB | Q11: =RIGHT(H11,3) -> ery | R11: =MID(J11,2,4) -> eadp | S11: =LEN(J11) -> 10 | T11: =TRIM(J11) -> Headphones | U11: =LEN(T11) -> 10 | V11: =UPPER(T11) -> HEADPHONES | W11: =LOWER(V11) -> headphones | X11: =PROPER(W11) -> Headphones | Y11: =_xlfn.CONCAT(F11," ",L11) -> Karnataka 5 | Z11: =_xlfn.CONCAT(K11:L11) -> BrandB5 | AA11: =CONCATENATE(K11," ",L11) -> BrandB 5 | AB11: =_xlfn.TEXTJOIN(" ",TRUE,F11:G11) -> Karnataka Website | AC11: =FIND("e",G11) -> 2 | AD11: =SEARCH("M",AB11) -> #VALUE! | AE11: =REPLACE(AB11,5,3,"p") -> Karnpka Website | AF11: karnataka | AG11: website | AH11: website
A12: 10011 | B12: 1466 | C12: 45098 | D12: 45106 | E12: Bengaluru | F12: Karnataka | G12: Mobile App | H12: Cash on Delivery | I12: Electronics | J12: Headphones | K12: BrandE | L12: 6 | M12: 3205.25 | N12: 0 | O12: 19231.5 | P12: BrandE | Q12: =RIGHT(H12,3) -> ery | R12: =MID(J12,2,4) -> eadp | S12: =LEN(J12) -> 10 | T12: =TRIM(J12) -> Headphones | U12: =LEN(T12) -> 10 | V12: =UPPER(T12) -> HEADPHONES | W12: =LOWER(V12) -> headphones | X12: =PROPER(W12) -> Headphones | Y12: =_xlfn.CONCAT(F12," ",L12) -> Karnataka 6 | Z12: =_xlfn.CONCAT(K12:L12) -> BrandE6 | AA12: =CONCATENATE(K12," ",L12) -> BrandE 6 | AB12: =_xlfn.TEXTJOIN(" ",TRUE,F12:G12) -> Karnataka Mobile App | AC12: =FIND("e",G12) -> 6 | AD12: =SEARCH("M",AB12) -> 11 | AE12: =REPLACE(AB12,5,3,"p") -> Karnpka Mobile App | AF12: karnataka | AG12: mobile | AH12: app
A13: 10012 | B13: 1214 | C13: 45214 | D13: 45220 | E13: Mumbai | F13: Tamil Nadu | G13: Website | H13: UPI | I13: Electronics | J13: Smartwatch | K13: BrandA | L13: 6 | M13: 272.35 | N13: 5 | O13: 1552.39 | P13: BrandA | Q13: =RIGHT(H13,3) -> UPI | R13: =MID(J13,2,4) -> mart | S13: =LEN(J13) -> 10 | T13: =TRIM(J13) -> Smartwatch | U13: =LEN(T13) -> 10 | V13: =UPPER(T13) -> SMARTWATCH | W13: =LOWER(V13) -> smartwatch | X13: =PROPER(W13) -> Smartwatch | Y13: =_xlfn.CONCAT(F13," ",L13) -> Tamil Nadu 6 | Z13: =_xlfn.CONCAT(K13:L13) -> BrandA6 | AA13: =CONCATENATE(K13," ",L13) -> BrandA 6 | AB13: =_xlfn.TEXTJOIN(" ",TRUE,F13:G13) -> Tamil Nadu Website | AC13: =FIND("e",G13) -> 2 | AD13: =SEARCH("M",AB13) -> 3 | AE13: =REPLACE(AB13,5,3,"p") -> Tamipadu Website | AF13: tamil nadu | AG13: website | AH13: website
... A501: 10500 | B501: 1569 | C501: 44972 | D501: 44977 | E501: Chennai | F501: Delhi | G501: Marketplace | H501: Net Banking | I501: Fashion | J501: Jeans | K501: BrandE | L501: 1 | M501: 2432.17 | N501: 20 | O501: 1945.74 | P501: BrandE | Q501: =RIGHT(H501,3) -> ing | R501: =MID(J501,2,4) -> eans | S501: =LEN(J501) -> 5 | T501: =TRIM(J501) -> Jeans | U501: =LEN(T501) -> 5 | V501: =UPPER(T501) -> JEANS | W501: =LOWER(V501) -> jeans | X501: =PROPER(W501) -> Jeans | Y501: =_xlfn.CONCAT(F501," ",L501) -> Delhi 1 | Z501: =_xlfn.CONCAT(K501:L501) -> BrandE1 | AA501: =CONCATENATE(K501," ",L501) -> BrandE 1 | AB501: =_xlfn.TEXTJOIN(" ",TRUE,F501:G501) -> Delhi Marketplace | AC501: =FIND("e",G501) -> 5 | AD501: =SEARCH("M",AB501) -> 7 | AE501: =REPLACE(AB501,5,3,"p") -> Delhparketplace | AF501: delhi | AG501: marketplace | AH501: marketplace

Sheet Day7.10.26 V-Lookup
A1: Order ID | B1: Customer ID | C1: Order Date | D1: Ship Date | E1: City | F1: State | G1: Sales Channel | H1: Payment Method | I1: Product Category | J1: Product Name | K1: Brand | L1: Units Sold | M1: Unit Price | N1: Discount % | O1: Net Sales | V1: Marks | W1: Category
A2: 10001 | B2: 1102 | C2: 45197 | D2: 45203 | E2: Chennai | F2: Delhi | G2: Mobile App | H2: Credit Card | I2: Home & Kitchen | J2: Mixer Grinder | K2: BrandA | L2: 7 | M2: 2843.87 | N2: 0 | O2: 19907.09 | V2: 0 | W2: Fail | Y2: Marks | Z2: Category
A3: 10002 | B3: 1435 | C3: 45199 | D3: 45203 | E3: Pune | F3: Tamil Nadu | G3: Website | H3: Debit Card | I3: Sports | J3: Football | K3: BrandD | L3: 9 | M3: 2525.23 | N3: 5 | O3: 21590.72 | V3: 40 | W3: C | Y3: 57 | Z3: =VLOOKUP(Y3,V1:W5,2,1) -> C
A4: 10003 | B4: 1860 | C4: 45109 | D4: 45114 | E4: Chennai | F4: West Bengal | G4: Marketplace | H4: Debit Card | I4: Fashion | J4: Sneakers | K4: BrandE | L4: 6 | M4: 3474.34 | N4: 15 | O4: 17719.13 | Q4: Order ID | R4: Net Sales | V4: 60 | W4: B
A5: 10004 | B5: 1270 | C5: 45079 | D5: 45087 | E5: Bengaluru | F5: West Bengal | G5: Website | H5: Cash on Delivery | I5: Sports | J5: Yoga Mat | K5: BrandA | L5: 1 | M5: 1008.79 | N5: 15 | O5: 857.47 | Q5: 10007 | R5: =VLOOKUP(Q5,A1:O502,15,0) -> 13636.89 | V5: 80 | W5: A
A6: 10005 | B6: 1106 | C6: 45241 | D6: 45244 | E6: Kolkata | F6: Karnataka | G6: Marketplace | H6: Credit Card | I6: Fashion | J6: Jacket | K6: BrandA | L6: 7 | M6: 3511.47 | N6: 20 | O6: 19664.23
A7: 10006 | B7: 1071 | C7: 45260 | D7: 45263 | E7: Hyderabad | F7: Telangana | G7: Website | H7: Net Banking | I7: Home & Kitchen | J7: Bedsheet | K7: BrandE | L7: 3 | M7: 3189.55 | N7: 10 | O7: 8611.78 | Q7: Customer ID | R7: Units Sold
A8: 10007 | B8: 1700 | C8: 45050 | D8: 45054 | E8: Bengaluru | F8: Telangana | G8: Mobile App | H8: UPI | I8: Fashion | J8: Sneakers | K8: BrandC | L8: 5 | M8: 3030.42 | N8: 10 | O8: 13636.89 | Q8: 1458 | R8: =VLOOKUP(Q8,B1:O502,11,0) -> 8
A9: 10008 | B9: 1020 | C9: 45040 | D9: 45041 | E9: Mumbai | F9: Delhi | G9: Website | H9: Credit Card | I9: Fashion | J9: Sneakers | K9: BrandB | L9: 4 | M9: 2310.83 | N9: 10 | O9: 8318.99
A10: 10009 | B10: 1614 | C10: 45204 | D10: 45213 | E10: Chennai | F10: West Bengal | G10: Website | H10: Debit Card | I10: Fashion | J10: T-Shirt | K10: BrandD | L10: 5 | M10: 1098.04 | N10: 15 | O10: 4666.67 | Q10: Order ID | R10: City | S10: Product Category | T10: Units Sold
A11: 10010 | B11: 1121 | C11: 45139 | D11: 45147 | E11: Bengaluru | F11: Karnataka | G11: Website | H11: Cash on Delivery | I11: Electronics | J11: Headphones | K11: BrandB | L11: 5 | M11: 1780.66 | N11: 20 | O11: 7122.64 | Q11: 10026 | R11: {=VLOOKUP(Q11,A1:O502,{5,9,12},0)} -> Bengaluru | S11: Beauty | T11: 9
A12: 10011 | B12: 1466 | C12: 45098 | D12: 45106 | E12: Bengaluru | F12: Karnataka | G12: Mobile App | H12: Cash on Delivery | I12: Electronics | J12: Headphones | K12: BrandE | L12: 6 | M12: 3205.25 | N12: 0 | O12: 19231.5
A13: 10012 | B13: 1214 | C13: 45214 | D13: 45220 | E13: Mumbai | F13: Tamil Nadu | G13: Website | H13: UPI | I13: Electronics | J13: Smartwatch | K13: BrandA | L13: 6 | M13: 272.35 | N13: 5 | O13: 1552.39 | Q13: Order ID | R13: City
A14: 10013 | B14: 1330 | C14: 45100 | D14: 45107 | E14: Delhi | F14: Tamil Nadu | G14: Mobile App | H14: Cash on Delivery | I14: Home & Kitchen | J14: Bedsheet | K14: BrandA | L14: 8 | M14: 3160.9 | N14: 0 | O14: 25287.2 | Q14: 10007 | R14: =VLOOKUP(Q14,$A$1:$O$502,5,0) -> Bengaluru
A15: 10014 | B15: 1458 | C15: 45039 | D15: 45045 | E15: Kolkata | F15: Karnataka | G15: Marketplace | H15: Cash on Delivery | I15: Sports | J15: Yoga Mat | K15: BrandD | L15: 8 | M15: 1074.27 | N15: 15 | O15: 7305.04 | Q15: 10009 | R15: =VLOOKUP(Q15,$A$1:$O$502,5,0) -> Chennai
A16: 10015 | B16: 1087 | C16: 45048 | D16: 45057 | E16: Hyderabad | F16: Tamil Nadu | G16: Website | H16: Credit Card | I16: Beauty | J16: Shampoo | K16: BrandA | L16: 9 | M16: 705.59 | N16: 10 | O16: 5715.28 | Q16: 10001 | R16: =VLOOKUP(Q16,$A$1:$O$502,5,0) -> Chennai
A17: 10016 | B17: 1372 | C17: 44958 | D17: 44961 | E17: Pune | F17: West Bengal | G17: Mobile App | H17: Net Banking | I17: Fashion | J17: Jacket | K17: BrandA | L17: 8 | M17: 595.45 | N17: 5 | O17: 4525.42 | Q17: 10005 | R17: =VLOOKUP(Q17,$A$1:$O$502,5,0) -> Kolkata
A18: 10017 | B18: 1099 | C18: 45148 | D18: 45151 | E18: Delhi | F18: Maharashtra | G18: Mobile App | H18: UPI | I18: Fashion | J18: Jacket | K18: BrandD | L18: 2 | M18: 254.91 | N18: 15 | O18: 433.35
A19: 10018 | B19: 1871 | C19: 45045 | D19: 45048 | E19: Chennai | F19: West Bengal | G19: Website | H19: Credit Card | I19: Home & Kitchen | J19: Curtains | K19: BrandD | L19: 1 | M19: 2165.81 | N19: 15 | O19: 1840.94 | Q19: Order ID | R19: Net Sales
A20: 10019 | B20: 1663 | C20: 44965 | D20: 44968 | E20: Bengaluru | F20: Karnataka | G20: Marketplace | H20: Net Banking | I20: Fashion | J20: Jacket | K20: BrandE | L20: 2 | M20: 990.3 | N20: 15 | O20: 1683.51 | Q20: 10502 | R20: =VLOOKUP(Q20,Table2[#All],15,0) -> 732.19
A21: 10020 | B21: 1130 | C21: 45194 | D21: 45203 | E21: Mumbai | F21: Karnataka | G21: Mobile App | H21: Credit Card | I21: Electronics | J21: Smartwatch | K21: BrandA | L21: 2 | M21: 3959.31 | N21: 5 | O21: 7522.69
A22: 10021 | B22: 1661 | C22: 45159 | D22: 45163 | E22: Mumbai | F22: West Bengal | G22: Website | H22: Credit Card | I22: Beauty | J22: Lipstick | K22: BrandA | L22: 3 | M22: 2361.58 | N22: 5 | O22: 6730.5 | Q22: Customer ID | R22: Order ID
A23: 10022 | B23: 1308 | C23: 44944 | D23: 44951 | E23: Kolkata | F23: Tamil Nadu | G23: Marketplace | H23: Cash on Delivery | I23: Books | J23: Fiction Novel | K23: BrandE | L23: 7 | M23: 680.86 | N23: 20 | O23: 3812.82 | Q23: 1106 | R23: =VLOOKUP(Q23,CHOOSE({1,2},Table2[[#All],[Customer ID]],Table2[[#All],[Order ID]]),2,0) -> 10005
A24: 10023 | B24: 1769 | C24: 45075 | D24: 45084 | E24: Delhi | F24: Tamil Nadu | G24: Mobile App | H24: Net Banking | I24: Fashion | J24: Sneakers | K24: BrandC | L24: 2 | M24: 2801.74 | N24: 20 | O24: 4482.78
A25: 10024 | B25: 1343 | C25: 45075 | D25: 45082 | E25: Pune | F25: Telangana | G25: Mobile App | H25: UPI | I25: Electronics | J25: Smartwatch | K25: BrandC | L25: 1 | M25: 3606.31 | N25: 0 | O25: 3606.31
A26: 10025 | B26: 1491 | C26: 45052 | D26: 45061 | E26: Kolkata | F26: Karnataka | G26: Marketplace | H26: UPI | I26: Books | J26: Comics | K26: BrandC | L26: 6 | M26: 3018.94 | N26: 5 | O26: 17207.96
A27: 10026 | B27: 1413 | C27: 45228 | D27: 45231 | E27: Bengaluru | F27: Delhi | G27: Marketplace | H27: Net Banking | I27: Beauty | J27: Perfume | K27: BrandE | L27: 9 | M27: 444.29 | N27: 5 | O27: 3798.68 | Q27: iferror
A28: 10027 | B28: 1805 | C28: 45286 | D28: 45290 | E28: Kolkata | F28: Telangana | G28: Website | H28: Cash on Delivery | I28: Books | J28: Fiction Novel | K28: BrandA | L28: 3 | M28: 3599.15 | N28: 5 | O28: 10257.58
A29: 10028 | B29: 1385 | C29: 45164 | D29: 45172 | E29: Hyderabad | F29: Tamil Nadu | G29: Website | H29: Debit Card | I29: Electronics | J29: Smartwatch | K29: BrandE | L29: 6 | M29: 3206.63 | N29: 20 | O29: 15391.82
A30: 10029 | B30: 1191 | C30: 45061 | D30: 45067 | E30: Mumbai | F30: West Bengal | G30: Mobile App | H30: Credit Card | I30: Sports | J30: Football | K30: BrandE | L30: 3 | M30: 759.47 | N30: 15 | O30: 1936.65
A31: 10030 | B31: 1955 | C31: 45077 | D31: 45082 | E31: Mumbai | F31: Tamil Nadu | G31: Marketplace | H31: Cash on Delivery | I31: Sports | J31: Cricket Bat | K31: BrandC | L31: 1 | M31: 349.38 | N31: 10 | O31: 314.44
A32: 10031 | B32: 1276 | C32: 45162 | D32: 45166 | E32: Chennai | F32: West Bengal | G32: Marketplace | H32: Net Banking | I32: Books | J32: Textbook | K32: BrandB | L32: 5 | M32: 2295.65 | N32: 20 | O32: 9182.6
A33: 10032 | B33: 1160 | C33: 45150 | D33: 45158 | E33: Chennai | F33: Telangana | G33: Marketplace | H33: Credit Card | I33: Home & Kitchen | J33: Bedsheet | K33: BrandA | L33: 4 | M33: 750.74 | N33: 5 | O33: 2852.81
A34: 10033 | B34: 1459 | C34: 45129 | D34: 45130 | E34: Pune | F34: Karnataka | G34: Mobile App | H34: UPI | I34: Books | J34: Comics | K34: BrandC | L34: 7 | M34: 3363.18 | N34: 20 | O34: 18833.81
A35: 10034 | B35: 1313 | C35: 45182 | D35: 45191 | E35: Bengaluru | F35: Tamil Nadu | G35: Marketplace | H35: Debit Card | I35: Fashion | J35: T-Shirt | K35: BrandB | L35: 6 | M35: 1529.59 | N35: 0 | O35: 9177.54
A36: 10035 | B36: 1021 | C36: 45012 | D36: 45013 | E36: Hyderabad | F36: West Bengal | G36: Marketplace | H36: UPI | I36: Fashion | J36: T-Shirt | K36: BrandB | L36: 7 | M36: 3664.64 | N36: 5 | O36: 24369.86
A37: 10036 | B37: 1252 | C37: 45076 | D37: 45084 | E37: Delhi | F37: Karnataka | G37: Mobile App | H37: Net Banking | I37: Sports | J37: Football | K37: BrandD | L37: 5 | M37: 2327.9 | N37: 0 | O37: 11639.5
A38: 10037 | B38: 1747 | C38: 45161 | D38: 45165 | E38: Kolkata | F38: Delhi | G38: Website | H38: Credit Card | I38: Home & Kitchen | J38: Curtains | K38: BrandA | L38: 4 | M38: 853.29 | N38: 5 | O38: 3242.5
A39: 10038 | B39: 1856 | C39: 45271 | D39: 45280 | E39: Pune | F39: West Bengal | G39: Website | H39: Net Banking | I39: Electronics | J39: Laptop | K39: BrandB | L39: 7 | M39: 687.46 | N39: 20 | O39: 3849.78
... A502: 10502 | B502: 1570 | C502: 44973 | D502: 44978 | E502: Chennai | F502: Delhi | G502: Marketplace | H502: UPI | I502: Beauty | J502: Perfume | K502: BrandA | L502: 8 | M502: 37888 | N502: 85 | O502: 732.19

Sheet Day7.10.26 H-Lookup
A1: Order ID | B1: 10001 | C1: 10002 | D1: 10003 | E1: 10004 | F1: 10005 | G1: 10006 | H1: 10007 | I1: 10008 | J1: 10009 | K1: 10010 | L1: 10011 | M1: 10012 | N1: 10013 | O1: 10014 | P1: 10015 | Q1: 10016 | R1: 10017 | S1: 10018 | T1: 10019 | U1: 10020 | V1: 10021 | W1: 10022 | X1: 10023 | Y1: 10024 | Z1: 10025 | AA1: 10026 | AB1: 10027 | AC1: 10028 | AD1: 10029 | AE1: 10030 | AF1: 10031 | AG1: 10032 | AH1: 10033 | AI1: 10034 | AJ1: 10035 | AK1: 10036 | AL1: 10037 | AM1: 10038 | AN1: 10039 | AO1: 10040 | AP1: 10041 | AQ1: 10042 | AR1: 10043 | AS1: 10044 | AT1: 10045 | AU1: 10046 | AV1: 10047 | AW1: 10048 | AX1: 10049 | AY1: 10050 | AZ1: 10051 | BA1: 10052 | BB1: 10053 | BC1: 10054 | BD1: 10055 | BE1: 10056 | BF1: 10057 | BG1: 10058 | BH1: 10059 | BI1: 10060 | BJ1: 10061 | BK1: 10062 | BL1: 10063 | BM1: 10064 | BN1: 10065 | BO1: 10066 | BP1: 10067 | BQ1: 10068 | BR1: 10069 | BS1: 10070 | BT1: 10071 | BU1: 10072 | BV1: 10073 | BW1: 10074 | BX1: 10075 | BY1: 10076 | BZ1: 10077 | CA1: 10078 | CB1: 10079 | CC1: 10080 | CD1: 10081 | CE1: 10082 | CF1: 10083 | CG1: 10084 | CH1: 10085 | CI1: 10086 | CJ1: 10087 | CK1: 10088 | CL1: 10089 | CM1: 10090 | CN1: 10091 | CO1: 10092 | CP1: 10093 | CQ1: 10094 | CR1: 10095 | CS1: 10096 | CT1: 10097 | CU1: 10098 | CV1: 10099 | CW1: 10100 | CX1: 10101 | CY1: 10102 | CZ1: 10103 | DA1: 10104 | DB1: 10105 | DC1: 10106 | DD1: 10107 | DE1: 10108 | DF1: 10109 | DG1: 10110 | DH1: 10111 | DI1: 10112 | DJ1: 10113 | DK1: 10114 | DL1: 10115 | DM1: 10116 | DN1: 10117 | DO1: 10118 | DP1: 10119 | DQ1: 10120 | DR1: 10121 | DS1: 10122 | DT1: 10123 | DU1: 10124 | DV1: 10125 | DW1: 10126 | DX1: 10127 | DY1: 10128 | DZ1: 10129 | EA1: 10130 | EB1: 10131 | EC1: 10132 | ED1: 10133 | EE1: 10134 | EF1: 10135 | EG1: 10136 | EH1: 10137 | EI1: 10138 | EJ1: 10139 | EK1: 10140 | EL1: 10141 | EM1: 10142 | EN1: 10143 | EO1: 10144 | EP1: 10145 | EQ1: 10146 | ER1: 10147 | ES1: 10148 | ET1: 10149 | EU1: 10150 | EV1: 10151 | EW1: 10152 | EX1: 10153 | EY1: 10154 | EZ1: 10155 | FA1: 10156 | FB1: 10157 | FC1: 10158 | FD1: 10159 | FE1: 10160 | FF1: 10161 | FG1: 10162 | FH1: 10163 | FI1: 10164 | FJ1: 10165 | FK1: 10166 | FL1: 10167 | FM1: 10168 | FN1: 10169 | FO1: 10170 | FP1: 10171 | FQ1: 10172 | FR1: 10173 | FS1: 10174 | FT1: 10175 | FU1: 10176 | FV1: 10177 | FW1: 10178 | FX1: 10179 | FY1: 10180 | FZ1: 10181 | GA1: 10182 | GB1: 10183 | GC1: 10184 | GD1: 10185 | GE1: 10186 | GF1: 10187 | GG1: 10188 | GH1: 10189 | GI1: 10190 | GJ1: 10191 | GK1: 10192 | GL1: 10193 | GM1: 10194 | GN1: 10195 | GO1: 10196 | GP1: 10197 | GQ1: 10198 | GR1: 10199 | GS1: 10200 | GT1: 10201 | GU1: 10202 | GV1: 10203 | GW1: 10204 | GX1: 10205 | GY1: 10206 | GZ1: 10207 | HA1: 10208 | HB1: 10209 | HC1: 10210 | HD1: 10211 | HE1: 10212 | HF1: 10213 | HG1: 10214 | HH1: 10215 | HI1: 10216 | HJ1: 10217 | HK1: 10218 | HL1: 10219 | HM1: 10220 | HN1: 10221 | HO1: 10222 | HP1: 10223 | HQ1: 10224 | HR1: 10225 | HS1: 10226 | HT1: 10227 | HU1: 10228 | HV1: 10229 | HW1: 10230 | HX1: 10231 | HY1: 10232 | HZ1: 10233 | IA1: 10234 | IB1: 10235 | IC1: 10236 | ID1: 10237 | IE1: 10238 | IF1: 10239 | IG1: 10240 | IH1: 10241 | II1: 10242 | IJ1: 10243 | IK1: 10244 | IL1: 10245 | IM1: 10246 | IN1: 10247 | IO1: 10248 | IP1: 10249 | IQ1: 10250 | IR1: 10251 | IS1: 10252 | IT1: 10253 | IU1: 10254 | IV1: 10255 | IW1: 10256 | IX1: 10257 | IY1: 10258 | IZ1: 10259 | JA1: 10260 | JB1: 10261 | JC1: 10262 | JD1: 10263 | JE1: 10264 | JF1: 10265 | JG1: 10266 | JH1: 10267 | JI1: 10268 | JJ1: 10269 | JK1: 10270 | JL1: 10271 | JM1: 10272 | JN1: 10273 | JO1: 10274 | JP1: 10275 | JQ1: 10276 | JR1: 10277 | JS1: 10278 | JT1: 10279 | JU1: 10280 | JV1: 10281 | JW1: 10282 | JX1: 10283 | JY1: 10284 | JZ1: 10285 | KA1: 10286 | KB1: 10287 | KC1: 10288 | KD1: 10289 | KE1: 10290 | KF1: 10291 | KG1: 10292 | KH1: 10293 | KI1: 10294 | KJ1: 10295 | KK1: 10296 | KL1: 10297 | KM1: 10298 | KN1: 10299 | KO1: 10300 | KP1: 10301 | KQ1: 10302 | KR1: 10303 | KS1: 10304 | KT1: 10305 | KU1: 10306 | KV1: 10307 | KW1: 10308 | KX1: 10309 | KY1: 10310 | KZ1: 10311 | LA1: 10312 | LB1: 10313 | LC1: 10314 | LD1: 10315 | LE1: 10316 | LF1: 10317 | LG1: 10318 | LH1: 10319 | LI1: 10320 | LJ1: 10321 | LK1: 10322 | LL1: 10323 | LM1: 10324 | LN1: 10325 | LO1: 10326 | LP1: 10327 | LQ1: 10328 | LR1: 10329 | LS1: 10330 | LT1: 10331 | LU1: 10332 | LV1: 10333 | LW1: 10334 | LX1: 10335 | LY1: 10336 | LZ1: 10337 | MA1: 10338 | MB1: 10339 | MC1: 10340 | MD1: 10341 | ME1: 10342 | MF1: 10343 | MG1: 10344 | MH1: 10345 | MI1: 10346 | MJ1: 10347 | MK1: 10348 | ML1: 10349 | MM1: 10350 | MN1: 10351 | MO1: 10352 | MP1: 10353 | MQ1: 10354 | MR1: 10355 | MS1: 10356 | MT1: 10357 | MU1: 10358 | MV1: 10359 | MW1: 10360 | MX1: 10361 | MY1: 10362 | MZ1: 10363 | NA1: 10364 | NB1: 10365 | NC1: 10366 | ND1: 10367 | NE1: 10368 | NF1: 10369 | NG1: 10370 | NH1: 10371 | NI1: 10372 | NJ1: 10373 | NK1: 10374 | NL1: 10375 | NM1: 10376 | NN1: 10377 | NO1: 10378 | NP1: 10379 | NQ1: 10380 | NR1: 10381 | NS1: 10382 | NT1: 10383 | NU1: 10384 | NV1: 10385 | NW1: 10386 | NX1: 10387 | NY1: 10388 | NZ1: 10389 | OA1: 10390 | OB1: 10391 | OC1: 10392 | OD1: 10393 | OE1: 10394 | OF1: 10395 | OG1: 10396 | OH1: 10397 | OI1: 10398 | OJ1: 10399 | OK1: 10400 | OL1: 10401 | OM1: 10402 | ON1: 10403 | OO1: 10404 | OP1: 10405 | OQ1: 10406 | OR1: 10407 | OS1: 10408 | OT1: 10409 | OU1: 10410 | OV1: 10411 | OW1: 10412 | OX1: 10413 | OY1: 10414 | OZ1: 10415 | PA1: 10416 | PB1: 10417 | PC1: 10418 | PD1: 10419 | PE1: 10420 | PF1: 10421 | PG1: 10422 | PH1: 10423 | PI1: 10424 | PJ1: 10425 | PK1: 10426 | PL1: 10427 | PM1: 10428 | PN1: 10429 | PO1: 10430 | PP1: 10431 | PQ1: 10432 | PR1: 10433 | PS1: 10434 | PT1: 10435 | PU1: 10436 | PV1: 10437 | PW1: 10438 | PX1: 10439 | PY1: 10440 | PZ1: 10441 | QA1: 10442 | QB1: 10443 | QC1: 10444 | QD1: 10445 | QE1: 10446 | QF1: 10447 | QG1: 10448 | QH1: 10449 | QI1: 10450 | QJ1: 10451 | QK1: 10452 | QL1: 10453 | QM1: 10454 | QN1: 10455 | QO1: 10456 | QP1: 10457 | QQ1: 10458 | QR1: 10459 | QS1: 10460 | QT1: 10461 | QU1: 10462 | QV1: 10463 | QW1: 10464 | QX1: 10465 | QY1: 10466 | QZ1: 10467 | RA1: 10468 | RB1: 10469 | RC1: 10470 | RD1: 10471 | RE1: 10472 | RF1: 10473 | RG1: 10474 | RH1: 10475 | RI1: 10476 | RJ1: 10477 | RK1: 10478 | RL1: 10479 | RM1: 10480 | RN1: 10481 | RO1: 10482 | RP1: 10483 | RQ1: 10484 | RR1: 10485 | RS1: 10486 | RT1: 10487 | RU1: 10488 | RV1: 10489 | RW1: 10490 | RX1: 10491 | RY1: 10492 | RZ1: 10493 | SA1: 10494 | SB1: 10495 | SC1: 10496 | SD1: 10497 | SE1: 10498 | SF1: 10499 | SG1: 10500
A2: Customer ID | B2: 1102 | C2: 1435 | D2: 1860 | E2: 1270 | F2: 1106 | G2: 1071 | H2: 1700 | I2: 1020 | J2: 1614 | K2: 1121 | L2: 1466 | M2: 1214 | N2: 1330 | O2: 1458 | P2: 1087 | Q2: 1372 | R2: 1099 | S2: 1871 | T2: 1663 | U2: 1130 | V2: 1661 | W2: 1308 | X2: 1769 | Y2: 1343 | Z2: 1491 | AA2: 1413 | AB2: 1805 | AC2: 1385 | AD2: 1191 | AE2: 1955 | AF2: 1276 | AG2: 1160 | AH2: 1459 | AI2: 1313 | AJ2: 1021 | AK2: 1252 | AL2: 1747 | AM2: 1856 | AN2: 1560 | AO2: 1474 | AP2: 1058 | AQ2: 1510 | AR2: 1681 | AS2: 1475 | AT2: 1699 | AU2: 1975 | AV2: 1782 | AW2: 1189 | AX2: 1957 | AY2: 1686 | AZ2: 1957 | BA2: 1562 | BB2: 1875 | BC2: 1566 | BD2: 1243 | BE2: 1831 | BF2: 1504 | BG2: 1130 | BH2: 1484 | BI2: 1818 | BJ2: 1646 | BK2: 1020 | BL2: 1840 | BM2: 1166 | BN2: 1273 | BO2: 1387 | BP2: 1600 | BQ2: 1315 | BR2: 1013 | BS2: 1241 | BT2: 1776 | BU2: 1345 | BV2: 1564 | BW2: 1897 | BX2: 1339 | BY2: 1091 | BZ2: 1366 | CA2: 1955 | CB2: 1454 | CC2: 1427 | CD2: 1508 | CE2: 1775 | CF2: 1942 | CG2: 1034 | CH2: 1205 | CI2: 1080 | CJ2: 1931 | CK2: 1561 | CL2: 1871 | CM2: 1387 | CN2: 1001 | CO2: 1389 | CP2: 1565 | CQ2: 1105 | CR2: 1771 | CS2: 1821 | CT2: 1476 | CU2: 1702 | CV2: 1401 | CW2: 1729 | CX2: 1555 | CY2: 1161 | CZ2: 1201 | DA2: 1957 | DB2: 1995 | DC2: 1269 | DD2: 1862 | DE2: 1815 | DF2: 1270 | DG2: 1455 | DH2: 1461 | DI2: 1726 | DJ2: 1251 | DK2: 1701 | DL2: 1295 | DM2: 1724 | DN2: 1719 | DO2: 1748 | DP2: 1337 | DQ2: 1878 | DR2: 1052 | DS2: 1791 | DT2: 1921 | DU2: 1216 | DV2: 1763 | DW2: 1187 | DX2: 1379 | DY2: 1492 | DZ2: 1040 | EA2: 1156 | EB2: 1014 | EC2: 1812 | ED2: 1064 | EE2: 1856 | EF2: 1838 | EG2: 1520 | EH2: 1343 | EI2: 1128 | EJ2: 1647 | EK2: 1471 | EL2: 1062 | EM2: 1138 | EN2: 1498 | EO2: 1592 | EP2: 1391 | EQ2: 1674 | ER2: 1418 | ES2: 1288 | ET2: 1378 | EU2: 1772 | EV2: 1489 | EW2: 1230 | EX2: 1040 | EY2: 1027 | EZ2: 1134 | FA2: 1200 | FB2: 1839 | FC2: 1779 | FD2: 1929 | FE2: 1032 | FF2: 1047 | FG2: 1502 | FH2: 1406 | FI2: 1573 | FJ2: 1727 | FK2: 1804 | FL2: 1098 | FM2: 1683 | FN2: 1871 | FO2: 1725 | FP2: 1986 | FQ2: 1546 | FR2: 1960 | FS2: 1738 | FT2: 1612 | FU2: 1942 | FV2: 1461 | FW2: 1642 | FX2: 1768 | FY2: 1004 | FZ2: 1217 | GA2: 1502 | GB2: 1766 | GC2: 1397 | GD2: 1870 | GE2: 1794 | GF2: 1392 | GG2: 1206 | GH2: 1014 | GI2: 1857 | GJ2: 1553 | GK2: 1891 | GL2: 1460 | GM2: 1690 | GN2: 1574 | GO2: 1863 | GP2: 1742 | GQ2: 1240 | GR2: 1563 | GS2: 1095 | GT2: 1899 | GU2: 1733 | GV2: 1484 | GW2: 1406 | GX2: 1230 | GY2: 1748 | GZ2: 1654 | HA2: 1170 | HB2: 1540 | HC2: 1035 | HD2: 1524 | HE2: 1159 | HF2: 1838 | HG2: 1698 | HH2: 1242 | HI2: 1085 | HJ2: 1795 | HK2: 1577 | HL2: 1681 | HM2: 1556 | HN2: 1573 | HO2: 1952 | HP2: 1645 | HQ2: 1795 | HR2: 1027 | HS2: 1619 | HT2: 1555 | HU2: 1339 | HV2: 1797 | HW2: 1957 | HX2: 1330 | HY2: 1639 | HZ2: 1505 | IA2: 1347 | IB2: 1472 | IC2: 1230 | ID2: 1189 | IE2: 1224 | IF2: 1384 | IG2: 1376 | IH2: 1282 | II2: 1957 | IJ2: 1632 | IK2: 1627 | IL2: 1972 | IM2: 1744 | IN2: 1258 | IO2: 1358 | IP2: 1709 | IQ2: 1455 | IR2: 1410 | IS2: 1648 | IT2: 1317 | IU2: 1676 | IV2: 1224 | IW2: 1818 | IX2: 1233 | IY2: 1683 | IZ2: 1663 | JA2: 1974 | JB2: 1826 | JC2: 1373 | JD2: 1671 | JE2: 1607 | JF2: 1471 | JG2: 1232 | JH2: 1691 | JI2: 1112 | JJ2: 1829 | JK2: 1496 | JL2: 1441 | JM2: 1563 | JN2: 1267 | JO2: 1509 | JP2: 1806 | JQ2: 1385 | JR2: 1386 | JS2: 1112 | JT2: 1612 | JU2: 1624 | JV2: 1951 | JW2: 1080 | JX2: 1698 | JY2: 1112 | JZ2: 1001 | KA2: 1641 | KB2: 1219 | KC2: 1565 | KD2: 1854 | KE2: 1996 | KF2: 1735 | KG2: 1224 | KH2: 1384 | KI2: 1402 | KJ2: 1637 | KK2: 1129 | KL2: 1052 | KM2: 1683 | KN2: 1729 | KO2: 1671 | KP2: 1709 | KQ2: 1415 | KR2: 1246 | KS2: 1835 | KT2: 1438 | KU2: 1202 | KV2: 1183 | KW2: 1122 | KX2: 1400 | KY2: 1766 | KZ2: 1293 | LA2: 1279 | LB2: 1836 | LC2: 1883 | LD2: 1609 | LE2: 1197 | LF2: 1981 | LG2: 1906 | LH2: 1510 | LI2: 1751 | LJ2: 1143 | LK2: 1608 | LL2: 1200 | LM2: 1123 | LN2: 1186 | LO2: 1325 | LP2: 1463 | LQ2: 1348 | LR2: 1770 | LS2: 1659 | LT2: 1763 | LU2: 1954 | LV2: 1931 | LW2: 1402 | LX2: 1345 | LY2: 1962 | LZ2: 1510 | MA2: 1146 | MB2: 1147 | MC2: 1863 | MD2: 1710 | ME2: 1819 | MF2: 1488 | MG2: 1928 | MH2: 1935 | MI2: 1639 | MJ2: 1550 | MK2: 1337 | ML2: 1871 | MM2: 1640 | MN2: 1778 | MO2: 1987 | MP2: 1952 | MQ2: 1472 | MR2: 1945 | MS2: 1150 | MT2: 1414 | MU2: 1989 | MV2: 1297 | MW2: 1610 | MX2: 1262 | MY2: 1763 | MZ2: 1143 | NA2: 1345 | NB2: 1623 | NC2: 1571 | ND2: 1880 | NE2: 1001 | NF2: 1896 | NG2: 1303 | NH2: 1253 | NI2: 1651 | NJ2: 1452 | NK2: 1036 | NL2: 1159 | NM2: 1008 | NN2: 1232 | NO2: 1098 | NP2: 1658 | NQ2: 1815 | NR2: 1207 | NS2: 1130 | NT2: 1403 | NU2: 1151 | NV2: 1053 | NW2: 1119 | NX2: 1672 | NY2: 1919 | NZ2: 1627 | OA2: 1586 | OB2: 1624 | OC2: 1967 | OD2: 1419 | OE2: 1421 | OF2: 1103 | OG2: 1851 | OH2: 1253 | OI2: 1226 | OJ2: 1111 | OK2: 1509 | OL2: 1472 | OM2: 1098 | ON2: 1152 | OO2: 1860 | OP2: 1913 | OQ2: 1895 | OR2: 1877 | OS2: 1337 | OT2: 1705 | OU2: 1821 | OV2: 1162 | OW2: 1719 | OX2: 1956 | OY2: 1680 | OZ2: 1995 | PA2: 1160 | PB2: 1579 | PC2: 1800 | PD2: 1397 | PE2: 1276 | PF2: 1815 | PG2: 1915 | PH2: 1503 | PI2: 1895 | PJ2: 1391 | PK2: 1134 | PL2: 1194 | PM2: 1400 | PN2: 1639 | PO2: 1032 | PP2: 1687 | PQ2: 1459 | PR2: 1954 | PS2: 1882 | PT2: 1469 | PU2: 1374 | PV2: 1021 | PW2: 1749 | PX2: 1669 | PY2: 1037 | PZ2: 1229 | QA2: 1364 | QB2: 1562 | QC2: 1437 | QD2: 1775 | QE2: 1282 | QF2: 1026 | QG2: 1225 | QH2: 1276 | QI2: 1797 | QJ2: 1608 | QK2: 1283 | QL2: 1878 | QM2: 1959 | QN2: 1480 | QO2: 1452 | QP2: 1828 | QQ2: 1815 | QR2: 1658 | QS2: 1515 | QT2: 1546 | QU2: 1191 | QV2: 1048 | QW2: 1511 | QX2: 1016 | QY2: 1171 | QZ2: 1219 | RA2: 1157 | RB2: 1476 | RC2: 1045 | RD2: 1372 | RE2: 1517 | RF2: 1098 | RG2: 1891 | RH2: 1744 | RI2: 1036 | RJ2: 1279 | RK2: 1348 | RL2: 1496 | RM2: 1301 | RN2: 1180 | RO2: 1606 | RP2: 1098 | RQ2: 1699 | RR2: 1992 | RS2: 1115 | RT2: 1190 | RU2: 1252 | RV2: 1980 | RW2: 1927 | RX2: 1982 | RY2: 1160 | RZ2: 1255 | SA2: 1322 | SB2: 1127 | SC2: 1017 | SD2: 1792 | SE2: 1734 | SF2: 1565 | SG2: 1569
A3: Order Date | B3: 45197 | C3: 45199 | D3: 45109 | E3: 45079 | F3: 45241 | G3: 45260 | H3: 45050 | I3: 45040 | J3: 45204 | K3: 45139 | L3: 45098 | M3: 45214 | N3: 45100 | O3: 45039 | P3: 45048 | Q3: 44958 | R3: 45148 | S3: 45045 | T3: 44965 | U3: 45194 | V3: 45159 | W3: 44944 | X3: 45075 | Y3: 45075 | Z3: 45052 | AA3: 45228 | AB3: 45286 | AC3: 45164 | AD3: 45061 | AE3: 45077 | AF3: 45162 | AG3: 45150 | AH3: 45129 | AI3: 45182 | AJ3: 45012 | AK3: 45076 | AL3: 45161 | AM3: 45271 | AN3: 44948 | AO3: 45274 | AP3: 45211 | AQ3: 45195 | AR3: 45184 | AS3: 44955 | AT3: 45139 | AU3: 45209 | AV3: 44976 | AW3: 45021 | AX3: 45014 | AY3: 44970 | AZ3: 45204 | BA3: 45097 | BB3: 45115 | BC3: 45279 | BD3: 45110 | BE3: 44929 | BF3: 45117 | BG3: 45044 | BH3: 44945 | BI3: 44949 | BJ3: 44956 | BK3: 45221 | BL3: 45034 | BM3: 45207 | BN3: 45054 | BO3: 45155 | BP3: 45037 | BQ3: 45062 | BR3: 45288 | BS3: 45112 | BT3: 45070 | BU3: 44998 | BV3: 45055 | BW3: 45290 | BX3: 45187 | BY3: 44929 | BZ3: 45030 | CA3: 45150 | CB3: 45246 | CC3: 45288 | CD3: 45280 | CE3: 44936 | CF3: 45228 | CG3: 45157 | CH3: 45145 | CI3: 44992 | CJ3: 45038 | CK3: 44939 | CL3: 45012 | CM3: 45160 | CN3: 45016 | CO3: 45240 | CP3: 44980 | CQ3: 44938 | CR3: 45135 | CS3: 44940 | CT3: 45047 | CU3: 44946 | CV3: 45001 | CW3: 45169 | CX3: 45149 | CY3: 44996 | CZ3: 45238 | DA3: 45137 | DB3: 45027 | DC3: 45112 | DD3: 45058 | DE3: 45037 | DF3: 45058 | DG3: 44946 | DH3: 44950 | DI3: 45153 | DJ3: 45080 | DK3: 45219 | DL3: 45156 | DM3: 45236 | DN3: 45285 | DO3: 45128 | DP3: 44964 | DQ3: 45186 | DR3: 45114 | DS3: 44983 | DT3: 44946 | DU3: 45199 | DV3: 45045 | DW3: 44997 | DX3: 44930 | DY3: 45147 | DZ3: 44940 | EA3: 44929 | EB3: 45142 | EC3: 45155 | ED3: 45262 | EE3: 45112 | EF3: 44981 | EG3: 45180 | EH3: 44950 | EI3: 45088 | EJ3: 45084 | EK3: 45008 | EL3: 45085 | EM3: 45114 | EN3: 44986 | EO3: 45231 | EP3: 45245 | EQ3: 45137 | ER3: 45078 | ES3: 45035 | ET3: 45002 | EU3: 44956 | EV3: 45240 | EW3: 45043 | EX3: 45282 | EY3: 45118 | EZ3: 44945 | FA3: 45099 | FB3: 45154 | FC3: 45276 | FD3: 45109 | FE3: 45039 | FF3: 45109 | FG3: 45072 | FH3: 45245 | FI3: 45042 | FJ3: 45039 | FK3: 45177 | FL3: 45177 | FM3: 45229 | FN3: 45239 | FO3: 45044 | FP3: 45227 | FQ3: 45087 | FR3: 45124 | FS3: 45186 | FT3: 45074 | FU3: 45166 | FV3: 44973 | FW3: 45124 | FX3: 44973 | FY3: 45004 | FZ3: 45050 | GA3: 45001 | GB3: 45285 | GC3: 45063 | GD3: 45016 | GE3: 45251 | GF3: 44987 | GG3: 45064 | GH3: 44976 | GI3: 45185 | GJ3: 45033 | GK3: 45039 | GL3: 45276 | GM3: 45180 | GN3: 45044 | GO3: 45124 | GP3: 45263 | GQ3: 45291 | GR3: 44977 | GS3: 45171 | GT3: 44961 | GU3: 45228 | GV3: 44995 | GW3: 45275 | GX3: 45246 | GY3: 44975 | GZ3: 45000 | HA3: 45118 | HB3: 45187 | HC3: 45282 | HD3: 44996 | HE3: 45016 | HF3: 45186 | HG3: 45052 | HH3: 45157 | HI3: 45221 | HJ3: 45055 | HK3: 45206 | HL3: 45239 | HM3: 45026 | HN3: 45252 | HO3: 45223 | HP3: 45108 | HQ3: 45100 | HR3: 45242 | HS3: 45290 | HT3: 45114 | HU3: 44983 | HV3: 44957 | HW3: 45010 | HX3: 45078 | HY3: 44962 | HZ3: 45139 | IA3: 45290 | IB3: 45032 | IC3: 45268 | ID3: 45146 | IE3: 45089 | IF3: 45146 | IG3: 45196 | IH3: 45046 | II3: 45262 | IJ3: 45108 | IK3: 45032 | IL3: 45143 | IM3: 45131 | IN3: 44996 | IO3: 44970 | IP3: 45255 | IQ3: 45227 | IR3: 45154 | IS3: 45110 | IT3: 45033 | IU3: 45010 | IV3: 45264 | IW3: 45176 | IX3: 45289 | IY3: 44947 | IZ3: 45122 | JA3: 45104 | JB3: 44933 | JC3: 44996 | JD3: 45053 | JE3: 45086 | JF3: 45174 | JG3: 45129 | JH3: 45074 | JI3: 45069 | JJ3: 45125 | JK3: 45080 | JL3: 45068 | JM3: 45239 | JN3: 45091 | JO3: 45240 | JP3: 44947 | JQ3: 45008 | JR3: 44995 | JS3: 45057 | JT3: 45013 | JU3: 45144 | JV3: 45231 | JW3: 45271 | JX3: 45267 | JY3: 45087 | JZ3: 45104 | KA3: 45043 | KB3: 45122 | KC3: 45253 | KD3: 45012 | KE3: 45215 | KF3: 45007 | KG3: 45078 | KH3: 44987 | KI3: 44987 | KJ3: 45280 | KK3: 44954 | KL3: 44969 | KM3: 45095 | KN3: 45012 | KO3: 45103 | KP3: 44943 | KQ3: 45024 | KR3: 45124 | KS3: 45024 | KT3: 44991 | KU3: 45256 | KV3: 45267 | KW3: 44931 | KX3: 44928 | KY3: 44948 | KZ3: 45038 | LA3: 44983 | LB3: 44992 | LC3: 45256 | LD3: 45024 | LE3: 45070 | LF3: 45051 | LG3: 45093 | LH3: 45012 | LI3: 45002 | LJ3: 45270 | LK3: 45220 | LL3: 44985 | LM3: 45064 | LN3: 45025 | LO3: 45118 | LP3: 45169 | LQ3: 45245 | LR3: 44975 | LS3: 44958 | LT3: 45203 | LU3: 44946 | LV3: 45080 | LW3: 44994 | LX3: 45140 | LY3: 45069 | LZ3: 45158 | MA3: 45139 | MB3: 45005 | MC3: 45140 | MD3: 45042 | ME3: 45018 | MF3: 45196 | MG3: 45094 | MH3: 44984 | MI3: 45210 | MJ3: 44952 | MK3: 44992 | ML3: 45174 | MM3: 45180 | MN3: 44970 | MO3: 45023 | MP3: 44968 | MQ3: 45153 | MR3: 45188 | MS3: 45093 | MT3: 45205 | MU3: 45015 | MV3: 45104 | MW3: 45123 | MX3: 45233 | MY3: 45193 | MZ3: 45194 | NA3: 45000 | NB3: 44934 | NC3: 45223 | ND3: 45090 | NE3: 45011 | NF3: 44998 | NG3: 44981 | NH3: 44973 | NI3: 45164 | NJ3: 45030 | NK3: 45136 | NL3: 44968 | NM3: 45242 | NN3: 45194 | NO3: 45189 | NP3: 45262 | NQ3: 45291 | NR3: 45185 | NS3: 45209 | NT3: 45040 | NU3: 45289 | NV3: 44966 | NW3: 45146 | NX3: 45055 | NY3: 44934 | NZ3: 45027 | OA3: 45102 | OB3: 45033 | OC3: 45027 | OD3: 45186 | OE3: 45172 | OF3: 45201 | OG3: 44958 | OH3: 45063 | OI3: 44938 | OJ3: 45228 | OK3: 44942 | OL3: 45055 | OM3: 44989 | ON3: 45035 | OO3: 44947 | OP3: 45084 | OQ3: 45195 | OR3: 45088 | OS3: 45186 | OT3: 45028 | OU3: 45149 | OV3: 44985 | OW3: 45173 | OX3: 45054 | OY3: 45209 | OZ3: 45251 | PA3: 44951 | PB3: 45057 | PC3: 45279 | PD3: 45122 | PE3: 45207 | PF3: 45080 | PG3: 45059 | PH3: 45153 | PI3: 45115 | PJ3: 45191 | PK3: 45060 | PL3: 45137 | PM3: 44986 | PN3: 45290 | PO3: 45290 | PP3: 45139 | PQ3: 45142 | PR3: 45152 | PS3: 45057 | PT3: 45002 | PU3: 45212 | PV3: 45203 | PW3: 45082 | PX3: 45174 | PY3: 45144 | PZ3: 45116 | QA3: 45089 | QB3: 45106 | QC3: 44960 | QD3: 44967 | QE3: 45233 | QF3: 45264 | QG3: 45240 | QH3: 45001 | QI3: 45205 | QJ3: 45102 | QK3: 45076 | QL3: 45199 | QM3: 45251 | QN3: 45034 | QO3: 45065 | QP3: 45276 | QQ3: 45197 | QR3: 45273 | QS3: 45215 | QT3: 45138 | QU3: 45198 | QV3: 44992 | QW3: 45174 | QX3: 45082 | QY3: 44973 | QZ3: 45127 | RA3: 45074 | RB3: 45050 | RC3: 44927 | RD3: 45173 | RE3: 45269 | RF3: 45054 | RG3: 45117 | RH3: 44993 | RI3: 44930 | RJ3: 45229 | RK3: 45220 | RL3: 45069 | RM3: 45117 | RN3: 44947 | RO3: 45153 | RP3: 45239 | RQ3: 45043 | RR3: 45228 | RS3: 45068 | RT3: 44965 | RU3: 45281 | RV3: 45178 | RW3: 45259 | RX3: 45133 | RY3: 45136 | RZ3: 45041 | SA3: 45151 | SB3: 45060 | SC3: 45177 | SD3: 45145 | SE3: 45017 | SF3: 45280 | SG3: 44972
A4: Ship Date | B4: 45203 | C4: 45203 | D4: 45114 | E4: 45087 | F4: 45244 | G4: 45263 | H4: 45054 | I4: 45041 | J4: 45213 | K4: 45147 | L4: 45106 | M4: 45220 | N4: 45107 | O4: 45045 | P4: 45057 | Q4: 44961 | R4: 45151 | S4: 45048 | T4: 44968 | U4: 45203 | V4: 45163 | W4: 44951 | X4: 45084 | Y4: 45082 | Z4: 45061 | AA4: 45231 | AB4: 45290 | AC4: 45172 | AD4: 45067 | AE4: 45082 | AF4: 45166 | AG4: 45158 | AH4: 45130 | AI4: 45191 | AJ4: 45013 | AK4: 45084 | AL4: 45165 | AM4: 45280 | AN4: 44953 | AO4: 45277 | AP4: 45220 | AQ4: 45204 | AR4: 45188 | AS4: 44959 | AT4: 45147 | AU4: 45211 | AV4: 44985 | AW4: 45027 | AX4: 45023 | AY4: 44978 | AZ4: 45211 | BA4: 45098 | BB4: 45118 | BC4: 45281 | BD4: 45115 | BE4: 44934 | BF4: 45122 | BG4: 45048 | BH4: 44950 | BI4: 44952 | BJ4: 44957 | BK4: 45226 | BL4: 45043 | BM4: 45216 | BN4: 45058 | BO4: 45158 | BP4: 45038 | BQ4: 45064 | BR4: 45296 | BS4: 45113 | BT4: 45078 | BU4: 45005 | BV4: 45063 | BW4: 45296 | BX4: 45196 | BY4: 44932 | BZ4: 45034 | CA4: 45156 | CB4: 45254 | CC4: 45293 | CD4: 45283 | CE4: 44942 | CF4: 45232 | CG4: 45166 | CH4: 45148 | CI4: 44996 | CJ4: 45045 | CK4: 44946 | CL4: 45016 | CM4: 45166 | CN4: 45019 | CO4: 45246 | CP4: 44982 | CQ4: 44946 | CR4: 45137 | CS4: 44947 | CT4: 45056 | CU4: 44947 | CV4: 45009 | CW4: 45176 | CX4: 45155 | CY4: 45002 | CZ4: 45244 | DA4: 45146 | DB4: 45029 | DC4: 45113 | DD4: 45064 | DE4: 45045 | DF4: 45061 | DG4: 44947 | DH4: 44959 | DI4: 45154 | DJ4: 45083 | DK4: 45227 | DL4: 45159 | DM4: 45240 | DN4: 45293 | DO4: 45129 | DP4: 44970 | DQ4: 45187 | DR4: 45115 | DS4: 44991 | DT4: 44950 | DU4: 45200 | DV4: 45052 | DW4: 45002 | DX4: 44935 | DY4: 45148 | DZ4: 44946 | EA4: 44938 | EB4: 45151 | EC4: 45163 | ED4: 45267 | EE4: 45113 | EF4: 44990 | EG4: 45181 | EH4: 44958 | EI4: 45093 | EJ4: 45087 | EK4: 45015 | EL4: 45092 | EM4: 45123 | EN4: 44993 | EO4: 45234 | EP4: 45246 | EQ4: 45145 | ER4: 45081 | ES4: 45043 | ET4: 45010 | EU4: 44961 | EV4: 45241 | EW4: 45050 | EX4: 45287 | EY4: 45126 | EZ4: 44954 | FA4: 45106 | FB4: 45161 | FC4: 45277 | FD4: 45113 | FE4: 45041 | FF4: 45111 | FG4: 45074 | FH4: 45249 | FI4: 45043 | FJ4: 45043 | FK4: 45179 | FL4: 45182 | FM4: 45232 | FN4: 45247 | FO4: 45048 | FP4: 45228 | FQ4: 45088 | FR4: 45127 | FS4: 45195 | FT4: 45081 | FU4: 45168 | FV4: 44982 | FW4: 45126 | FX4: 44976 | FY4: 45006 | FZ4: 45053 | GA4: 45007 | GB4: 45294 | GC4: 45072 | GD4: 45023 | GE4: 45254 | GF4: 44991 | GG4: 45070 | GH4: 44981 | GI4: 45187 | GJ4: 45039 | GK4: 45042 | GL4: 45284 | GM4: 45182 | GN4: 45045 | GO4: 45133 | GP4: 45266 | GQ4: 45292 | GR4: 44984 | GS4: 45176 | GT4: 44966 | GU4: 45229 | GV4: 45004 | GW4: 45282 | GX4: 45254 | GY4: 44984 | GZ4: 45006 | HA4: 45123 | HB4: 45193 | HC4: 45284 | HD4: 45000 | HE4: 45019 | HF4: 45193 | HG4: 45061 | HH4: 45162 | HI4: 45227 | HJ4: 45057 | HK4: 45209 | HL4: 45242 | HM4: 45035 | HN4: 45259 | HO4: 45231 | HP4: 45117 | HQ4: 45106 | HR4: 45246 | HS4: 45291 | HT4: 45122 | HU4: 44990 | HV4: 44959 | HW4: 45018 | HX4: 45083 | HY4: 44969 | HZ4: 45143 | IA4: 45295 | IB4: 45040 | IC4: 45269 | ID4: 45147 | IE4: 45093 | IF4: 45149 | IG4: 45198 | IH4: 45049 | II4: 45263 | IJ4: 45109 | IK4: 45038 | IL4: 45148 | IM4: 45139 | IN4: 44998 | IO4: 44974 | IP4: 45263 | IQ4: 45233 | IR4: 45155 | IS4: 45114 | IT4: 45034 | IU4: 45012 | IV4: 45269 | IW4: 45184 | IX4: 45297 | IY4: 44950 | IZ4: 45126 | JA4: 45110 | JB4: 44936 | JC4: 44998 | JD4: 45059 | JE4: 45091 | JF4: 45179 | JG4: 45134 | JH4: 45079 | JI4: 45072 | JJ4: 45132 | JK4: 45086 | JL4: 45072 | JM4: 45241 | JN4: 45100 | JO4: 45241 | JP4: 44951 | JQ4: 45009 | JR4: 45001 | JS4: 45061 | JT4: 45018 | JU4: 45149 | JV4: 45240 | JW4: 45272 | JX4: 45269 | JY4: 45093 | JZ4: 45109 | KA4: 45050 | KB4: 45125 | KC4: 45256 | KD4: 45014 | KE4: 45218 | KF4: 45008 | KG4: 45083 | KH4: 44992 | KI4: 44994 | KJ4: 45284 | KK4: 44957 | KL4: 44970 | KM4: 45103 | KN4: 45015 | KO4: 45105 | KP4: 44947 | KQ4: 45027 | KR4: 45125 | KS4: 45027 | KT4: 44993 | KU4: 45264 | KV4: 45273 | KW4: 44940 | KX4: 44936 | KY4: 44951 | KZ4: 45043 | LA4: 44990 | LB4: 44997 | LC4: 45264 | LD4: 45029 | LE4: 45071 | LF4: 45056 | LG4: 45097 | LH4: 45018 | LI4: 45005 | LJ4: 45275 | LK4: 45222 | LL4: 44991 | LM4: 45070 | LN4: 45030 | LO4: 45124 | LP4: 45176 | LQ4: 45250 | LR4: 44976 | LS4: 44966 | LT4: 45207 | LU4: 44955 | LV4: 45086 | LW4: 44995 | LX4: 45143 | LY4: 45072 | LZ4: 45162 | MA4: 45145 | MB4: 45012 | MC4: 45144 | MD4: 45048 | ME4: 45019 | MF4: 45204 | MG4: 45101 | MH4: 44993 | MI4: 45213 | MJ4: 44954 | MK4: 44993 | ML4: 45177 | MM4: 45185 | MN4: 44972 | MO4: 45026 | MP4: 44972 | MQ4: 45160 | MR4: 45191 | MS4: 45102 | MT4: 45213 | MU4: 45019 | MV4: 45105 | MW4: 45124 | MX4: 45234 | MY4: 45194 | MZ4: 45202 | NA4: 45003 | NB4: 44940 | NC4: 45226 | ND4: 45095 | NE4: 45018 | NF4: 45000 | NG4: 44987 | NH4: 44979 | NI4: 45167 | NJ4: 45036 | NK4: 45141 | NL4: 44970 | NM4: 45251 | NN4: 45202 | NO4: 45192 | NP4: 45270 | NQ4: 45300 | NR4: 45188 | NS4: 45212 | NT4: 45042 | NU4: 45297 | NV4: 44967 | NW4: 45154 | NX4: 45062 | NY4: 44941 | NZ4: 45030 | OA4: 45103 | OB4: 45037 | OC4: 45036 | OD4: 45191 | OE4: 45173 | OF4: 45206 | OG4: 44966 | OH4: 45071 | OI4: 44943 | OJ4: 45237 | OK4: 44943 | OL4: 45059 | OM4: 44992 | ON4: 45037 | OO4: 44955 | OP4: 45091 | OQ4: 45204 | OR4: 45090 | OS4: 45190 | OT4: 45034 | OU4: 45152 | OV4: 44993 | OW4: 45176 | OX4: 45056 | OY4: 45212 | OZ4: 45257 | PA4: 44953 | PB4: 45065 | PC4: 45280 | PD4: 45129 | PE4: 45209 | PF4: 45086 | PG4: 45061 | PH4: 45155 | PI4: 45123 | PJ4: 45193 | PK4: 45067 | PL4: 45140 | PM4: 44994 | PN4: 45297 | PO4: 45298 | PP4: 45146 | PQ4: 45148 | PR4: 45159 | PS4: 45062 | PT4: 45009 | PU4: 45213 | PV4: 45204 | PW4: 45091 | PX4: 45179 | PY4: 45149 | PZ4: 45119 | QA4: 45094 | QB4: 45109 | QC4: 44969 | QD4: 44976 | QE4: 45239 | QF4: 45265 | QG4: 45247 | QH4: 45008 | QI4: 45209 | QJ4: 45110 | QK4: 45082 | QL4: 45203 | QM4: 45255 | QN4: 45036 | QO4: 45067 | QP4: 45280 | QQ4: 45202 | QR4: 45281 | QS4: 45221 | QT4: 45142 | QU4: 45205 | QV4: 45000 | QW4: 45176 | QX4: 45089 | QY4: 44975 | QZ4: 45129 | RA4: 45082 | RB4: 45052 | RC4: 44936 | RD4: 45174 | RE4: 45278 | RF4: 45055 | RG4: 45119 | RH4: 44999 | RI4: 44936 | RJ4: 45230 | RK4: 45227 | RL4: 45077 | RM4: 45119 | RN4: 44955 | RO4: 45162 | RP4: 45245 | RQ4: 45048 | RR4: 45237 | RS4: 45077 | RT4: 44966 | RU4: 45284 | RV4: 45187 | RW4: 45261 | RX4: 45137 | RY4: 45140 | RZ4: 45043 | SA4: 45154 | SB4: 45063 | SC4: 45178 | SD4: 45151 | SE4: 45025 | SF4: 45283 | SG4: 44977
A5: City | B5: Chennai | C5: Pune | D5: Chennai | E5: Bengaluru | F5: Kolkata | G5: Hyderabad | H5: Bengaluru | I5: Mumbai | J5: Chennai | K5: Bengaluru | L5: Bengaluru | M5: Mumbai | N5: Delhi | O5: Kolkata | P5: Hyderabad | Q5: Pune | R5: Delhi | S5: Chennai | T5: Bengaluru | U5: Mumbai | V5: Mumbai | W5: Kolkata | X5: Delhi | Y5: Pune | Z5: Kolkata | AA5: Bengaluru | AB5: Kolkata | AC5: Hyderabad | AD5: Mumbai | AE5: Mumbai | AF5: Chennai | AG5: Chennai | AH5: Pune | AI5: Bengaluru | AJ5: Hyderabad | AK5: Delhi | AL5: Kolkata | AM5: Pune | AN5: Bengaluru | AO5: Chennai | AP5: Kolkata | AQ5: Chennai | AR5: Kolkata | AS5: Delhi | AT5: Bengaluru | AU5: Kolkata | AV5: Hyderabad | AW5: Pune | AX5: Mumbai | AY5: Hyderabad | AZ5: Hyderabad | BA5: Pune | BB5: Mumbai | BC5: Hyderabad | BD5: Kolkata | BE5: Kolkata | BF5: Kolkata | BG5: Mumbai | BH5: Hyderabad | BI5: Mumbai | BJ5: Kolkata | BK5: Pune | BL5: Hyderabad | BM5: Hyderabad | BN5: Chennai | BO5: Chennai | BP5: Delhi | BQ5: Bengaluru | BR5: Chennai | BS5: Mumbai | BT5: Chennai | BU5: Delhi | BV5: Hyderabad | BW5: Delhi | BX5: Hyderabad | BY5: Pune | BZ5: Pune | CA5: Hyderabad | CB5: Bengaluru | CC5: Chennai | CD5: Mumbai | CE5: Mumbai | CF5: Kolkata | CG5: Hyderabad | CH5: Mumbai | CI5: Bengaluru | CJ5: Hyderabad | CK5: Bengaluru | CL5: Mumbai | CM5: Mumbai | CN5: Kolkata | CO5: Mumbai | CP5: Hyderabad | CQ5: Pune | CR5: Hyderabad | CS5: Hyderabad | CT5: Kolkata | CU5: Kolkata | CV5: Mumbai | CW5: Delhi | CX5: Delhi | CY5: Kolkata | CZ5: Mumbai | DA5: Delhi | DB5: Mumbai | DC5: Mumbai | DD5: Mumbai | DE5: Chennai | DF5: Hyderabad | DG5: Mumbai | DH5: Chennai | DI5: Kolkata | DJ5: Delhi | DK5: Hyderabad | DL5: Pune | DM5: Delhi | DN5: Hyderabad | DO5: Pune | DP5: Delhi | DQ5: Hyderabad | DR5: Delhi | DS5: Delhi | DT5: Pune | DU5: Delhi | DV5: Delhi | DW5: Pune | DX5: Kolkata | DY5: Mumbai | DZ5: Bengaluru | EA5: Chennai | EB5: Bengaluru | EC5: Bengaluru | ED5: Hyderabad | EE5: Mumbai | EF5: Hyderabad | EG5: Mumbai | EH5: Pune | EI5: Pune | EJ5: Mumbai | EK5: Delhi | EL5: Kolkata | EM5: Delhi | EN5: Kolkata | EO5: Hyderabad | EP5: Kolkata | EQ5: Hyderabad | ER5: Pune | ES5: Bengaluru | ET5: Pune | EU5: Pune | EV5: Bengaluru | EW5: Kolkata | EX5: Kolkata | EY5: Hyderabad | EZ5: Delhi | FA5: Hyderabad | FB5: Delhi | FC5: Pune | FD5: Bengaluru | FE5: Pune | FF5: Mumbai | FG5: Kolkata | FH5: Delhi | FI5: Hyderabad | FJ5: Bengaluru | FK5: Delhi | FL5: Hyderabad | FM5: Kolkata | FN5: Pune | FO5: Kolkata | FP5: Chennai | FQ5: Mumbai | FR5: Chennai | FS5: Bengaluru | FT5: Delhi | FU5: Bengaluru | FV5: Pune | FW5: Hyderabad | FX5: Kolkata | FY5: Chennai | FZ5: Chennai | GA5: Pune | GB5: Chennai | GC5: Pune | GD5: Bengaluru | GE5: Kolkata | GF5: Delhi | GG5: Hyderabad | GH5: Delhi | GI5: Bengaluru | GJ5: Hyderabad | GK5: Chennai | GL5: Mumbai | GM5: Bengaluru | GN5: Bengaluru | GO5: Kolkata | GP5: Delhi | GQ5: Bengaluru | GR5: Bengaluru | GS5: Chennai | GT5: Chennai | GU5: Hyderabad | GV5: Pune | GW5: Pune | GX5: Mumbai | GY5: Pune | GZ5: Kolkata | HA5: Mumbai | HB5: Hyderabad | HC5: Chennai | HD5: Pune | HE5: Delhi | HF5: Chennai | HG5: Kolkata | HH5: Chennai | HI5: Kolkata | HJ5: Kolkata | HK5: Kolkata | HL5: Hyderabad | HM5: Kolkata | HN5: Kolkata | HO5: Delhi | HP5: Mumbai | HQ5: Bengaluru | HR5: Mumbai | HS5: Kolkata | HT5: Delhi | HU5: Chennai | HV5: Delhi | HW5: Kolkata | HX5: Delhi | HY5: Pune | HZ5: Delhi | IA5: Kolkata | IB5: Hyderabad | IC5: Pune | ID5: Delhi | IE5: Bengaluru | IF5: Bengaluru | IG5: Delhi | IH5: Hyderabad | II5: Chennai | IJ5: Kolkata | IK5: Bengaluru | IL5: Chennai | IM5: Delhi | IN5: Chennai | IO5: Pune | IP5: Mumbai | IQ5: Bengaluru | IR5: Delhi | IS5: Kolkata | IT5: Hyderabad | IU5: Pune | IV5: Delhi | IW5: Kolkata | IX5: Hyderabad | IY5: Hyderabad | IZ5: Delhi | JA5: Pune | JB5: Chennai | JC5: Chennai | JD5: Hyderabad | JE5: Chennai | JF5: Mumbai | JG5: Hyderabad | JH5: Hyderabad | JI5: Kolkata | JJ5: Chennai | JK5: Pune | JL5: Hyderabad | JM5: Pune | JN5: Mumbai | JO5: Kolkata | JP5: Delhi | JQ5: Pune | JR5: Hyderabad | JS5: Mumbai | JT5: Bengaluru | JU5: Mumbai | JV5: Mumbai | JW5: Kolkata | JX5: Delhi | JY5: Bengaluru | JZ5: Chennai | KA5: Chennai | KB5: Pune | KC5: Mumbai | KD5: Kolkata | KE5: Kolkata | KF5: Chennai | KG5: Pune | KH5: Pune | KI5: Pune | KJ5: Bengaluru | KK5: Delhi | KL5: Bengaluru | KM5: Hyderabad | KN5: Hyderabad | KO5: Delhi | KP5: Chennai | KQ5: Delhi | KR5: Kolkata | KS5: Hyderabad | KT5: Mumbai | KU5: Mumbai | KV5: Chennai | KW5: Kolkata | KX5: Bengaluru | KY5: Kolkata | KZ5: Mumbai | LA5: Mumbai | LB5: Hyderabad | LC5: Kolkata | LD5: Kolkata | LE5: Mumbai | LF5: Bengaluru | LG5: Chennai | LH5: Pune | LI5: Chennai | LJ5: Kolkata | LK5: Chennai | LL5: Mumbai | LM5: Mumbai | LN5: Kolkata | LO5: Kolkata | LP5: Pune | LQ5: Pune | LR5: Hyderabad | LS5: Kolkata | LT5: Bengaluru | LU5: Chennai | LV5: Kolkata | LW5: Delhi | LX5: Hyderabad | LY5: Delhi | LZ5: Mumbai | MA5: Pune | MB5: Chennai | MC5: Kolkata | MD5: Delhi | ME5: Chennai | MF5: Mumbai | MG5: Pune | MH5: Bengaluru | MI5: Hyderabad | MJ5: Chennai | MK5: Chennai | ML5: Bengaluru | MM5: Chennai | MN5: Mumbai | MO5: Mumbai | MP5: Bengaluru | MQ5: Hyderabad | MR5: Kolkata | MS5: Delhi | MT5: Kolkata | MU5: Chennai | MV5: Delhi | MW5: Bengaluru | MX5: Bengaluru | MY5: Hyderabad | MZ5: Delhi | NA5: Mumbai | NB5: Delhi | NC5: Chennai | ND5: Mumbai | NE5: Pune | NF5: Pune | NG5: Pune | NH5: Bengaluru | NI5: Delhi | NJ5: Pune | NK5: Kolkata | NL5: Hyderabad | NM5: Kolkata | NN5: Pune | NO5: Hyderabad | NP5: Chennai | NQ5: Kolkata | NR5: Delhi | NS5: Delhi | NT5: Kolkata | NU5: Pune | NV5: Delhi | NW5: Chennai | NX5: Mumbai | NY5: Pune | NZ5: Chennai | OA5: Hyderabad | OB5: Chennai | OC5: Pune | OD5: Hyderabad | OE5: Pune | OF5: Delhi | OG5: Mumbai | OH5: Pune | OI5: Pune | OJ5: Delhi | OK5: Bengaluru | OL5: Delhi | OM5: Hyderabad | ON5: Delhi | OO5: Delhi | OP5: Mumbai | OQ5: Delhi | OR5: Pune | OS5: Mumbai | OT5: Kolkata | OU5: Bengaluru | OV5: Mumbai | OW5: Hyderabad | OX5: Kolkata | OY5: Mumbai | OZ5: Mumbai | PA5: Bengaluru | PB5: Pune | PC5: Hyderabad | PD5: Chennai | PE5: Chennai | PF5: Mumbai | PG5: Delhi | PH5: Hyderabad | PI5: Kolkata | PJ5: Delhi | PK5: Delhi | PL5: Hyderabad | PM5: Pune | PN5: Mumbai | PO5: Mumbai | PP5: Mumbai | PQ5: Mumbai | PR5: Chennai | PS5: Mumbai | PT5: Chennai | PU5: Chennai | PV5: Pune | PW5: Mumbai | PX5: Bengaluru | PY5: Kolkata | PZ5: Delhi | QA5: Chennai | QB5: Hyderabad | QC5: Hyderabad | QD5: Kolkata | QE5: Hyderabad | QF5: Bengaluru | QG5: Hyderabad | QH5: Delhi | QI5: Delhi | QJ5: Chennai | QK5: Mumbai | QL5: Pune | QM5: Bengaluru | QN5: Chennai | QO5: Bengaluru | QP5: Mumbai | QQ5: Hyderabad | QR5: Hyderabad | QS5: Pune | QT5: Mumbai | QU5: Chennai | QV5: Pune | QW5: Mumbai | QX5: Kolkata | QY5: Delhi | QZ5: Pune | RA5: Pune | RB5: Chennai | RC5: Bengaluru | RD5: Kolkata | RE5: Chennai | RF5: Mumbai | RG5: Mumbai | RH5: Mumbai | RI5: Mumbai | RJ5: Bengaluru | RK5: Kolkata | RL5: Hyderabad | RM5: Delhi | RN5: Bengaluru | RO5: Bengaluru | RP5: Hyderabad | RQ5: Hyderabad | RR5: Delhi | RS5: Delhi | RT5: Hyderabad | RU5: Mumbai | RV5: Bengaluru | RW5: Chennai | RX5: Delhi | RY5: Delhi | RZ5: Hyderabad | SA5: Kolkata | SB5: Chennai | SC5: Chennai | SD5: Delhi | SE5: Mumbai | SF5: Kolkata | SG5: Chennai
A6: State | B6: Delhi | C6: Tamil Nadu | D6: West Bengal | E6: West Bengal | F6: Karnataka | G6: Telangana | H6: Telangana | I6: Delhi | J6: West Bengal | K6: Karnataka | L6: Karnataka | M6: Tamil Nadu | N6: Tamil Nadu | O6: Karnataka | P6: Tamil Nadu | Q6: West Bengal | R6: Maharashtra | S6: West Bengal | T6: Karnataka | U6: Karnataka | V6: West Bengal | W6: Tamil Nadu | X6: Tamil Nadu | Y6: Telangana | Z6: Karnataka | AA6: Delhi | AB6: Telangana | AC6: Tamil Nadu | AD6: West Bengal | AE6: Tamil Nadu | AF6: West Bengal | AG6: Telangana | AH6: Karnataka | AI6: Tamil Nadu | AJ6: West Bengal | AK6: Karnataka | AL6: Delhi | AM6: West Bengal | AN6: Telangana | AO6: Delhi | AP6: Delhi | AQ6: Maharashtra | AR6: Tamil Nadu | AS6: West Bengal | AT6: Delhi | AU6: Maharashtra | AV6: Telangana | AW6: Karnataka | AX6: West Bengal | AY6: Delhi | AZ6: Tamil Nadu | BA6: Maharashtra | BB6: Delhi | BC6: Tamil Nadu | BD6: Delhi | BE6: West Bengal | BF6: West Bengal | BG6: West Bengal | BH6: Telangana | BI6: Telangana | BJ6: Maharashtra | BK6: West Bengal | BL6: Tamil Nadu | BM6: Delhi | BN6: Karnataka | BO6: Tamil Nadu | BP6: Telangana | BQ6: Telangana | BR6: Tamil Nadu | BS6: Telangana | BT6: West Bengal | BU6: Maharashtra | BV6: Delhi | BW6: Maharashtra | BX6: Delhi | BY6: Delhi | BZ6: Maharashtra | CA6: Tamil Nadu | CB6: Delhi | CC6: Maharashtra | CD6: Delhi | CE6: Karnataka | CF6: Tamil Nadu | CG6: West Bengal | CH6: Delhi | CI6: Karnataka | CJ6: West Bengal | CK6: West Bengal | CL6: Delhi | CM6: Maharashtra | CN6: Delhi | CO6: Karnataka | CP6: West Bengal | CQ6: Delhi | CR6: Maharashtra | CS6: Delhi | CT6: Tamil Nadu | CU6: Maharashtra | CV6: Karnataka | CW6: West Bengal | CX6: Delhi | CY6: Maharashtra | CZ6: Tamil Nadu | DA6: Maharashtra | DB6: Telangana | DC6: Tamil Nadu | DD6: Karnataka | DE6: West Bengal | DF6: Karnataka | DG6: Delhi | DH6: Maharashtra | DI6: Telangana | DJ6: Tamil Nadu | DK6: Tamil Nadu | DL6: Maharashtra | DM6: Telangana | DN6: Maharashtra | DO6: Delhi | DP6: Karnataka | DQ6: Tamil Nadu | DR6: Delhi | DS6: Karnataka | DT6: Delhi | DU6: Telangana | DV6: Tamil Nadu | DW6: Maharashtra | DX6: Maharashtra | DY6: Karnataka | DZ6: West Bengal | EA6: Telangana | EB6: Karnataka | EC6: West Bengal | ED6: Delhi | EE6: Telangana | EF6: Delhi | EG6: Tamil Nadu | EH6: Telangana | EI6: West Bengal | EJ6: Tamil Nadu | EK6: Maharashtra | EL6: West Bengal | EM6: Karnataka | EN6: Maharashtra | EO6: Maharashtra | EP6: Karnataka | EQ6: Telangana | ER6: Maharashtra | ES6: West Bengal | ET6: Tamil Nadu | EU6: Maharashtra | EV6: West Bengal | EW6: Delhi | EX6: West Bengal | EY6: Tamil Nadu | EZ6: West Bengal | FA6: Karnataka | FB6: Tamil Nadu | FC6: Telangana | FD6: Delhi | FE6: Karnataka | FF6: Telangana | FG6: West Bengal | FH6: Tamil Nadu | FI6: Delhi | FJ6: Karnataka | FK6: Telangana | FL6: Telangana | FM6: Delhi | FN6: West Bengal | FO6: Delhi | FP6: Telangana | FQ6: Maharashtra | FR6: Karnataka | FS6: Delhi | FT6: Telangana | FU6: West Bengal | FV6: Telangana | FW6: West Bengal | FX6: Delhi | FY6: West Bengal | FZ6: Tamil Nadu | GA6: Tamil Nadu | GB6: Tamil Nadu | GC6: Maharashtra | GD6: Delhi | GE6: Telangana | GF6: Telangana | GG6: Maharashtra | GH6: West Bengal | GI6: Maharashtra | GJ6: West Bengal | GK6: West Bengal | GL6: Karnataka | GM6: Telangana | GN6: Tamil Nadu | GO6: West Bengal | GP6: Karnataka | GQ6: Telangana | GR6: Tamil Nadu | GS6: West Bengal | GT6: West Bengal | GU6: Maharashtra | GV6: Maharashtra | GW6: Telangana | GX6: Tamil Nadu | GY6: West Bengal | GZ6: Telangana | HA6: Telangana | HB6: Delhi | HC6: Maharashtra | HD6: Tamil Nadu | HE6: West Bengal | HF6: Telangana | HG6: West Bengal | HH6: Delhi | HI6: Tamil Nadu | HJ6: Telangana | HK6: West Bengal | HL6: Maharashtra | HM6: Delhi | HN6: Tamil Nadu | HO6: Delhi | HP6: Maharashtra | HQ6: Tamil Nadu | HR6: Delhi | HS6: Karnataka | HT6: Maharashtra | HU6: Maharashtra | HV6: Maharashtra | HW6: Karnataka | HX6: Karnataka | HY6: West Bengal | HZ6: Telangana | IA6: Delhi | IB6: West Bengal | IC6: Delhi | ID6: Telangana | IE6: Karnataka | IF6: Telangana | IG6: Karnataka | IH6: Telangana | II6: West Bengal | IJ6: Tamil Nadu | IK6: West Bengal | IL6: Delhi | IM6: West Bengal | IN6: Maharashtra | IO6: Delhi | IP6: Telangana | IQ6: Delhi | IR6: Tamil Nadu | IS6: Karnataka | IT6: Telangana | IU6: Delhi | IV6: Telangana | IW6: Telangana | IX6: Telangana | IY6: Karnataka | IZ6: West Bengal | JA6: Telangana | JB6: Maharashtra | JC6: Tamil Nadu | JD6: Karnataka | JE6: Delhi | JF6: Karnataka | JG6: Delhi | JH6: Karnataka | JI6: Delhi | JJ6: Telangana | JK6: West Bengal | JL6: Delhi | JM6: Delhi | JN6: Maharashtra | JO6: Delhi | JP6: Maharashtra | JQ6: Tamil Nadu | JR6: Telangana | JS6: Maharashtra | JT6: West Bengal | JU6: Telangana | JV6: Maharashtra | JW6: Telangana | JX6: Telangana | JY6: Telangana | JZ6: Tamil Nadu | KA6: West Bengal | KB6: Karnataka | KC6: Karnataka | KD6: Maharashtra | KE6: Telangana | KF6: Maharashtra | KG6: Tamil Nadu | KH6: Tamil Nadu | KI6: Delhi | KJ6: Tamil Nadu | KK6: Delhi | KL6: West Bengal | KM6: Maharashtra | KN6: West Bengal | KO6: Tamil Nadu | KP6: West Bengal | KQ6: West Bengal | KR6: West Bengal | KS6: Tamil Nadu | KT6: Telangana | KU6: West Bengal | KV6: Delhi | KW6: Tamil Nadu | KX6: West Bengal | KY6: Telangana | KZ6: Tamil Nadu | LA6: Karnataka | LB6: Telangana | LC6: Delhi | LD6: West Bengal | LE6: Karnataka | LF6: Karnataka | LG6: Tamil Nadu | LH6: Karnataka | LI6: Delhi | LJ6: Delhi | LK6: Maharashtra | LL6: Delhi | LM6: Telangana | LN6: Karnataka | LO6: Delhi | LP6: Tamil Nadu | LQ6: Maharashtra | LR6: Karnataka | LS6: Maharashtra | LT6: Karnataka | LU6: Tamil Nadu | LV6: Maharashtra | LW6: West Bengal | LX6: Telangana | LY6: Telangana | LZ6: Karnataka | MA6: West Bengal | MB6: Maharashtra | MC6: West Bengal | MD6: West Bengal | ME6: Maharashtra | MF6: Tamil Nadu | MG6: West Bengal | MH6: West Bengal | MI6: Tamil Nadu | MJ6: West Bengal | MK6: West Bengal | ML6: West Bengal | MM6: Telangana | MN6: Delhi | MO6: Tamil Nadu | MP6: West Bengal | MQ6: Telangana | MR6: Tamil Nadu | MS6: Karnataka | MT6: Karnataka | MU6: West Bengal | MV6: Telangana | MW6: Telangana | MX6: Tamil Nadu | MY6: Tamil Nadu | MZ6: Telangana | NA6: Tamil Nadu | NB6: Telangana | NC6: Delhi | ND6: Telangana | NE6: Karnataka | NF6: Tamil Nadu | NG6: Telangana | NH6: Telangana | NI6: Tamil Nadu | NJ6: Delhi | NK6: Delhi | NL6: Tamil Nadu | NM6: Maharashtra | NN6: Tamil Nadu | NO6: Tamil Nadu | NP6: Delhi | NQ6: Delhi | NR6: Tamil Nadu | NS6: Tamil Nadu | NT6: Tamil Nadu | NU6: Delhi | NV6: Tamil Nadu | NW6: Tamil Nadu | NX6: West Bengal | NY6: Maharashtra | NZ6: Karnataka | OA6: Maharashtra | OB6: West Bengal | OC6: Karnataka | OD6: Tamil Nadu | OE6: West Bengal | OF6: Tamil Nadu | OG6: Delhi | OH6: Telangana | OI6: West Bengal | OJ6: Delhi | OK6: West Bengal | OL6: West Bengal | OM6: Delhi | ON6: Karnataka | OO6: Maharashtra | OP6: Tamil Nadu | OQ6: West Bengal | OR6: Tamil Nadu | OS6: Telangana | OT6: Delhi | OU6: Tamil Nadu | OV6: Delhi | OW6: Tamil Nadu | OX6: Maharashtra | OY6: Maharashtra | OZ6: Maharashtra | PA6: Maharashtra | PB6: Maharashtra | PC6: Maharashtra | PD6: Delhi | PE6: West Bengal | PF6: Tamil Nadu | PG6: Maharashtra | PH6: Delhi | PI6: Delhi | PJ6: Delhi | PK6: West Bengal | PL6: Tamil Nadu | PM6: West Bengal | PN6: Karnataka | PO6: Delhi | PP6: Karnataka | PQ6: Telangana | PR6: Maharashtra | PS6: Maharashtra | PT6: West Bengal | PU6: Tamil Nadu | PV6: Karnataka | PW6: Tamil Nadu | PX6: West Bengal | PY6: Maharashtra | PZ6: Tamil Nadu | QA6: Tamil Nadu | QB6: Maharashtra | QC6: Karnataka | QD6: Maharashtra | QE6: Tamil Nadu | QF6: Karnataka | QG6: Karnataka | QH6: Maharashtra | QI6: Tamil Nadu | QJ6: West Bengal | QK6: Tamil Nadu | QL6: Delhi | QM6: Telangana | QN6: West Bengal | QO6: Karnataka | QP6: West Bengal | QQ6: Karnataka | QR6: Karnataka | QS6: West Bengal | QT6: Karnataka | QU6: Karnataka | QV6: Delhi | QW6: Tamil Nadu | QX6: Tamil Nadu | QY6: Telangana | QZ6: Telangana | RA6: Delhi | RB6: Telangana | RC6: West Bengal | RD6: Maharashtra | RE6: Maharashtra | RF6: Maharashtra | RG6: Delhi | RH6: Delhi | RI6: Karnataka | RJ6: Maharashtra | RK6: West Bengal | RL6: Telangana | RM6: West Bengal | RN6: Telangana | RO6: Maharashtra | RP6: Maharashtra | RQ6: Maharashtra | RR6: Delhi | RS6: Telangana | RT6: Delhi | RU6: Delhi | RV6: Tamil Nadu | RW6: West Bengal | RX6: West Bengal | RY6: Karnataka | RZ6: Delhi | SA6: Telangana | SB6: Tamil Nadu | SC6: Tamil Nadu | SD6: West Bengal | SE6: Delhi | SF6: Karnataka | SG6: Delhi
A7: Sales Channel | B7: Mobile App | C7: Website | D7: Marketplace | E7: Website | F7: Marketplace | G7: Website | H7: Mobile App | I7: Website | J7: Website | K7: Website | L7: Mobile App | M7: Website | N7: Mobile App | O7: Marketplace | P7: Website | Q7: Mobile App | R7: Mobile App | S7: Website | T7: Marketplace | U7: Mobile App | V7: Website | W7: Marketplace | X7: Mobile App | Y7: Mobile App | Z7: Marketplace | AA7: Marketplace | AB7: Website | AC7: Website | AD7: Mobile App | AE7: Marketplace | AF7: Marketplace | AG7: Marketplace | AH7: Mobile App | AI7: Marketplace | AJ7: Marketplace | AK7: Mobile App | AL7: Website | AM7: Website | AN7: Mobile App | AO7: Marketplace | AP7: Mobile App | AQ7: Website | AR7: Website | AS7: Mobile App | AT7: Mobile App | AU7: Website | AV7: Mobile App | AW7: Website | AX7: Mobile App | AY7: Mobile App | AZ7: Mobile App | BA7: Website | BB7: Mobile App | BC7: Website | BD7: Website | BE7: Mobile App | BF7: Mobile App | BG7: Website | BH7: Website | BI7: Marketplace | BJ7: Website | BK7: Marketplace | BL7: Marketplace | BM7: Marketplace | BN7: Mobile App | BO7: Mobile App | BP7: Website | BQ7: Marketplace | BR7: Mobile App | BS7: Mobile App | BT7: Mobile App | BU7: Mobile App | BV7: Mobile App | BW7: Marketplace | BX7: Marketplace | BY7: Marketplace | BZ7: Marketplace | CA7: Website | CB7: Marketplace | CC7: Mobile App | CD7: Marketplace | CE7: Website | CF7: Mobile App | CG7: Marketplace | CH7: Marketplace | CI7: Marketplace | CJ7: Mobile App | CK7: Mobile App | CL7: Website | CM7: Mobile App | CN7: Mobile App | CO7: Marketplace | CP7: Mobile App | CQ7: Marketplace | CR7: Marketplace | CS7: Mobile App | CT7: Website | CU7: Website | CV7: Mobile App | CW7: Website | CX7: Marketplace | CY7: Marketplace | CZ7: Mobile App | DA7: Website | DB7: Website | DC7: Marketplace | DD7: Mobile App | DE7: Website | DF7: Mobile App | DG7: Website | DH7: Marketplace | DI7: Marketplace | DJ7: Mobile App | DK7: Marketplace | DL7: Website | DM7: Marketplace | DN7: Mobile App | DO7: Mobile App | DP7: Mobile App | DQ7: Website | DR7: Website | DS7: Website | DT7: Website | DU7: Website | DV7: Marketplace | DW7: Website | DX7: Website | DY7: Marketplace | DZ7: Website | EA7: Mobile App | EB7: Website | EC7: Website | ED7: Mobile App | EE7: Mobile App | EF7: Mobile App | EG7: Mobile App | EH7: Website | EI7: Mobile App | EJ7: Mobile App | EK7: Marketplace | EL7: Mobile App | EM7: Mobile App | EN7: Marketplace | EO7: Marketplace | EP7: Website | EQ7: Marketplace | ER7: Website | ES7: Marketplace | ET7: Marketplace | EU7: Website | EV7: Marketplace | EW7: Website | EX7: Marketplace | EY7: Mobile App | EZ7: Marketplace | FA7: Website | FB7: Marketplace | FC7: Website | FD7: Website | FE7: Mobile App | FF7: Mobile App | FG7: Website | FH7: Marketplace | FI7: Website | FJ7: Website | FK7: Marketplace | FL7: Marketplace | FM7: Marketplace | FN7: Marketplace | FO7: Website | FP7: Website | FQ7: Mobile App | FR7: Website | FS7: Marketplace | FT7: Mobile App | FU7: Marketplace | FV7: Website | FW7: Mobile App | FX7: Marketplace | FY7: Mobile App | FZ7: Mobile App | GA7: Website | GB7: Marketplace | GC7: Mobile App | GD7: Mobile App | GE7: Marketplace | GF7: Mobile App | GG7: Mobile App | GH7: Mobile App | GI7: Marketplace | GJ7: Marketplace | GK7: Marketplace | GL7: Marketplace | GM7: Website | GN7: Mobile App | GO7: Marketplace | GP7: Mobile App | GQ7: Mobile App | GR7: Website | GS7: Marketplace | GT7: Marketplace | GU7: Mobile App | GV7: Marketplace | GW7: Mobile App | GX7: Mobile App | GY7: Website | GZ7: Website | HA7: Website | HB7: Mobile App | HC7: Marketplace | HD7: Website | HE7: Marketplace | HF7: Website | HG7: Website | HH7: Mobile App | HI7: Website | HJ7: Website | HK7: Mobile App | HL7: Marketplace | HM7: Website | HN7: Mobile App | HO7: Website | HP7: Mobile App | HQ7: Marketplace | HR7: Marketplace | HS7: Mobile App | HT7: Mobile App | HU7: Mobile App | HV7: Marketplace | HW7: Website | HX7: Marketplace | HY7: Mobile App | HZ7: Mobile App | IA7: Marketplace | IB7: Mobile App | IC7: Marketplace | ID7: Mobile App | IE7: Website | IF7: Website | IG7: Mobile App | IH7: Marketplace | II7: Website | IJ7: Marketplace | IK7: Mobile App | IL7: Marketplace | IM7: Website | IN7: Marketplace | IO7: Marketplace | IP7: Mobile App | IQ7: Mobile App | IR7: Mobile App | IS7: Website | IT7: Website | IU7: Mobile App | IV7: Mobile App | IW7: Website | IX7: Website | IY7: Website | IZ7: Website | JA7: Mobile App | JB7: Website | JC7: Mobile App | JD7: Marketplace | JE7: Marketplace | JF7: Website | JG7: Marketplace | JH7: Marketplace | JI7: Marketplace | JJ7: Website | JK7: Website | JL7: Marketplace | JM7: Mobile App | JN7: Marketplace | JO7: Website | JP7: Website | JQ7: Website | JR7: Marketplace | JS7: Mobile App | JT7: Website | JU7: Website | JV7: Marketplace | JW7: Mobile App | JX7: Marketplace | JY7: Website | JZ7: Mobile App | KA7: Mobile App | KB7: Website | KC7: Mobile App | KD7: Mobile App | KE7: Marketplace | KF7: Website | KG7: Website | KH7: Website | KI7: Website | KJ7: Website | KK7: Mobile App | KL7: Marketplace | KM7: Website | KN7: Marketplace | KO7: Marketplace | KP7: Mobile App | KQ7: Website | KR7: Mobile App | KS7: Website | KT7: Mobile App | KU7: Marketplace | KV7: Website | KW7: Marketplace | KX7: Marketplace | KY7: Mobile App | KZ7: Website | LA7: Marketplace | LB7: Mobile App | LC7: Website | LD7: Website | LE7: Marketplace | LF7: Website | LG7: Marketplace | LH7: Website | LI7: Mobile App | LJ7: Marketplace | LK7: Marketplace | LL7: Website | LM7: Website | LN7: Marketplace | LO7: Website | LP7: Mobile App | LQ7: Website | LR7: Mobile App | LS7: Mobile App | LT7: Mobile App | LU7: Mobile App | LV7: Mobile App | LW7: Website | LX7: Mobile App | LY7: Website | LZ7: Mobile App | MA7: Marketplace | MB7: Mobile App | MC7: Marketplace | MD7: Mobile App | ME7: Mobile App | MF7: Mobile App | MG7: Marketplace | MH7: Marketplace | MI7: Mobile App | MJ7: Website | MK7: Mobile App | ML7: Marketplace | MM7: Mobile App | MN7: Marketplace | MO7: Marketplace | MP7: Marketplace | MQ7: Mobile App | MR7: Marketplace | MS7: Marketplace | MT7: Mobile App | MU7: Marketplace | MV7: Mobile App | MW7: Marketplace | MX7: Website | MY7: Website | MZ7: Marketplace | NA7: Website | NB7: Mobile App | NC7: Website | ND7: Marketplace | NE7: Marketplace | NF7: Mobile App | NG7: Marketplace | NH7: Mobile App | NI7: Website | NJ7: Website | NK7: Mobile App | NL7: Mobile App | NM7: Marketplace | NN7: Website | NO7: Mobile App | NP7: Website | NQ7: Mobile App | NR7: Website | NS7: Marketplace | NT7: Website | NU7: Website | NV7: Website | NW7: Website | NX7: Website | NY7: Marketplace | NZ7: Mobile App | OA7: Website | OB7: Marketplace | OC7: Website | OD7: Website | OE7: Mobile App | OF7: Website | OG7: Marketplace | OH7: Marketplace | OI7: Mobile App | OJ7: Website | OK7: Marketplace | OL7: Website | OM7: Website | ON7: Website | OO7: Mobile App | OP7: Website | OQ7: Marketplace | OR7: Website | OS7: Marketplace | OT7: Website | OU7: Marketplace | OV7: Marketplace | OW7: Website | OX7: Website | OY7: Marketplace | OZ7: Mobile App | PA7: Website | PB7: Mobile App | PC7: Website | PD7: Website | PE7: Website | PF7: Website | PG7: Mobile App | PH7: Website | PI7: Marketplace | PJ7: Marketplace | PK7: Mobile App | PL7: Website | PM7: Marketplace | PN7: Mobile App | PO7: Website | PP7: Marketplace | PQ7: Marketplace | PR7: Mobile App | PS7: Website | PT7: Website | PU7: Marketplace | PV7: Marketplace | PW7: Marketplace | PX7: Website | PY7: Mobile App | PZ7: Mobile App | QA7: Website | QB7: Mobile App | QC7: Marketplace | QD7: Mobile App | QE7: Mobile App | QF7: Mobile App | QG7: Marketplace | QH7: Website | QI7: Marketplace | QJ7: Website | QK7: Website | QL7: Website | QM7: Mobile App | QN7: Mobile App | QO7: Website | QP7: Website | QQ7: Mobile App | QR7: Marketplace | QS7: Website | QT7: Marketplace | QU7: Mobile App | QV7: Website | QW7: Marketplace | QX7: Marketplace | QY7: Marketplace | QZ7: Mobile App | RA7: Mobile App | RB7: Marketplace | RC7: Marketplace | RD7: Mobile App | RE7: Marketplace | RF7: Marketplace | RG7: Mobile App | RH7: Marketplace | RI7: Marketplace | RJ7: Marketplace | RK7: Mobile App | RL7: Marketplace | RM7: Mobile App | RN7: Mobile App | RO7: Website | RP7: Website | RQ7: Marketplace | RR7: Mobile App | RS7: Website | RT7: Marketplace | RU7: Website | RV7: Website | RW7: Mobile App | RX7: Mobile App | RY7: Website | RZ7: Website | SA7: Mobile App | SB7: Marketplace | SC7: Mobile App | SD7: Website | SE7: Marketplace | SF7: Website | SG7: Marketplace
A8: Payment Method | B8: Credit Card | C8: Debit Card | D8: Debit Card | E8: Cash on Delivery | F8: Credit Card | G8: Net Banking | H8: UPI | I8: Credit Card | J8: Debit Card | K8: Cash on Delivery | L8: Cash on Delivery | M8: UPI | N8: Cash on Delivery | O8: Cash on Delivery | P8: Credit Card | Q8: Net Banking | R8: UPI | S8: Credit Card | T8: Net Banking | U8: Credit Card | V8: Credit Card | W8: Cash on Delivery | X8: Net Banking | Y8: UPI | Z8: UPI | AA8: Net Banking | AB8: Cash on Delivery | AC8: Debit Card | AD8: Credit Card | AE8: Cash on Delivery | AF8: Net Banking | AG8: Credit Card | AH8: UPI | AI8: Debit Card | AJ8: UPI | AK8: Net Banking | AL8: Credit Card | AM8: Net Banking | AN8: Credit Card | AO8: Cash on Delivery | AP8: Debit Card | AQ8: Cash on Delivery | AR8: Cash on Delivery | AS8: Net Banking | AT8: Debit Card | AU8: Credit Card | AV8: Credit Card | AW8: UPI | AX8: Credit Card | AY8: Net Banking | AZ8: Cash on Delivery | BA8: Cash on Delivery | BB8: Cash on Delivery | BC8: Debit Card | BD8: Credit Card | BE8: Net Banking | BF8: Debit Card | BG8: UPI | BH8: Net Banking | BI8: Net Banking | BJ8: Net Banking | BK8: Cash on Delivery | BL8: Net Banking | BM8: Credit Card | BN8: Net Banking | BO8: Cash on Delivery | BP8: Net Banking | BQ8: UPI | BR8: UPI | BS8: Cash on Delivery | BT8: Credit Card | BU8: Credit Card | BV8: Debit Card | BW8: Cash on Delivery | BX8: Net Banking | BY8: Cash on Delivery | BZ8: Debit Card | CA8: Cash on Delivery | CB8: Cash on Delivery | CC8: Debit Card | CD8: Credit Card | CE8: Net Banking | CF8: Debit Card | CG8: UPI | CH8: Credit Card | CI8: UPI | CJ8: Credit Card | CK8: Net Banking | CL8: Net Banking | CM8: Cash on Delivery | CN8: UPI | CO8: Credit Card | CP8: Net Banking | CQ8: Debit Card | CR8: Net Banking | CS8: Debit Card | CT8: Credit Card | CU8: Net Banking | CV8: Net Banking | CW8: Credit Card | CX8: Net Banking | CY8: Debit Card | CZ8: Net Banking | DA8: UPI | DB8: Cash on Delivery | DC8: Debit Card | DD8: UPI | DE8: Credit Card | DF8: Debit Card | DG8: Cash on Delivery | DH8: Cash on Delivery | DI8: Credit Card | DJ8: Credit Card | DK8: Debit Card | DL8: Net Banking | DM8: Credit Card | DN8: Net Banking | DO8: UPI | DP8: Cash on Delivery | DQ8: Net Banking | DR8: Cash on Delivery | DS8: Net Banking | DT8: UPI | DU8: Credit Card | DV8: UPI | DW8: Credit Card | DX8: Credit Card | DY8: Cash on Delivery | DZ8: UPI | EA8: Net Banking | EB8: UPI | EC8: Cash on Delivery | ED8: Credit Card | EE8: Cash on Delivery | EF8: Debit Card | EG8: Debit Card | EH8: Net Banking | EI8: Cash on Delivery | EJ8: Net Banking | EK8: Net Banking | EL8: Debit Card | EM8: Net Banking | EN8: Debit Card | EO8: Credit Card | EP8: Cash on Delivery | EQ8: Net Banking | ER8: Debit Card | ES8: UPI | ET8: Net Banking | EU8: Credit Card | EV8: Credit Card | EW8: UPI | EX8: Debit Card | EY8: Net Banking | EZ8: Debit Card | FA8: Credit Card | FB8: Debit Card | FC8: Credit Card | FD8: Debit Card | FE8: UPI | FF8: Cash on Delivery | FG8: UPI | FH8: UPI | FI8: Cash on Delivery | FJ8: Cash on Delivery | FK8: Net Banking | FL8: Net Banking | FM8: UPI | FN8: UPI | FO8: Credit Card | FP8: Credit Card | FQ8: Net Banking | FR8: Net Banking | FS8: Credit Card | FT8: Credit Card | FU8: Debit Card | FV8: Debit Card | FW8: Credit Card | FX8: Debit Card | FY8: Cash on Delivery | FZ8: Net Banking | GA8: Net Banking | GB8: Credit Card | GC8: UPI | GD8: Credit Card | GE8: Debit Card | GF8: UPI | GG8: Debit Card | GH8: Cash on Delivery | GI8: Debit Card | GJ8: Cash on Delivery | GK8: Cash on Delivery | GL8: Debit Card | GM8: Debit Card | GN8: Cash on Delivery | GO8: UPI | GP8: Cash on Delivery | GQ8: Net Banking | GR8: Cash on Delivery | GS8: UPI | GT8: Net Banking | GU8: Credit Card | GV8: Credit Card | GW8: UPI | GX8: Cash on Delivery | GY8: Debit Card | GZ8: UPI | HA8: Net Banking | HB8: Net Banking | HC8: Credit Card | HD8: Net Banking | HE8: UPI | HF8: Net Banking | HG8: UPI | HH8: Debit Card | HI8: Credit Card | HJ8: Net Banking | HK8: UPI | HL8: Cash on Delivery | HM8: Credit Card | HN8: Debit Card | HO8: UPI | HP8: Debit Card | HQ8: Debit Card | HR8: Net Banking | HS8: Net Banking | HT8: UPI | HU8: Cash on Delivery | HV8: UPI | HW8: Cash on Delivery | HX8: Debit Card | HY8: Credit Card | HZ8: UPI | IA8: UPI | IB8: Cash on Delivery | IC8: Debit Card | ID8: Debit Card | IE8: Cash on Delivery | IF8: Debit Card | IG8: Net Banking | IH8: Credit Card | II8: UPI | IJ8: Credit Card | IK8: UPI | IL8: Net Banking | IM8: Debit Card | IN8: Cash on Delivery | IO8: Net Banking | IP8: Credit Card | IQ8: Cash on Delivery | IR8: Debit Card | IS8: Net Banking | IT8: Cash on Delivery | IU8: Net Banking | IV8: Net Banking | IW8: Debit Card | IX8: UPI | IY8: Cash on Delivery | IZ8: Debit Card | JA8: Net Banking | JB8: Debit Card | JC8: UPI | JD8: Cash on Delivery | JE8: UPI | JF8: Credit Card | JG8: Cash on Delivery | JH8: UPI | JI8: Net Banking | JJ8: Cash on Delivery | JK8: Cash on Delivery | JL8: Debit Card | JM8: Net Banking | JN8: Credit Card | JO8: UPI | JP8: Debit Card | JQ8: UPI | JR8: Credit Card | JS8: Credit Card | JT8: Cash on Delivery | JU8: Credit Card | JV8: UPI | JW8: Net Banking | JX8: Net Banking | JY8: Cash on Delivery | JZ8: UPI | KA8: UPI | KB8: Credit Card | KC8: UPI | KD8: Debit Card | KE8: Credit Card | KF8: Debit Card | KG8: Cash on Delivery | KH8: Net Banking | KI8: Cash on Delivery | KJ8: Net Banking | KK8: Cash on Delivery | KL8: UPI | KM8: Debit Card | KN8: Net Banking | KO8: Credit Card | KP8: Debit Card | KQ8: Credit Card | KR8: Debit Card | KS8: Debit Card | KT8: Cash on Delivery | KU8: Net Banking | KV8: Net Banking | KW8: Debit Card | KX8: UPI | KY8: UPI | KZ8: Credit Card | LA8: Credit Card | LB8: Cash on Delivery | LC8: Debit Card | LD8: Credit Card | LE8: Credit Card | LF8: Debit Card | LG8: Cash on Delivery | LH8: Credit Card | LI8: Cash on Delivery | LJ8: Net Banking | LK8: Cash on Delivery | LL8: UPI | LM8: UPI | LN8: Cash on Delivery | LO8: UPI | LP8: Net Banking | LQ8: Debit Card | LR8: UPI | LS8: UPI | LT8: Cash on Delivery | LU8: Net Banking | LV8: Debit Card | LW8: Cash on Delivery | LX8: Cash on Delivery | LY8: Net Banking | LZ8: Debit Card | MA8: Net Banking | MB8: Debit Card | MC8: Net Banking | MD8: Cash on Delivery | ME8: Cash on Delivery | MF8: Credit Card | MG8: UPI | MH8: Net Banking | MI8: Credit Card | MJ8: UPI | MK8: Net Banking | ML8: Debit Card | MM8: UPI | MN8: Cash on Delivery | MO8: Credit Card | MP8: UPI | MQ8: UPI | MR8: Cash on Delivery | MS8: Net Banking | MT8: Debit Card | MU8: Cash on Delivery | MV8: Debit Card | MW8: Net Banking | MX8: UPI | MY8: Debit Card | MZ8: Credit Card | NA8: Credit Card | NB8: Cash on Delivery | NC8: Net Banking | ND8: Cash on Delivery | NE8: Cash on Delivery | NF8: Cash on Delivery | NG8: Credit Card | NH8: Credit Card | NI8: Cash on Delivery | NJ8: Credit Card | NK8: Net Banking | NL8: Cash on Delivery | NM8: Credit Card | NN8: Debit Card | NO8: Cash on Delivery | NP8: Cash on Delivery | NQ8: Net Banking | NR8: UPI | NS8: UPI | NT8: Net Banking | NU8: Net Banking | NV8: Net Banking | NW8: UPI | NX8: Net Banking | NY8: Credit Card | NZ8: Cash on Delivery | OA8: Cash on Delivery | OB8: Debit Card | OC8: Debit Card | OD8: Cash on Delivery | OE8: Credit Card | OF8: UPI | OG8: UPI | OH8: Credit Card | OI8: UPI | OJ8: Net Banking | OK8: Cash on Delivery | OL8: Cash on Delivery | OM8: Credit Card | ON8: UPI | OO8: Debit Card | OP8: Debit Card | OQ8: UPI | OR8: Debit Card | OS8: Credit Card | OT8: Credit Card | OU8: UPI | OV8: Debit Card | OW8: Credit Card | OX8: Credit Card | OY8: Net Banking | OZ8: Net Banking | PA8: Credit Card | PB8: UPI | PC8: Cash on Delivery | PD8: Cash on Delivery | PE8: Credit Card | PF8: Credit Card | PG8: Credit Card | PH8: UPI | PI8: Net Banking | PJ8: Credit Card | PK8: Credit Card | PL8: Debit Card | PM8: UPI | PN8: Credit Card | PO8: Debit Card | PP8: Cash on Delivery | PQ8: Credit Card | PR8: Credit Card | PS8: Debit Card | PT8: UPI | PU8: Credit Card | PV8: Cash on Delivery | PW8: Credit Card | PX8: Cash on Delivery | PY8: Net Banking | PZ8: Net Banking | QA8: Cash on Delivery | QB8: UPI | QC8: Credit Card | QD8: Credit Card | QE8: Net Banking | QF8: Cash on Delivery | QG8: Credit Card | QH8: Credit Card | QI8: UPI | QJ8: Debit Card | QK8: Net Banking | QL8: Net Banking | QM8: Debit Card | QN8: Credit Card | QO8: UPI | QP8: UPI | QQ8: Net Banking | QR8: UPI | QS8: Debit Card | QT8: Credit Card | QU8: Debit Card | QV8: Cash on Delivery | QW8: Net Banking | QX8: UPI | QY8: Cash on Delivery | QZ8: UPI | RA8: Credit Card | RB8: Credit Card | RC8: Credit Card | RD8: UPI | RE8: Cash on Delivery | RF8: Credit Card | RG8: Cash on Delivery | RH8: UPI | RI8: Cash on Delivery | RJ8: UPI | RK8: UPI | RL8: Net Banking | RM8: UPI | RN8: UPI | RO8: Debit Card | RP8: Credit Card | RQ8: Net Banking | RR8: Net Banking | RS8: Net Banking | RT8: Debit Card | RU8: UPI | RV8: Credit Card | RW8: Cash on Delivery | RX8: UPI | RY8: Debit Card | RZ8: UPI | SA8: UPI | SB8: Debit Card | SC8: Net Banking | SD8: Net Banking | SE8: Credit Card | SF8: Credit Card | SG8: Net Banking
A9: Product Category | B9: Home & Kitchen | C9: Sports | D9: Fashion | E9: Sports | F9: Fashion | G9: Home & Kitchen | H9: Fashion | I9: Fashion | J9: Fashion | K9: Electronics | L9: Electronics | M9: Electronics | N9: Home & Kitchen | O9: Sports | P9: Beauty | Q9: Fashion | R9: Fashion | S9: Home & Kitchen | T9: Fashion | U9: Electronics | V9: Beauty | W9: Books | X9: Fashion | Y9: Electronics | Z9: Books | AA9: Beauty | AB9: Books | AC9: Electronics | AD9: Sports | AE9: Sports | AF9: Books | AG9: Home & Kitchen | AH9: Books | AI9: Fashion | AJ9: Fashion | AK9: Sports | AL9: Home & Kitchen | AM9: Electronics | AN9: Fashion | AO9: Sports | AP9: Beauty | AQ9: Sports | AR9: Fashion | AS9: Fashion | AT9: Sports | AU9: Electronics | AV9: Books | AW9: Fashion | AX9: Sports | AY9: Sports | AZ9: Home & Kitchen | BA9: Books | BB9: Beauty | BC9: Electronics | BD9: Beauty | BE9: Books | BF9: Books | BG9: Books | BH9: Beauty | BI9: Books | BJ9: Sports | BK9: Beauty | BL9: Books | BM9: Sports | BN9: Home & Kitchen | BO9: Books | BP9: Beauty | BQ9: Fashion | BR9: Books | BS9: Fashion | BT9: Sports | BU9: Home & Kitchen | BV9: Electronics | BW9: Home & Kitchen | BX9: Books | BY9: Fashion | BZ9: Fashion | CA9: Beauty | CB9: Fashion | CC9: Beauty | CD9: Sports | CE9: Electronics | CF9: Books | CG9: Beauty | CH9: Electronics | CI9: Fashion | CJ9: Fashion | CK9: Electronics | CL9: Fashion | CM9: Sports | CN9: Sports | CO9: Electronics | CP9: Beauty | CQ9: Beauty | CR9: Electronics | CS9: Beauty | CT9: Beauty | CU9: Sports | CV9: Beauty | CW9: Home & Kitchen | CX9: Books | CY9: Fashion | CZ9: Home & Kitchen | DA9: Beauty | DB9: Sports | DC9: Electronics | DD9: Beauty | DE9: Sports | DF9: Books | DG9: Beauty | DH9: Electronics | DI9: Sports | DJ9: Sports | DK9: Sports | DL9: Books | DM9: Beauty | DN9: Books | DO9: Fashion | DP9: Fashion | DQ9: Beauty | DR9: Books | DS9: Electronics | DT9: Sports | DU9: Sports | DV9: Beauty | DW9: Fashion | DX9: Fashion | DY9: Sports | DZ9: Beauty | EA9: Books | EB9: Fashion | EC9: Books | ED9: Fashion | EE9: Fashion | EF9: Home & Kitchen | EG9: Fashion | EH9: Electronics | EI9: Beauty | EJ9: Beauty | EK9: Books | EL9: Fashion | EM9: Electronics | EN9: Books | EO9: Home & Kitchen | EP9: Books | EQ9: Books | ER9: Fashion | ES9: Home & Kitchen | ET9: Books | EU9: Electronics | EV9: Electronics | EW9: Beauty | EX9: Home & Kitchen | EY9: Home & Kitchen | EZ9: Beauty | FA9: Books | FB9: Home & Kitchen | FC9: Electronics | FD9: Electronics | FE9: Fashion | FF9: Home & Kitchen | FG9: Books | FH9: Beauty | FI9: Beauty | FJ9: Books | FK9: Sports | FL9: Fashion | FM9: Beauty | FN9: Home & Kitchen | FO9: Fashion | FP9: Home & Kitchen | FQ9: Electronics | FR9: Fashion | FS9: Beauty | FT9: Fashion | FU9: Fashion | FV9: Fashion | FW9: Sports | FX9: Fashion | FY9: Home & Kitchen | FZ9: Electronics | GA9: Books | GB9: Fashion | GC9: Beauty | GD9: Fashion | GE9: Beauty | GF9: Home & Kitchen | GG9: Beauty | GH9: Books | GI9: Electronics | GJ9: Beauty | GK9: Beauty | GL9: Electronics | GM9: Books | GN9: Fashion | GO9: Beauty | GP9: Electronics | GQ9: Home & Kitchen | GR9: Electronics | GS9: Home & Kitchen | GT9: Books | GU9: Fashion | GV9: Electronics | GW9: Sports | GX9: Beauty | GY9: Books | GZ9: Electronics | HA9: Beauty | HB9: Electronics | HC9: Home & Kitchen | HD9: Electronics | HE9: Sports | HF9: Electronics | HG9: Electronics | HH9: Sports | HI9: Books | HJ9: Electronics | HK9: Sports | HL9: Beauty | HM9: Home & Kitchen | HN9: Home & Kitchen | HO9: Electronics | HP9: Books | HQ9: Books | HR9: Beauty | HS9: Electronics | HT9: Home & Kitchen | HU9: Books | HV9: Electronics | HW9: Books | HX9: Sports | HY9: Books | HZ9: Home & Kitchen | IA9: Fashion | IB9: Beauty | IC9: Beauty | ID9: Home & Kitchen | IE9: Books | IF9: Electronics | IG9: Books | IH9: Home & Kitchen | II9: Beauty | IJ9: Books | IK9: Beauty | IL9: Electronics | IM9: Beauty | IN9: Beauty | IO9: Fashion | IP9: Fashion | IQ9: Sports | IR9: Fashion | IS9: Beauty | IT9: Home & Kitchen | IU9: Beauty | IV9: Home & Kitchen | IW9: Home & Kitchen | IX9: Fashion | IY9: Books | IZ9: Electronics | JA9: Fashion | JB9: Fashion | JC9: Books | JD9: Electronics | JE9: Beauty | JF9: Sports | JG9: Sports | JH9: Beauty | JI9: Fashion | JJ9: Electronics | JK9: Fashion | JL9: Home & Kitchen | JM9: Fashion | JN9: Fashion | JO9: Beauty | JP9: Beauty | JQ9: Beauty | JR9: Sports | JS9: Home & Kitchen | JT9: Beauty | JU9: Electronics | JV9: Sports | JW9: Books | JX9: Electronics | JY9: Electronics | JZ9: Beauty | KA9: Books | KB9: Books | KC9: Sports | KD9: Books | KE9: Home & Kitchen | KF9: Beauty | KG9: Books | KH9: Sports | KI9: Home & Kitchen | KJ9: Fashion | KK9: Fashion | KL9: Home & Kitchen | KM9: Sports | KN9: Home & Kitchen | KO9: Beauty | KP9: Beauty | KQ9: Fashion | KR9: Books | KS9: Sports | KT9: Fashion | KU9: Books | KV9: Books | KW9: Beauty | KX9: Electronics | KY9: Electronics | KZ9: Home & Kitchen | LA9: Beauty | LB9: Books | LC9: Sports | LD9: Electronics | LE9: Books | LF9: Electronics | LG9: Electronics | LH9: Electronics | LI9: Sports | LJ9: Beauty | LK9: Sports | LL9: Fashion | LM9: Books | LN9: Beauty | LO9: Beauty | LP9: Beauty | LQ9: Beauty | LR9: Sports | LS9: Beauty | LT9: Home & Kitchen | LU9: Books | LV9: Beauty | LW9: Books | LX9: Home & Kitchen | LY9: Home & Kitchen | LZ9: Books | MA9: Electronics | MB9: Fashion | MC9: Electronics | MD9: Electronics | ME9: Sports | MF9: Electronics | MG9: Beauty | MH9: Sports | MI9: Sports | MJ9: Home & Kitchen | MK9: Electronics | ML9: Home & Kitchen | MM9: Books | MN9: Fashion | MO9: Sports | MP9: Books | MQ9: Books | MR9: Beauty | MS9: Fashion | MT9: Books | MU9: Books | MV9: Fashion | MW9: Fashion | MX9: Books | MY9: Fashion | MZ9: Books | NA9: Books | NB9: Beauty | NC9: Electronics | ND9: Books | NE9: Home & Kitchen | NF9: Sports | NG9: Electronics | NH9: Electronics | NI9: Electronics | NJ9: Beauty | NK9: Books | NL9: Beauty | NM9: Books | NN9: Beauty | NO9: Beauty | NP9: Sports | NQ9: Home & Kitchen | NR9: Beauty | NS9: Sports | NT9: Fashion | NU9: Home & Kitchen | NV9: Beauty | NW9: Electronics | NX9: Fashion | NY9: Fashion | NZ9: Sports | OA9: Fashion | OB9: Home & Kitchen | OC9: Beauty | OD9: Beauty | OE9: Electronics | OF9: Sports | OG9: Electronics | OH9: Fashion | OI9: Electronics | OJ9: Home & Kitchen | OK9: Beauty | OL9: Fashion | OM9: Electronics | ON9: Sports | OO9: Home & Kitchen | OP9: Home & Kitchen | OQ9: Electronics | OR9: Beauty | OS9: Electronics | OT9: Fashion | OU9: Electronics | OV9: Home & Kitchen | OW9: Electronics | OX9: Beauty | OY9: Sports | OZ9: Books | PA9: Electronics | PB9: Beauty | PC9: Beauty | PD9: Sports | PE9: Home & Kitchen | PF9: Beauty | PG9: Beauty | PH9: Beauty | PI9: Beauty | PJ9: Fashion | PK9: Fashion | PL9: Home & Kitchen | PM9: Electronics | PN9: Beauty | PO9: Sports | PP9: Electronics | PQ9: Sports | PR9: Electronics | PS9: Home & Kitchen | PT9: Beauty | PU9: Beauty | PV9: Books | PW9: Sports | PX9: Electronics | PY9: Electronics | PZ9: Fashion | QA9: Books | QB9: Fashion | QC9: Fashion | QD9: Fashion | QE9: Sports | QF9: Sports | QG9: Home & Kitchen | QH9: Home & Kitchen | QI9: Fashion | QJ9: Books | QK9: Electronics | QL9: Sports | QM9: Books | QN9: Beauty | QO9: Sports | QP9: Sports | QQ9: Home & Kitchen | QR9: Electronics | QS9: Electronics | QT9: Beauty | QU9: Beauty | QV9: Sports | QW9: Fashion | QX9: Home & Kitchen | QY9: Home & Kitchen | QZ9: Sports | RA9: Books | RB9: Fashion | RC9: Sports | RD9: Fashion | RE9: Fashion | RF9: Fashion | RG9: Sports | RH9: Home & Kitchen | RI9: Home & Kitchen | RJ9: Fashion | RK9: Books | RL9: Electronics | RM9: Sports | RN9: Electronics | RO9: Books | RP9: Sports | RQ9: Fashion | RR9: Home & Kitchen | RS9: Electronics | RT9: Beauty | RU9: Beauty | RV9: Books | RW9: Fashion | RX9: Electronics | RY9: Fashion | RZ9: Electronics | SA9: Books | SB9: Books | SC9: Beauty | SD9: Fashion | SE9: Sports | SF9: Beauty | SG9: Fashion
A10: Product Name | B10: Mixer Grinder | C10: Football | D10: Sneakers | E10: Yoga Mat | F10: Jacket | G10: Bedsheet | H10: Sneakers | I10: Sneakers | J10: T-Shirt | K10: Headphones | L10: Headphones | M10: Smartwatch | N10: Bedsheet | O10: Yoga Mat | P10: Shampoo | Q10: Jacket | R10: Jacket | S10: Curtains | T10: Jacket | U10: Smartwatch | V10: Lipstick | W10: Fiction Novel | X10: Sneakers | Y10: Smartwatch | Z10: Comics | AA10: Perfume | AB10: Fiction Novel | AC10: Smartwatch | AD10: Football | AE10: Cricket Bat | AF10: Textbook | AG10: Bedsheet | AH10: Comics | AI10: T-Shirt | AJ10: T-Shirt | AK10: Football | AL10: Curtains | AM10: Laptop | AN10: T-Shirt | AO10: Football | AP10: Face Cream | AQ10: Football | AR10: T-Shirt | AS10: T-Shirt | AT10: Cricket Bat | AU10: Smartwatch | AV10: Textbook | AW10: Jeans | AX10: Football | AY10: Cricket Bat | AZ10: Cookware Set | BA10: Textbook | BB10: Face Cream | BC10: Headphones | BD10: Face Cream | BE10: Textbook | BF10: Fiction Novel | BG10: Comics | BH10: Face Cream | BI10: Textbook | BJ10: Yoga Mat | BK10: Lipstick | BL10: Textbook | BM10: Yoga Mat | BN10: Bedsheet | BO10: Biography | BP10: Face Cream | BQ10: T-Shirt | BR10: Textbook | BS10: Jacket | BT10: Cricket Bat | BU10: Curtains | BV10: Smartphone | BW10: Bedsheet | BX10: Fiction Novel | BY10: Jacket | BZ10: Sneakers | CA10: Perfume | CB10: Sneakers | CC10: Lipstick | CD10: Football | CE10: Laptop | CF10: Textbook | CG10: Lipstick | CH10: Headphones | CI10: Jeans | CJ10: Jacket | CK10: Laptop | CL10: T-Shirt | CM10: Football | CN10: Football | CO10: Headphones | CP10: Lipstick | CQ10: Perfume | CR10: Headphones | CS10: Perfume | CT10: Perfume | CU10: Yoga Mat | CV10: Shampoo | CW10: Bedsheet | CX10: Comics | CY10: Jacket | CZ10: Mixer Grinder | DA10: Shampoo | DB10: Football | DC10: Laptop | DD10: Perfume | DE10: Yoga Mat | DF10: Comics | DG10: Lipstick | DH10: Smartphone | DI10: Yoga Mat | DJ10: Cricket Bat | DK10: Dumbbells | DL10: Textbook | DM10: Perfume | DN10: Fiction Novel | DO10: T-Shirt | DP10: Sneakers | DQ10: Shampoo | DR10: Textbook | DS10: Laptop | DT10: Dumbbells | DU10: Cricket Bat | DV10: Face Cream | DW10: T-Shirt | DX10: Jacket | DY10: Cricket Bat | DZ10: Lipstick | EA10: Textbook | EB10: Sneakers | EC10: Fiction Novel | ED10: T-Shirt | EE10: Jeans | EF10: Bedsheet | EG10: Jacket | EH10: Headphones | EI10: Shampoo | EJ10: Shampoo | EK10: Comics | EL10: Jacket | EM10: Smartwatch | EN10: Fiction Novel | EO10: Curtains | EP10: Comics | EQ10: Textbook | ER10: T-Shirt | ES10: Mixer Grinder | ET10: Textbook | EU10: Smartwatch | EV10: Laptop | EW10: Lipstick | EX10: Cookware Set | EY10: Bedsheet | EZ10: Lipstick | FA10: Comics | FB10: Mixer Grinder | FC10: Laptop | FD10: Smartphone | FE10: T-Shirt | FF10: Mixer Grinder | FG10: Fiction Novel | FH10: Shampoo | FI10: Face Cream | FJ10: Textbook | FK10: Football | FL10: Sneakers | FM10: Lipstick | FN10: Curtains | FO10: Jeans | FP10: Bedsheet | FQ10: Laptop | FR10: Jeans | FS10: Shampoo | FT10: Sneakers | FU10: Jacket | FV10: Sneakers | FW10: Cricket Bat | FX10: Sneakers | FY10: Bedsheet | FZ10: Headphones | GA10: Comics | GB10: Jacket | GC10: Face Cream | GD10: Jacket | GE10: Lipstick | GF10: Bedsheet | GG10: Shampoo | GH10: Textbook | GI10: Smartwatch | GJ10: Lipstick | GK10: Perfume | GL10: Smartwatch | GM10: Comics | GN10: Jeans | GO10: Shampoo | GP10: Smartphone | GQ10: Cookware Set | GR10: Smartwatch | GS10: Cookware Set | GT10: Comics | GU10: Jeans | GV10: Smartphone | GW10: Football | GX10: Perfume | GY10: Comics | GZ10: Smartwatch | HA10: Shampoo | HB10: Headphones | HC10: Mixer Grinder | HD10: Smartwatch | HE10: Cricket Bat | HF10: Laptop | HG10: Laptop | HH10: Football | HI10: Biography | HJ10: Headphones | HK10: Dumbbells | HL10: Face Cream | HM10: Curtains | HN10: Mixer Grinder | HO10: Smartwatch | HP10: Comics | HQ10: Fiction Novel | HR10: Shampoo | HS10: Laptop | HT10: Curtains | HU10: Textbook | HV10: Smartphone | HW10: Textbook | HX10: Yoga Mat | HY10: Comics | HZ10: Curtains | IA10: T-Shirt | IB10: Perfume | IC10: Perfume | ID10: Mixer Grinder | IE10: Textbook | IF10: Laptop | IG10: Biography | IH10: Cookware Set | II10: Face Cream | IJ10: Comics | IK10: Shampoo | IL10: Smartwatch | IM10: Shampoo | IN10: Face Cream | IO10: Jacket | IP10: Jeans | IQ10: Dumbbells | IR10: T-Shirt | IS10: Perfume | IT10: Mixer Grinder | IU10: Face Cream | IV10: Mixer Grinder | IW10: Mixer Grinder | IX10: Sneakers | IY10: Comics | IZ10: Smartwatch | JA10: Jeans | JB10: Sneakers | JC10: Comics | JD10: Laptop | JE10: Perfume | JF10: Cricket Bat | JG10: Cricket Bat | JH10: Shampoo | JI10: Jacket | JJ10: Smartwatch | JK10: Jeans | JL10: Cookware Set | JM10: T-Shirt | JN10: Jacket | JO10: Perfume | JP10: Face Cream | JQ10: Shampoo | JR10: Dumbbells | JS10: Bedsheet | JT10: Perfume | JU10: Smartphone | JV10: Dumbbells | JW10: Biography | JX10: Laptop | JY10: Smartwatch | JZ10: Lipstick | KA10: Fiction Novel | KB10: Biography | KC10: Yoga Mat | KD10: Fiction Novel | KE10: Mixer Grinder | KF10: Shampoo | KG10: Biography | KH10: Football | KI10: Bedsheet | KJ10: T-Shirt | KK10: T-Shirt | KL10: Mixer Grinder | KM10: Yoga Mat | KN10: Bedsheet | KO10: Shampoo | KP10: Shampoo | KQ10: Jeans | KR10: Biography | KS10: Cricket Bat | KT10: T-Shirt | KU10: Textbook | KV10: Fiction Novel | KW10: Shampoo | KX10: Smartwatch | KY10: Smartwatch | KZ10: Bedsheet | LA10: Lipstick | LB10: Textbook | LC10: Dumbbells | LD10: Headphones | LE10: Fiction Novel | LF10: Laptop | LG10: Smartphone | LH10: Headphones | LI10: Yoga Mat | LJ10: Perfume | LK10: Cricket Bat | LL10: T-Shirt | LM10: Fiction Novel | LN10: Face Cream | LO10: Perfume | LP10: Perfume | LQ10: Shampoo | LR10: Football | LS10: Face Cream | LT10: Curtains | LU10: Biography | LV10: Perfume | LW10: Comics | LX10: Bedsheet | LY10: Cookware Set | LZ10: Textbook | MA10: Headphones | MB10: Sneakers | MC10: Headphones | MD10: Smartwatch | ME10: Football | MF10: Smartwatch | MG10: Lipstick | MH10: Yoga Mat | MI10: Yoga Mat | MJ10: Mixer Grinder | MK10: Smartphone | ML10: Curtains | MM10: Textbook | MN10: Sneakers | MO10: Yoga Mat | MP10: Biography | MQ10: Fiction Novel | MR10: Shampoo | MS10: T-Shirt | MT10: Fiction Novel | MU10: Fiction Novel | MV10: T-Shirt | MW10: Sneakers | MX10: Comics | MY10: T-Shirt | MZ10: Textbook | NA10: Biography | NB10: Shampoo | NC10: Laptop | ND10: Textbook | NE10: Mixer Grinder | NF10: Yoga Mat | NG10: Laptop | NH10: Smartphone | NI10: Laptop | NJ10: Shampoo | NK10: Fiction Novel | NL10: Perfume | NM10: Comics | NN10: Lipstick | NO10: Face Cream | NP10: Dumbbells | NQ10: Curtains | NR10: Lipstick | NS10: Yoga Mat | NT10: T-Shirt | NU10: Curtains | NV10: Face Cream | NW10: Smartphone | NX10: Sneakers | NY10: Jacket | NZ10: Dumbbells | OA10: T-Shirt | OB10: Cookware Set | OC10: Perfume | OD10: Perfume | OE10: Headphones | OF10: Yoga Mat | OG10: Smartwatch | OH10: Jacket | OI10: Laptop | OJ10: Bedsheet | OK10: Perfume | OL10: T-Shirt | OM10: Smartwatch | ON10: Yoga Mat | OO10: Cookware Set | OP10: Cookware Set | OQ10: Smartwatch | OR10: Shampoo | OS10: Laptop | OT10: Jacket | OU10: Headphones | OV10: Bedsheet | OW10: Laptop | OX10: Shampoo | OY10: Yoga Mat | OZ10: Biography | PA10: Laptop | PB10: Face Cream | PC10: Lipstick | PD10: Football | PE10: Cookware Set | PF10: Face Cream | PG10: Face Cream | PH10: Perfume | PI10: Lipstick | PJ10: Jacket | PK10: Sneakers | PL10: Curtains | PM10: Smartwatch | PN10: Lipstick | PO10: Dumbbells | PP10: Smartwatch | PQ10: Cricket Bat | PR10: Smartwatch | PS10: Mixer Grinder | PT10: Lipstick | PU10: Perfume | PV10: Textbook | PW10: Cricket Bat | PX10: Smartwatch | PY10: Headphones | PZ10: Jeans | QA10: Fiction Novel | QB10: Jeans | QC10: Sneakers | QD10: T-Shirt | QE10: Football | QF10: Dumbbells | QG10: Mixer Grinder | QH10: Cookware Set | QI10: Sneakers | QJ10: Comics | QK10: Smartphone | QL10: Football | QM10: Fiction Novel | QN10: Face Cream | QO10: Football | QP10: Football | QQ10: Curtains | QR10: Laptop | QS10: Headphones | QT10: Face Cream | QU10: Face Cream | QV10: Yoga Mat | QW10: Jeans | QX10: Bedsheet | QY10: Bedsheet | QZ10: Dumbbells | RA10: Comics | RB10: T-Shirt | RC10: Yoga Mat | RD10: T-Shirt | RE10: T-Shirt | RF10: T-Shirt | RG10: Football | RH10: Curtains | RI10: Mixer Grinder | RJ10: T-Shirt | RK10: Textbook | RL10: Smartphone | RM10: Yoga Mat | RN10: Headphones | RO10: Biography | RP10: Cricket Bat | RQ10: Jeans | RR10: Bedsheet | RS10: Laptop | RT10: Shampoo | RU10: Perfume | RV10: Textbook | RW10: Sneakers | RX10: Laptop | RY10: Sneakers | RZ10: Smartphone | SA10: Biography | SB10: Comics | SC10: Perfume | SD10: Jacket | SE10: Yoga Mat | SF10: Perfume | SG10: Jeans
A11: Brand | B11: BrandA | C11: BrandD | D11: BrandE | E11: BrandA | F11: BrandA | G11: BrandE | H11: BrandC | I11: BrandB | J11: BrandD | K11: BrandB | L11: BrandE | M11: BrandA | N11: BrandA | O11: BrandD | P11: BrandA | Q11: BrandA | R11: BrandD | S11: BrandD | T11: BrandE | U11: BrandA | V11: BrandA | W11: BrandE | X11: BrandC | Y11: BrandC | Z11: BrandC | AA11: BrandE | AB11: BrandA | AC11: BrandE | AD11: BrandE | AE11: BrandC | AF11: BrandB | AG11: BrandA | AH11: BrandC | AI11: BrandB | AJ11: BrandB | AK11: BrandD | AL11: BrandA | AM11: BrandB | AN11: BrandC | AO11: BrandD | AP11: BrandA | AQ11: BrandE | AR11: BrandC | AS11: BrandB | AT11: BrandB | AU11: BrandC | AV11: BrandB | AW11: BrandD | AX11: BrandA | AY11: BrandD | AZ11: BrandB | BA11: BrandE | BB11: BrandA | BC11: BrandA | BD11: BrandC | BE11: BrandC | BF11: BrandE | BG11: BrandA | BH11: BrandE | BI11: BrandC | BJ11: BrandC | BK11: BrandA | BL11: BrandD | BM11: BrandB | BN11: BrandC | BO11: BrandC | BP11: BrandD | BQ11: BrandD | BR11: BrandE | BS11: BrandE | BT11: BrandB | BU11: BrandB | BV11: BrandA | BW11: BrandE | BX11: BrandC | BY11: BrandE | BZ11: BrandC | CA11: BrandD | CB11: BrandE | CC11: BrandD | CD11: BrandB | CE11: BrandB | CF11: BrandA | CG11: BrandE | CH11: BrandD | CI11: BrandC | CJ11: BrandB | CK11: BrandB | CL11: BrandC | CM11: BrandD | CN11: BrandD | CO11: BrandE | CP11: BrandE | CQ11: BrandA | CR11: BrandB | CS11: BrandE | CT11: BrandD | CU11: BrandC | CV11: BrandD | CW11: BrandB | CX11: BrandD | CY11: BrandA | CZ11: BrandB | DA11: BrandC | DB11: BrandA | DC11: BrandB | DD11: BrandC | DE11: BrandA | DF11: BrandA | DG11: BrandB | DH11: BrandE | DI11: BrandA | DJ11: BrandA | DK11: BrandC | DL11: BrandD | DM11: BrandB | DN11: BrandB | DO11: BrandE | DP11: BrandE | DQ11: BrandB | DR11: BrandE | DS11: BrandC | DT11: BrandB | DU11: BrandE | DV11: BrandB | DW11: BrandD | DX11: BrandA | DY11: BrandB | DZ11: BrandA | EA11: BrandE | EB11: BrandA | EC11: BrandB | ED11: BrandD | EE11: BrandE | EF11: BrandB | EG11: BrandE | EH11: BrandC | EI11: BrandA | EJ11: BrandC | EK11: BrandB | EL11: BrandD | EM11: BrandE | EN11: BrandA | EO11: BrandE | EP11: BrandB | EQ11: BrandE | ER11: BrandA | ES11: BrandB | ET11: BrandE | EU11: BrandD | EV11: BrandB | EW11: BrandB | EX11: BrandD | EY11: BrandC | EZ11: BrandA | FA11: BrandC | FB11: BrandE | FC11: BrandD | FD11: BrandC | FE11: BrandB | FF11: BrandE | FG11: BrandE | FH11: BrandC | FI11: BrandC | FJ11: BrandD | FK11: BrandA | FL11: BrandC | FM11: BrandC | FN11: BrandB | FO11: BrandE | FP11: BrandA | FQ11: BrandB | FR11: BrandD | FS11: BrandD | FT11: BrandC | FU11: BrandC | FV11: BrandD | FW11: BrandC | FX11: BrandA | FY11: BrandC | FZ11: BrandE | GA11: BrandC | GB11: BrandB | GC11: BrandA | GD11: BrandB | GE11: BrandB | GF11: BrandE | GG11: BrandA | GH11: BrandA | GI11: BrandA | GJ11: BrandA | GK11: BrandA | GL11: BrandE | GM11: BrandC | GN11: BrandB | GO11: BrandA | GP11: BrandC | GQ11: BrandC | GR11: BrandB | GS11: BrandE | GT11: BrandD | GU11: BrandD | GV11: BrandC | GW11: BrandB | GX11: BrandD | GY11: BrandC | GZ11: BrandE | HA11: BrandD | HB11: BrandC | HC11: BrandC | HD11: BrandA | HE11: BrandE | HF11: BrandA | HG11: BrandB | HH11: BrandA | HI11: BrandA | HJ11: BrandD | HK11: BrandC | HL11: BrandE | HM11: BrandA | HN11: BrandE | HO11: BrandA | HP11: BrandB | HQ11: BrandA | HR11: BrandD | HS11: BrandC | HT11: BrandB | HU11: BrandA | HV11: BrandE | HW11: BrandB | HX11: BrandB | HY11: BrandA | HZ11: BrandB | IA11: BrandE | IB11: BrandB | IC11: BrandE | ID11: BrandA | IE11: BrandC | IF11: BrandB | IG11: BrandC | IH11: BrandE | II11: BrandB | IJ11: BrandD | IK11: BrandC | IL11: BrandB | IM11: BrandC | IN11: BrandB | IO11: BrandA | IP11: BrandC | IQ11: BrandD | IR11: BrandD | IS11: BrandE | IT11: BrandB | IU11: BrandC | IV11: BrandE | IW11: BrandC | IX11: BrandB | IY11: BrandD | IZ11: BrandA | JA11: BrandD | JB11: BrandE | JC11: BrandA | JD11: BrandE | JE11: BrandB | JF11: BrandA | JG11: BrandE | JH11: BrandB | JI11: BrandD | JJ11: BrandB | JK11: BrandC | JL11: BrandB | JM11: BrandB | JN11: BrandC | JO11: BrandE | JP11: BrandE | JQ11: BrandB | JR11: BrandC | JS11: BrandC | JT11: BrandD | JU11: BrandE | JV11: BrandA | JW11: BrandE | JX11: BrandE | JY11: BrandD | JZ11: BrandA | KA11: BrandD | KB11: BrandA | KC11: BrandB | KD11: BrandA | KE11: BrandD | KF11: BrandE | KG11: BrandA | KH11: BrandA | KI11: BrandC | KJ11: BrandE | KK11: BrandB | KL11: BrandD | KM11: BrandB | KN11: BrandE | KO11: BrandA | KP11: BrandA | KQ11: BrandE | KR11: BrandA | KS11: BrandA | KT11: BrandA | KU11: BrandD | KV11: BrandD | KW11: BrandC | KX11: BrandB | KY11: BrandE | KZ11: BrandE | LA11: BrandE | LB11: BrandC | LC11: BrandD | LD11: BrandC | LE11: BrandE | LF11: BrandB | LG11: BrandA | LH11: BrandD | LI11: BrandD | LJ11: BrandC | LK11: BrandD | LL11: BrandE | LM11: BrandE | LN11: BrandC | LO11: BrandE | LP11: BrandB | LQ11: BrandC | LR11: BrandB | LS11: BrandA | LT11: BrandB | LU11: BrandA | LV11: BrandA | LW11: BrandB | LX11: BrandC | LY11: BrandE | LZ11: BrandE | MA11: BrandA | MB11: BrandA | MC11: BrandC | MD11: BrandD | ME11: BrandB | MF11: BrandA | MG11: BrandE | MH11: BrandC | MI11: BrandB | MJ11: BrandC | MK11: BrandB | ML11: BrandB | MM11: BrandA | MN11: BrandC | MO11: BrandC | MP11: BrandE | MQ11: BrandE | MR11: BrandA | MS11: BrandA | MT11: BrandD | MU11: BrandE | MV11: BrandB | MW11: BrandC | MX11: BrandA | MY11: BrandC | MZ11: BrandC | NA11: BrandD | NB11: BrandE | NC11: BrandA | ND11: BrandC | NE11: BrandA | NF11: BrandB | NG11: BrandD | NH11: BrandB | NI11: BrandA | NJ11: BrandA | NK11: BrandE | NL11: BrandC | NM11: BrandC | NN11: BrandB | NO11: BrandD | NP11: BrandC | NQ11: BrandE | NR11: BrandB | NS11: BrandB | NT11: BrandE | NU11: BrandD | NV11: BrandE | NW11: BrandD | NX11: BrandE | NY11: BrandE | NZ11: BrandA | OA11: BrandB | OB11: BrandE | OC11: BrandE | OD11: BrandC | OE11: BrandB | OF11: BrandC | OG11: BrandB | OH11: BrandC | OI11: BrandE | OJ11: BrandE | OK11: BrandA | OL11: BrandC | OM11: BrandD | ON11: BrandA | OO11: BrandC | OP11: BrandC | OQ11: BrandA | OR11: BrandE | OS11: BrandC | OT11: BrandE | OU11: BrandA | OV11: BrandE | OW11: BrandB | OX11: BrandD | OY11: BrandC | OZ11: BrandD | PA11: BrandE | PB11: BrandC | PC11: BrandE | PD11: BrandB | PE11: BrandA | PF11: BrandC | PG11: BrandB | PH11: BrandB | PI11: BrandC | PJ11: BrandE | PK11: BrandB | PL11: BrandD | PM11: BrandB | PN11: BrandE | PO11: BrandE | PP11: BrandD | PQ11: BrandB | PR11: BrandE | PS11: BrandC | PT11: BrandA | PU11: BrandA | PV11: BrandA | PW11: BrandB | PX11: BrandD | PY11: BrandE | PZ11: BrandC | QA11: BrandC | QB11: BrandB | QC11: BrandA | QD11: BrandB | QE11: BrandD | QF11: BrandD | QG11: BrandE | QH11: BrandE | QI11: BrandD | QJ11: BrandD | QK11: BrandD | QL11: BrandB | QM11: BrandD | QN11: BrandC | QO11: BrandA | QP11: BrandD | QQ11: BrandA | QR11: BrandB | QS11: BrandA | QT11: BrandB | QU11: BrandC | QV11: BrandB | QW11: BrandB | QX11: BrandE | QY11: BrandD | QZ11: BrandD | RA11: BrandC | RB11: BrandC | RC11: BrandD | RD11: BrandE | RE11: BrandD | RF11: BrandE | RG11: BrandC | RH11: BrandA | RI11: BrandC | RJ11: BrandC | RK11: BrandB | RL11: BrandB | RM11: BrandB | RN11: BrandB | RO11: BrandE | RP11: BrandD | RQ11: BrandA | RR11: BrandC | RS11: BrandE | RT11: BrandA | RU11: BrandE | RV11: BrandE | RW11: BrandC | RX11: BrandD | RY11: BrandB | RZ11: BrandD | SA11: BrandC | SB11: BrandC | SC11: BrandC | SD11: BrandA | SE11: BrandD | SF11: BrandD | SG11: BrandE
A12: Units Sold | B12: 7 | C12: 9 | D12: 6 | E12: 1 | F12: 7 | G12: 3 | H12: 5 | I12: 4 | J12: 5 | K12: 5 | L12: 6 | M12: 6 | N12: 8 | O12: 8 | P12: 9 | Q12: 8 | R12: 2 | S12: 1 | T12: 2 | U12: 2 | V12: 3 | W12: 7 | X12: 2 | Y12: 1 | Z12: 6 | AA12: 9 | AB12: 3 | AC12: 6 | AD12: 3 | AE12: 1 | AF12: 5 | AG12: 4 | AH12: 7 | AI12: 6 | AJ12: 7 | AK12: 5 | AL12: 4 | AM12: 7 | AN12: 7 | AO12: 6 | AP12: 8 | AQ12: 4 | AR12: 5 | AS12: 4 | AT12: 1 | AU12: 8 | AV12: 1 | AW12: 5 | AX12: 6 | AY12: 6 | AZ12: 5 | BA12: 3 | BB12: 5 | BC12: 8 | BD12: 2 | BE12: 6 | BF12: 9 | BG12: 8 | BH12: 8 | BI12: 8 | BJ12: 7 | BK12: 8 | BL12: 6 | BM12: 2 | BN12: 2 | BO12: 8 | BP12: 1 | BQ12: 6 | BR12: 6 | BS12: 4 | BT12: 3 | BU12: 3 | BV12: 1 | BW12: 3 | BX12: 4 | BY12: 5 | BZ12: 3 | CA12: 6 | CB12: 5 | CC12: 3 | CD12: 6 | CE12: 6 | CF12: 8 | CG12: 2 | CH12: 1 | CI12: 4 | CJ12: 7 | CK12: 3 | CL12: 3 | CM12: 5 | CN12: 5 | CO12: 3 | CP12: 9 | CQ12: 4 | CR12: 3 | CS12: 2 | CT12: 9 | CU12: 4 | CV12: 3 | CW12: 7 | CX12: 8 | CY12: 2 | CZ12: 7 | DA12: 5 | DB12: 5 | DC12: 3 | DD12: 5 | DE12: 2 | DF12: 4 | DG12: 6 | DH12: 1 | DI12: 4 | DJ12: 6 | DK12: 9 | DL12: 2 | DM12: 7 | DN12: 6 | DO12: 2 | DP12: 8 | DQ12: 7 | DR12: 5 | DS12: 5 | DT12: 7 | DU12: 9 | DV12: 9 | DW12: 9 | DX12: 6 | DY12: 6 | DZ12: 3 | EA12: 1 | EB12: 7 | EC12: 4 | ED12: 1 | EE12: 8 | EF12: 6 | EG12: 6 | EH12: 2 | EI12: 1 | EJ12: 2 | EK12: 4 | EL12: 2 | EM12: 1 | EN12: 7 | EO12: 8 | EP12: 6 | EQ12: 4 | ER12: 6 | ES12: 3 | ET12: 8 | EU12: 2 | EV12: 5 | EW12: 1 | EX12: 6 | EY12: 2 | EZ12: 4 | FA12: 6 | FB12: 8 | FC12: 8 | FD12: 6 | FE12: 4 | FF12: 8 | FG12: 8 | FH12: 1 | FI12: 4 | FJ12: 4 | FK12: 7 | FL12: 7 | FM12: 8 | FN12: 5 | FO12: 7 | FP12: 8 | FQ12: 9 | FR12: 3 | FS12: 3 | FT12: 4 | FU12: 5 | FV12: 1 | FW12: 7 | FX12: 9 | FY12: 8 | FZ12: 5 | GA12: 4 | GB12: 7 | GC12: 5 | GD12: 7 | GE12: 1 | GF12: 1 | GG12: 3 | GH12: 2 | GI12: 2 | GJ12: 7 | GK12: 2 | GL12: 4 | GM12: 2 | GN12: 6 | GO12: 8 | GP12: 4 | GQ12: 5 | GR12: 4 | GS12: 3 | GT12: 5 | GU12: 9 | GV12: 8 | GW12: 8 | GX12: 8 | GY12: 8 | GZ12: 7 | HA12: 8 | HB12: 8 | HC12: 8 | HD12: 7 | HE12: 1 | HF12: 4 | HG12: 4 | HH12: 5 | HI12: 6 | HJ12: 4 | HK12: 2 | HL12: 6 | HM12: 8 | HN12: 8 | HO12: 7 | HP12: 6 | HQ12: 2 | HR12: 7 | HS12: 5 | HT12: 6 | HU12: 8 | HV12: 8 | HW12: 3 | HX12: 7 | HY12: 1 | HZ12: 1 | IA12: 7 | IB12: 9 | IC12: 7 | ID12: 5 | IE12: 8 | IF12: 2 | IG12: 9 | IH12: 6 | II12: 9 | IJ12: 2 | IK12: 3 | IL12: 8 | IM12: 1 | IN12: 7 | IO12: 7 | IP12: 1 | IQ12: 9 | IR12: 8 | IS12: 4 | IT12: 5 | IU12: 2 | IV12: 9 | IW12: 6 | IX12: 3 | IY12: 7 | IZ12: 9 | JA12: 3 | JB12: 2 | JC12: 7 | JD12: 7 | JE12: 4 | JF12: 9 | JG12: 8 | JH12: 1 | JI12: 1 | JJ12: 5 | JK12: 6 | JL12: 3 | JM12: 9 | JN12: 6 | JO12: 4 | JP12: 7 | JQ12: 8 | JR12: 9 | JS12: 6 | JT12: 6 | JU12: 8 | JV12: 5 | JW12: 3 | JX12: 3 | JY12: 6 | JZ12: 2 | KA12: 6 | KB12: 6 | KC12: 8 | KD12: 7 | KE12: 8 | KF12: 9 | KG12: 6 | KH12: 3 | KI12: 3 | KJ12: 1 | KK12: 5 | KL12: 4 | KM12: 9 | KN12: 9 | KO12: 5 | KP12: 4 | KQ12: 7 | KR12: 6 | KS12: 4 | KT12: 2 | KU12: 1 | KV12: 4 | KW12: 4 | KX12: 1 | KY12: 6 | KZ12: 4 | LA12: 1 | LB12: 1 | LC12: 1 | LD12: 8 | LE12: 8 | LF12: 2 | LG12: 7 | LH12: 8 | LI12: 8 | LJ12: 7 | LK12: 5 | LL12: 1 | LM12: 9 | LN12: 7 | LO12: 2 | LP12: 6 | LQ12: 2 | LR12: 1 | LS12: 7 | LT12: 2 | LU12: 2 | LV12: 5 | LW12: 5 | LX12: 7 | LY12: 1 | LZ12: 8 | MA12: 3 | MB12: 4 | MC12: 9 | MD12: 4 | ME12: 5 | MF12: 7 | MG12: 4 | MH12: 1 | MI12: 9 | MJ12: 4 | MK12: 9 | ML12: 6 | MM12: 1 | MN12: 3 | MO12: 2 | MP12: 9 | MQ12: 1 | MR12: 9 | MS12: 9 | MT12: 8 | MU12: 8 | MV12: 1 | MW12: 8 | MX12: 3 | MY12: 7 | MZ12: 1 | NA12: 1 | NB12: 5 | NC12: 5 | ND12: 8 | NE12: 7 | NF12: 8 | NG12: 6 | NH12: 6 | NI12: 2 | NJ12: 6 | NK12: 5 | NL12: 3 | NM12: 6 | NN12: 8 | NO12: 9 | NP12: 1 | NQ12: 3 | NR12: 3 | NS12: 8 | NT12: 1 | NU12: 5 | NV12: 3 | NW12: 2 | NX12: 8 | NY12: 3 | NZ12: 7 | OA12: 1 | OB12: 6 | OC12: 3 | OD12: 8 | OE12: 6 | OF12: 2 | OG12: 6 | OH12: 7 | OI12: 5 | OJ12: 3 | OK12: 4 | OL12: 4 | OM12: 6 | ON12: 1 | OO12: 4 | OP12: 4 | OQ12: 1 | OR12: 9 | OS12: 4 | OT12: 7 | OU12: 3 | OV12: 3 | OW12: 8 | OX12: 8 | OY12: 1 | OZ12: 2 | PA12: 8 | PB12: 1 | PC12: 8 | PD12: 8 | PE12: 2 | PF12: 4 | PG12: 6 | PH12: 9 | PI12: 8 | PJ12: 8 | PK12: 7 | PL12: 9 | PM12: 2 | PN12: 3 | PO12: 8 | PP12: 6 | PQ12: 9 | PR12: 4 | PS12: 8 | PT12: 3 | PU12: 3 | PV12: 8 | PW12: 5 | PX12: 3 | PY12: 1 | PZ12: 3 | QA12: 9 | QB12: 5 | QC12: 2 | QD12: 7 | QE12: 2 | QF12: 4 | QG12: 7 | QH12: 4 | QI12: 7 | QJ12: 7 | QK12: 1 | QL12: 6 | QM12: 9 | QN12: 2 | QO12: 3 | QP12: 5 | QQ12: 9 | QR12: 4 | QS12: 1 | QT12: 4 | QU12: 6 | QV12: 5 | QW12: 1 | QX12: 4 | QY12: 6 | QZ12: 4 | RA12: 9 | RB12: 5 | RC12: 8 | RD12: 9 | RE12: 5 | RF12: 6 | RG12: 1 | RH12: 7 | RI12: 4 | RJ12: 2 | RK12: 5 | RL12: 3 | RM12: 6 | RN12: 8 | RO12: 7 | RP12: 3 | RQ12: 8 | RR12: 2 | RS12: 9 | RT12: 4 | RU12: 1 | RV12: 8 | RW12: 7 | RX12: 5 | RY12: 5 | RZ12: 7 | SA12: 5 | SB12: 8 | SC12: 6 | SD12: 5 | SE12: 9 | SF12: 2 | SG12: 1
A13: Unit Price | B13: 2843.87 | C13: 2525.23 | D13: 3474.34 | E13: 1008.79 | F13: 3511.47 | G13: 3189.55 | H13: 3030.42 | I13: 2310.83 | J13: 1098.04 | K13: 1780.66 | L13: 3205.25 | M13: 272.35 | N13: 3160.9 | O13: 1074.27 | P13: 705.59 | Q13: 595.45 | R13: 254.91 | S13: 2165.81 | T13: 990.3 | U13: 3959.31 | V13: 2361.58 | W13: 680.86 | X13: 2801.74 | Y13: 3606.31 | Z13: 3018.94 | AA13: 444.29 | AB13: 3599.15 | AC13: 3206.63 | AD13: 759.47 | AE13: 349.38 | AF13: 2295.65 | AG13: 750.74 | AH13: 3363.18 | AI13: 1529.59 | AJ13: 3664.64 | AK13: 2327.9 | AL13: 853.29 | AM13: 687.46 | AN13: 2369.42 | AO13: 3083.25 | AP13: 3158.8 | AQ13: 1211.67 | AR13: 936.35 | AS13: 214.51 | AT13: 2764.92 | AU13: 444.79 | AV13: 1769.93 | AW13: 2466.48 | AX13: 3757.87 | AY13: 1350.44 | AZ13: 1111.62 | BA13: 2668.52 | BB13: 2534.07 | BC13: 1428.62 | BD13: 3723.19 | BE13: 3402.72 | BF13: 1012.33 | BG13: 1070.7 | BH13: 2122.36 | BI13: 3128.25 | BJ13: 319.56 | BK13: 2819.34 | BL13: 2645.71 | BM13: 1041.2 | BN13: 2773.21 | BO13: 3769.71 | BP13: 330.13 | BQ13: 1380.66 | BR13: 1836.98 | BS13: 3612.15 | BT13: 3854.71 | BU13: 1859.84 | BV13: 3037.61 | BW13: 2196.89 | BX13: 2220.46 | BY13: 1220.68 | BZ13: 985.28 | CA13: 1258.82 | CB13: 2291.86 | CC13: 262.25 | CD13: 3642.91 | CE13: 751.69 | CF13: 997.34 | CG13: 2145.36 | CH13: 2883.94 | CI13: 518.56 | CJ13: 1373.12 | CK13: 3879.4 | CL13: 1160.02 | CM13: 1355.24 | CN13: 3370.52 | CO13: 343.33 | CP13: 1938.76 | CQ13: 1611.52 | CR13: 1368.86 | CS13: 1249.94 | CT13: 501.79 | CU13: 1362.08 | CV13: 315.75 | CW13: 3156.71 | CX13: 1683.18 | CY13: 1859.03 | CZ13: 3590.34 | DA13: 2683.51 | DB13: 181.03 | DC13: 3781.22 | DD13: 1063.01 | DE13: 564.31 | DF13: 3107.29 | DG13: 2076.84 | DH13: 1820.02 | DI13: 1110.59 | DJ13: 2257.77 | DK13: 1206.38 | DL13: 3621.09 | DM13: 978.54 | DN13: 3554.77 | DO13: 2303.71 | DP13: 3339.68 | DQ13: 2894.46 | DR13: 2832.28 | DS13: 1398.73 | DT13: 1050.5 | DU13: 961.91 | DV13: 3450.19 | DW13: 3308.64 | DX13: 1846.21 | DY13: 659.76 | DZ13: 1621.67 | EA13: 2534.47 | EB13: 1899.45 | EC13: 3153.73 | ED13: 3990.85 | EE13: 885.86 | EF13: 1919.66 | EG13: 1809.29 | EH13: 1322.3 | EI13: 912.67 | EJ13: 402.91 | EK13: 3565.41 | EL13: 1766.42 | EM13: 2063.05 | EN13: 3680.23 | EO13: 3138.72 | EP13: 652.43 | EQ13: 2326.87 | ER13: 1852.67 | ES13: 3219.26 | ET13: 2938.3 | EU13: 2808.06 | EV13: 1461.1 | EW13: 3249.11 | EX13: 351.71 | EY13: 764.56 | EZ13: 1442.15 | FA13: 445.71 | FB13: 1054.73 | FC13: 3346.08 | FD13: 3800.77 | FE13: 1322.72 | FF13: 1168.39 | FG13: 1227.59 | FH13: 1219.22 | FI13: 288.33 | FJ13: 3718.63 | FK13: 972.74 | FL13: 1767.02 | FM13: 187.29 | FN13: 3453.13 | FO13: 2964.96 | FP13: 3795.01 | FQ13: 3159.22 | FR13: 1357.77 | FS13: 1104.31 | FT13: 2836.21 | FU13: 1551.83 | FV13: 2329.93 | FW13: 174.09 | FX13: 388.26 | FY13: 2211.17 | FZ13: 2329.38 | GA13: 3043.09 | GB13: 658.07 | GC13: 2125.75 | GD13: 898.62 | GE13: 508.81 | GF13: 1730.41 | GG13: 778.85 | GH13: 1003.86 | GI13: 1372.59 | GJ13: 1148.65 | GK13: 487.23 | GL13: 496.18 | GM13: 894.01 | GN13: 344.65 | GO13: 2561.86 | GP13: 1256.21 | GQ13: 1227.02 | GR13: 1428.19 | GS13: 2701.77 | GT13: 3501.94 | GU13: 3072.48 | GV13: 2950.99 | GW13: 2014.91 | GX13: 2821.15 | GY13: 2278.14 | GZ13: 982.56 | HA13: 953.07 | HB13: 1291.11 | HC13: 3656.59 | HD13: 2257.55 | HE13: 2975.54 | HF13: 1484.25 | HG13: 1719.71 | HH13: 633.43 | HI13: 809.49 | HJ13: 3335.32 | HK13: 2401.63 | HL13: 1449.5 | HM13: 3240.98 | HN13: 1099.1 | HO13: 3907.73 | HP13: 1477.55 | HQ13: 1448.65 | HR13: 1350.86 | HS13: 620.13 | HT13: 577.88 | HU13: 2645.2 | HV13: 3519.2 | HW13: 3193.5 | HX13: 693.26 | HY13: 2250.49 | HZ13: 556.53 | IA13: 324.38 | IB13: 2677.09 | IC13: 2210.34 | ID13: 465.79 | IE13: 284.52 | IF13: 3960.56 | IG13: 265.58 | IH13: 1861.43 | II13: 2092.78 | IJ13: 601.53 | IK13: 800.89 | IL13: 1504.45 | IM13: 3082.45 | IN13: 2102.27 | IO13: 2605.92 | IP13: 3942.92 | IQ13: 3106.82 | IR13: 1822.29 | IS13: 1868.8 | IT13: 2532.27 | IU13: 2711.66 | IV13: 2077.74 | IW13: 2632.72 | IX13: 240.6 | IY13: 1804.05 | IZ13: 1223.91 | JA13: 647.32 | JB13: 533.25 | JC13: 2472.29 | JD13: 2165.86 | JE13: 1126.3 | JF13: 1963.16 | JG13: 2045.09 | JH13: 900.78 | JI13: 2660.56 | JJ13: 3156.54 | JK13: 3197.13 | JL13: 2469.51 | JM13: 2119.81 | JN13: 384.88 | JO13: 1258.15 | JP13: 509.1 | JQ13: 3860.72 | JR13: 670.06 | JS13: 734.34 | JT13: 3574.87 | JU13: 3784.12 | JV13: 3098.44 | JW13: 170.81 | JX13: 155.18 | JY13: 1605.69 | JZ13: 702.07 | KA13: 220.79 | KB13: 1936.66 | KC13: 3780.79 | KD13: 1396.71 | KE13: 2695.39 | KF13: 2661.11 | KG13: 1116.66 | KH13: 2654.14 | KI13: 967.49 | KJ13: 619.73 | KK13: 2850.33 | KL13: 586.75 | KM13: 3988.1 | KN13: 856.29 | KO13: 2437.45 | KP13: 1733.79 | KQ13: 636.59 | KR13: 257.2 | KS13: 2547.52 | KT13: 3256.02 | KU13: 3391.76 | KV13: 2008.45 | KW13: 3143.2 | KX13: 2740.46 | KY13: 2938.38 | KZ13: 2046.51 | LA13: 2588.64 | LB13: 3251.27 | LC13: 1681.85 | LD13: 3253.02 | LE13: 2429.26 | LF13: 788.72 | LG13: 245.03 | LH13: 1546.6 | LI13: 2254.78 | LJ13: 3383.31 | LK13: 640.82 | LL13: 3230.79 | LM13: 3472.58 | LN13: 730.15 | LO13: 3428.64 | LP13: 3967.1 | LQ13: 2948.33 | LR13: 3171.36 | LS13: 3978.5 | LT13: 2481.1 | LU13: 1335.36 | LV13: 3374.49 | LW13: 2515.77 | LX13: 2387.6 | LY13: 1126.5 | LZ13: 3061.89 | MA13: 464.42 | MB13: 3708.51 | MC13: 1404.42 | MD13: 641.93 | ME13: 1853.11 | MF13: 313.51 | MG13: 2785.81 | MH13: 3625.42 | MI13: 3373.46 | MJ13: 640.37 | MK13: 636.14 | ML13: 3281.72 | MM13: 3708.38 | MN13: 1923.58 | MO13: 2071.04 | MP13: 1375.31 | MQ13: 3592.92 | MR13: 2632.88 | MS13: 1259.77 | MT13: 1300.31 | MU13: 3581.12 | MV13: 202.49 | MW13: 1392.5 | MX13: 2284.27 | MY13: 720.64 | MZ13: 504.58 | NA13: 3288.81 | NB13: 3593.46 | NC13: 3320.88 | ND13: 3610.33 | NE13: 2279.48 | NF13: 3277.19 | NG13: 1628.56 | NH13: 2715.13 | NI13: 3957.02 | NJ13: 1019.05 | NK13: 1651.11 | NL13: 1998.18 | NM13: 681.36 | NN13: 462 | NO13: 3344.43 | NP13: 3910.66 | NQ13: 1708.19 | NR13: 487.45 | NS13: 403.38 | NT13: 3581.58 | NU13: 1935.68 | NV13: 1382.11 | NW13: 1984.38 | NX13: 1375.47 | NY13: 2032.79 | NZ13: 3459.29 | OA13: 2430.36 | OB13: 2824.42 | OC13: 1553.98 | OD13: 2993.25 | OE13: 2716.48 | OF13: 610.31 | OG13: 2354.67 | OH13: 1138.46 | OI13: 3245.77 | OJ13: 1789.86 | OK13: 3979.53 | OL13: 506.13 | OM13: 3154.34 | ON13: 2743.75 | OO13: 3104.87 | OP13: 1333.99 | OQ13: 2044.41 | OR13: 3216.56 | OS13: 1045.28 | OT13: 1020.23 | OU13: 2271.55 | OV13: 2165.72 | OW13: 1236.71 | OX13: 1297.59 | OY13: 1219.7 | OZ13: 3120.32 | PA13: 2659.82 | PB13: 3354.81 | PC13: 3905.57 | PD13: 1975.53 | PE13: 406.77 | PF13: 335.16 | PG13: 1288.31 | PH13: 3740.3 | PI13: 2164.37 | PJ13: 1196.38 | PK13: 1686.79 | PL13: 2454.59 | PM13: 2663.86 | PN13: 742.59 | PO13: 3911.57 | PP13: 2247.37 | PQ13: 672.4 | PR13: 3590.5 | PS13: 437.36 | PT13: 3644.78 | PU13: 3986.78 | PV13: 2846.66 | PW13: 3116.22 | PX13: 1448.62 | PY13: 3775.07 | PZ13: 2189.4 | QA13: 2969.7 | QB13: 3707.81 | QC13: 3904.44 | QD13: 3357.84 | QE13: 1316.62 | QF13: 3871.21 | QG13: 2568.26 | QH13: 3732.97 | QI13: 2753 | QJ13: 1332.87 | QK13: 1574.59 | QL13: 2269.32 | QM13: 3191.56 | QN13: 1374.23 | QO13: 2381.96 | QP13: 1480.66 | QQ13: 3290.71 | QR13: 1946.9 | QS13: 445.38 | QT13: 789.3 | QU13: 385.25 | QV13: 2072.32 | QW13: 559.4 | QX13: 589.44 | QY13: 3773.04 | QZ13: 3509.72 | RA13: 1890.53 | RB13: 3945.35 | RC13: 150.72 | RD13: 2513.82 | RE13: 2523.25 | RF13: 1911.16 | RG13: 1678.25 | RH13: 1903.23 | RI13: 1747.6 | RJ13: 2962.4 | RK13: 671.12 | RL13: 910.91 | RM13: 845 | RN13: 1160.51 | RO13: 2172.24 | RP13: 578.15 | RQ13: 3492.45 | RR13: 1294.84 | RS13: 775.77 | RT13: 2751.14 | RU13: 296.63 | RV13: 2536.88 | RW13: 2838.06 | RX13: 977.43 | RY13: 311.56 | RZ13: 1550.03 | SA13: 529.59 | SB13: 598.44 | SC13: 1128.91 | SD13: 1287.55 | SE13: 2190.39 | SF13: 2761.81 | SG13: 2432.17
A14: Discount % | B14: 0 | C14: 5 | D14: 15 | E14: 15 | F14: 20 | G14: 10 | H14: 10 | I14: 10 | J14: 15 | K14: 20 | L14: 0 | M14: 5 | N14: 0 | O14: 15 | P14: 10 | Q14: 5 | R14: 15 | S14: 15 | T14: 15 | U14: 5 | V14: 5 | W14: 20 | X14: 20 | Y14: 0 | Z14: 5 | AA14: 5 | AB14: 5 | AC14: 20 | AD14: 15 | AE14: 10 | AF14: 20 | AG14: 5 | AH14: 20 | AI14: 0 | AJ14: 5 | AK14: 0 | AL14: 5 | AM14: 20 | AN14: 15 | AO14: 10 | AP14: 0 | AQ14: 20 | AR14: 15 | AS14: 20 | AT14: 0 | AU14: 10 | AV14: 20 | AW14: 5 | AX14: 15 | AY14: 20 | AZ14: 15 | BA14: 5 | BB14: 10 | BC14: 10 | BD14: 5 | BE14: 15 | BF14: 20 | BG14: 5 | BH14: 0 | BI14: 15 | BJ14: 10 | BK14: 5 | BL14: 10 | BM14: 15 | BN14: 10 | BO14: 5 | BP14: 15 | BQ14: 0 | BR14: 5 | BS14: 20 | BT14: 5 | BU14: 15 | BV14: 5 | BW14: 0 | BX14: 0 | BY14: 20 | BZ14: 10 | CA14: 15 | CB14: 15 | CC14: 10 | CD14: 0 | CE14: 0 | CF14: 5 | CG14: 20 | CH14: 20 | CI14: 20 | CJ14: 5 | CK14: 20 | CL14: 10 | CM14: 5 | CN14: 10 | CO14: 5 | CP14: 20 | CQ14: 10 | CR14: 10 | CS14: 10 | CT14: 5 | CU14: 15 | CV14: 20 | CW14: 10 | CX14: 15 | CY14: 20 | CZ14: 20 | DA14: 10 | DB14: 10 | DC14: 5 | DD14: 15 | DE14: 15 | DF14: 10 | DG14: 20 | DH14: 10 | DI14: 20 | DJ14: 20 | DK14: 10 | DL14: 0 | DM14: 15 | DN14: 20 | DO14: 20 | DP14: 0 | DQ14: 5 | DR14: 0 | DS14: 0 | DT14: 20 | DU14: 15 | DV14: 0 | DW14: 5 | DX14: 10 | DY14: 0 | DZ14: 0 | EA14: 5 | EB14: 15 | EC14: 0 | ED14: 0 | EE14: 15 | EF14: 5 | EG14: 0 | EH14: 15 | EI14: 0 | EJ14: 10 | EK14: 20 | EL14: 10 | EM14: 0 | EN14: 5 | EO14: 20 | EP14: 10 | EQ14: 15 | ER14: 5 | ES14: 10 | ET14: 15 | EU14: 0 | EV14: 15 | EW14: 10 | EX14: 10 | EY14: 0 | EZ14: 15 | FA14: 15 | FB14: 0 | FC14: 15 | FD14: 0 | FE14: 5 | FF14: 10 | FG14: 5 | FH14: 20 | FI14: 20 | FJ14: 20 | FK14: 0 | FL14: 15 | FM14: 5 | FN14: 5 | FO14: 5 | FP14: 5 | FQ14: 20 | FR14: 5 | FS14: 15 | FT14: 20 | FU14: 5 | FV14: 0 | FW14: 10 | FX14: 10 | FY14: 10 | FZ14: 20 | GA14: 5 | GB14: 20 | GC14: 15 | GD14: 0 | GE14: 0 | GF14: 10 | GG14: 10 | GH14: 10 | GI14: 5 | GJ14: 15 | GK14: 15 | GL14: 15 | GM14: 15 | GN14: 10 | GO14: 0 | GP14: 10 | GQ14: 15 | GR14: 10 | GS14: 15 | GT14: 20 | GU14: 0 | GV14: 20 | GW14: 5 | GX14: 10 | GY14: 5 | GZ14: 10 | HA14: 20 | HB14: 15 | HC14: 15 | HD14: 10 | HE14: 15 | HF14: 20 | HG14: 15 | HH14: 20 | HI14: 5 | HJ14: 20 | HK14: 0 | HL14: 0 | HM14: 0 | HN14: 10 | HO14: 10 | HP14: 10 | HQ14: 20 | HR14: 10 | HS14: 5 | HT14: 0 | HU14: 20 | HV14: 0 | HW14: 10 | HX14: 20 | HY14: 15 | HZ14: 5 | IA14: 10 | IB14: 10 | IC14: 5 | ID14: 5 | IE14: 15 | IF14: 10 | IG14: 10 | IH14: 0 | II14: 20 | IJ14: 20 | IK14: 0 | IL14: 20 | IM14: 5 | IN14: 20 | IO14: 20 | IP14: 0 | IQ14: 15 | IR14: 20 | IS14: 20 | IT14: 15 | IU14: 0 | IV14: 15 | IW14: 0 | IX14: 5 | IY14: 0 | IZ14: 5 | JA14: 5 | JB14: 0 | JC14: 10 | JD14: 0 | JE14: 20 | JF14: 20 | JG14: 10 | JH14: 5 | JI14: 10 | JJ14: 20 | JK14: 10 | JL14: 0 | JM14: 10 | JN14: 5 | JO14: 0 | JP14: 15 | JQ14: 20 | JR14: 20 | JS14: 10 | JT14: 0 | JU14: 15 | JV14: 0 | JW14: 20 | JX14: 0 | JY14: 15 | JZ14: 10 | KA14: 5 | KB14: 0 | KC14: 5 | KD14: 20 | KE14: 10 | KF14: 10 | KG14: 0 | KH14: 10 | KI14: 0 | KJ14: 0 | KK14: 5 | KL14: 10 | KM14: 0 | KN14: 5 | KO14: 15 | KP14: 5 | KQ14: 5 | KR14: 0 | KS14: 20 | KT14: 20 | KU14: 20 | KV14: 5 | KW14: 0 | KX14: 10 | KY14: 5 | KZ14: 5 | LA14: 0 | LB14: 15 | LC14: 5 | LD14: 15 | LE14: 15 | LF14: 20 | LG14: 0 | LH14: 15 | LI14: 0 | LJ14: 20 | LK14: 0 | LL14: 5 | LM14: 15 | LN14: 0 | LO14: 10 | LP14: 0 | LQ14: 15 | LR14: 20 | LS14: 20 | LT14: 15 | LU14: 5 | LV14: 5 | LW14: 20 | LX14: 20 | LY14: 15 | LZ14: 5 | MA14: 20 | MB14: 5 | MC14: 20 | MD14: 0 | ME14: 10 | MF14: 0 | MG14: 20 | MH14: 10 | MI14: 10 | MJ14: 20 | MK14: 20 | ML14: 5 | MM14: 20 | MN14: 15 | MO14: 20 | MP14: 15 | MQ14: 20 | MR14: 5 | MS14: 15 | MT14: 0 | MU14: 15 | MV14: 5 | MW14: 15 | MX14: 20 | MY14: 20 | MZ14: 5 | NA14: 10 | NB14: 20 | NC14: 0 | ND14: 5 | NE14: 15 | NF14: 15 | NG14: 0 | NH14: 20 | NI14: 5 | NJ14: 0 | NK14: 20 | NL14: 5 | NM14: 15 | NN14: 5 | NO14: 10 | NP14: 5 | NQ14: 10 | NR14: 5 | NS14: 10 | NT14: 15 | NU14: 20 | NV14: 10 | NW14: 10 | NX14: 15 | NY14: 10 | NZ14: 0 | OA14: 15 | OB14: 0 | OC14: 15 | OD14: 10 | OE14: 0 | OF14: 10 | OG14: 15 | OH14: 10 | OI14: 0 | OJ14: 0 | OK14: 10 | OL14: 5 | OM14: 15 | ON14: 15 | OO14: 10 | OP14: 5 | OQ14: 0 | OR14: 20 | OS14: 20 | OT14: 10 | OU14: 5 | OV14: 5 | OW14: 15 | OX14: 0 | OY14: 5 | OZ14: 20 | PA14: 0 | PB14: 0 | PC14: 10 | PD14: 5 | PE14: 10 | PF14: 5 | PG14: 15 | PH14: 10 | PI14: 10 | PJ14: 20 | PK14: 10 | PL14: 5 | PM14: 20 | PN14: 10 | PO14: 10 | PP14: 15 | PQ14: 10 | PR14: 0 | PS14: 20 | PT14: 0 | PU14: 20 | PV14: 15 | PW14: 10 | PX14: 10 | PY14: 10 | PZ14: 20 | QA14: 10 | QB14: 0 | QC14: 10 | QD14: 15 | QE14: 0 | QF14: 10 | QG14: 10 | QH14: 5 | QI14: 20 | QJ14: 0 | QK14: 5 | QL14: 15 | QM14: 20 | QN14: 0 | QO14: 10 | QP14: 0 | QQ14: 10 | QR14: 20 | QS14: 10 | QT14: 15 | QU14: 10 | QV14: 15 | QW14: 20 | QX14: 20 | QY14: 0 | QZ14: 15 | RA14: 15 | RB14: 5 | RC14: 5 | RD14: 5 | RE14: 10 | RF14: 5 | RG14: 15 | RH14: 10 | RI14: 20 | RJ14: 0 | RK14: 5 | RL14: 20 | RM14: 15 | RN14: 0 | RO14: 20 | RP14: 0 | RQ14: 5 | RR14: 15 | RS14: 0 | RT14: 20 | RU14: 5 | RV14: 5 | RW14: 20 | RX14: 20 | RY14: 0 | RZ14: 10 | SA14: 5 | SB14: 0 | SC14: 20 | SD14: 0 | SE14: 20 | SF14: 15 | SG14: 20
A15: Net Sales | B15: 19907.09 | C15: 21590.72 | D15: 17719.13 | E15: 857.47 | F15: 19664.23 | G15: 8611.78 | H15: 13636.89 | I15: 8318.99 | J15: 4666.67 | K15: 7122.64 | L15: 19231.5 | M15: 1552.39 | N15: 25287.2 | O15: 7305.04 | P15: 5715.28 | Q15: 4525.42 | R15: 433.35 | S15: 1840.94 | T15: 1683.51 | U15: 7522.69 | V15: 6730.5 | W15: 3812.82 | X15: 4482.78 | Y15: 3606.31 | Z15: 17207.96 | AA15: 3798.68 | AB15: 10257.58 | AC15: 15391.82 | AD15: 1936.65 | AE15: 314.44 | AF15: 9182.6 | AG15: 2852.81 | AH15: 18833.81 | AI15: 9177.54 | AJ15: 24369.86 | AK15: 11639.5 | AL15: 3242.5 | AM15: 3849.78 | AN15: 14098.05 | AO15: 16649.55 | AP15: 25270.4 | AQ15: 3877.34 | AR15: 3979.49 | AS15: 686.43 | AT15: 2764.92 | AU15: 3202.49 | AV15: 1415.94 | AW15: 11715.78 | AX15: 19165.14 | AY15: 6482.11 | AZ15: 4724.39 | BA15: 7605.28 | BB15: 11403.31 | BC15: 10286.06 | BD15: 7074.06 | BE15: 17353.87 | BF15: 7288.78 | BG15: 8137.32 | BH15: 16978.88 | BI15: 21272.1 | BJ15: 2013.23 | BK15: 21426.98 | BL15: 14286.83 | BM15: 1770.04 | BN15: 4991.78 | BO15: 28649.8 | BP15: 280.61 | BQ15: 8283.96 | BR15: 10470.79 | BS15: 11558.88 | BT15: 10985.92 | BU15: 4742.59 | BV15: 2885.73 | BW15: 6590.67 | BX15: 8881.84 | BY15: 4882.72 | BZ15: 2660.26 | CA15: 6419.98 | CB15: 9740.4 | CC15: 708.07 | CD15: 21857.46 | CE15: 4510.14 | CF15: 7579.78 | CG15: 3432.58 | CH15: 2307.15 | CI15: 1659.39 | CJ15: 9131.25 | CK15: 9310.56 | CL15: 3132.05 | CM15: 6437.39 | CN15: 15167.34 | CO15: 978.49 | CP15: 13959.07 | CQ15: 5801.47 | CR15: 3695.92 | CS15: 2249.89 | CT15: 4290.3 | CU15: 4631.07 | CV15: 757.8 | CW15: 19887.27 | CX15: 11445.62 | CY15: 2974.45 | CZ15: 20105.9 | DA15: 12075.79 | DB15: 814.63 | DC15: 10776.48 | DD15: 4517.79 | DE15: 959.33 | DF15: 11186.24 | DG15: 9968.83 | DH15: 1638.02 | DI15: 3553.89 | DJ15: 10837.3 | DK15: 9771.68 | DL15: 7242.18 | DM15: 5822.31 | DN15: 17062.9 | DO15: 3685.94 | DP15: 26717.44 | DQ15: 19248.16 | DR15: 14161.4 | DS15: 6993.65 | DT15: 5882.8 | DU15: 7358.61 | DV15: 31051.71 | DW15: 28288.87 | DX15: 9969.53 | DY15: 3958.56 | DZ15: 4865.01 | EA15: 2407.75 | EB15: 11301.73 | EC15: 12614.92 | ED15: 3990.85 | EE15: 6023.85 | EF15: 10942.06 | EG15: 10855.74 | EH15: 2247.91 | EI15: 912.67 | EJ15: 725.24 | EK15: 11409.31 | EL15: 3179.56 | EM15: 2063.05 | EN15: 24473.53 | EO15: 20087.81 | EP15: 3523.12 | EQ15: 7911.36 | ER15: 10560.22 | ES15: 8692 | ET15: 19980.44 | EU15: 5616.12 | EV15: 6209.68 | EW15: 2924.2 | EX15: 1899.23 | EY15: 1529.12 | EZ15: 4903.31 | FA15: 2273.12 | FB15: 8437.84 | FC15: 22753.34 | FD15: 22804.62 | FE15: 5026.34 | FF15: 8412.41 | FG15: 9329.68 | FH15: 975.38 | FI15: 922.66 | FJ15: 11899.62 | FK15: 6809.18 | FL15: 10513.77 | FM15: 1423.4 | FN15: 16402.37 | FO15: 19716.98 | FP15: 28842.08 | FQ15: 22746.38 | FR15: 3869.64 | FS15: 2815.99 | FT15: 9075.87 | FU15: 7371.19 | FV15: 2329.93 | FW15: 1096.77 | FX15: 3144.91 | FY15: 15920.42 | FZ15: 9317.52 | GA15: 11563.74 | GB15: 3685.19 | GC15: 9034.44 | GD15: 6290.34 | GE15: 508.81 | GF15: 1557.37 | GG15: 2102.89 | GH15: 1806.95 | GI15: 2607.92 | GJ15: 6834.47 | GK15: 828.29 | GL15: 1687.01 | GM15: 1519.82 | GN15: 1861.11 | GO15: 20494.88 | GP15: 4522.36 | GQ15: 5214.84 | GR15: 5141.48 | GS15: 6889.51 | GT15: 14007.76 | GU15: 27652.32 | GV15: 18886.34 | GW15: 15313.32 | GX15: 20312.28 | GY15: 17313.86 | GZ15: 6190.13 | HA15: 6099.65 | HB15: 8779.55 | HC15: 24864.81 | HD15: 14222.56 | HE15: 2529.21 | HF15: 4749.6 | HG15: 5847.01 | HH15: 2533.72 | HI15: 4614.09 | HJ15: 10673.02 | HK15: 4803.26 | HL15: 8697 | HM15: 25927.84 | HN15: 7913.52 | HO15: 24618.7 | HP15: 7978.77 | HQ15: 2317.84 | HR15: 8510.42 | HS15: 2945.62 | HT15: 3467.28 | HU15: 16929.28 | HV15: 28153.6 | HW15: 8622.45 | HX15: 3882.26 | HY15: 1912.92 | HZ15: 528.7 | IA15: 2043.59 | IB15: 21684.43 | IC15: 14698.76 | ID15: 2212.5 | IE15: 1934.74 | IF15: 7129.01 | IG15: 2151.2 | IH15: 11168.58 | II15: 15068.02 | IJ15: 962.45 | IK15: 2402.67 | IL15: 9628.48 | IM15: 2928.33 | IN15: 11772.71 | IO15: 14593.15 | IP15: 3942.92 | IQ15: 23767.17 | IR15: 11662.66 | IS15: 5980.16 | IT15: 10762.15 | IU15: 5423.32 | IV15: 15894.71 | IW15: 15796.32 | IX15: 685.71 | IY15: 12628.35 | IZ15: 10464.43 | JA15: 1844.86 | JB15: 1066.5 | JC15: 15575.43 | JD15: 15161.02 | JE15: 3604.16 | JF15: 14134.75 | JG15: 14724.65 | JH15: 855.74 | JI15: 2394.5 | JJ15: 12626.16 | JK15: 17264.5 | JL15: 7408.53 | JM15: 17170.46 | JN15: 2193.82 | JO15: 5032.6 | JP15: 3029.14 | JQ15: 24708.61 | JR15: 4824.43 | JS15: 3965.44 | JT15: 21449.22 | JU15: 25732.02 | JV15: 15492.2 | JW15: 409.94 | JX15: 465.54 | JY15: 8189.02 | JZ15: 1263.73 | KA15: 1258.5 | KB15: 11619.96 | KC15: 28734 | KD15: 7821.58 | KE15: 19406.81 | KF15: 21554.99 | KG15: 6699.96 | KH15: 7166.18 | KI15: 2902.47 | KJ15: 619.73 | KK15: 13539.07 | KL15: 2112.3 | KM15: 35892.9 | KN15: 7321.28 | KO15: 10359.16 | KP15: 6588.4 | KQ15: 4233.32 | KR15: 1543.2 | KS15: 8152.06 | KT15: 5209.63 | KU15: 2713.41 | KV15: 7632.11 | KW15: 12572.8 | KX15: 2466.41 | KY15: 16748.77 | KZ15: 7776.74 | LA15: 2588.64 | LB15: 2763.58 | LC15: 1597.76 | LD15: 22120.54 | LE15: 16518.97 | LF15: 1261.95 | LG15: 1715.21 | LH15: 10516.88 | LI15: 18038.24 | LJ15: 18946.54 | LK15: 3204.1 | LL15: 3069.25 | LM15: 26565.24 | LN15: 5111.05 | LO15: 6171.55 | LP15: 23802.6 | LQ15: 5012.16 | LR15: 2537.09 | LS15: 22279.6 | LT15: 4217.87 | LU15: 2537.18 | LV15: 16028.83 | LW15: 10063.08 | LX15: 13370.56 | LY15: 957.52 | LZ15: 23270.36 | MA15: 1114.61 | MB15: 14092.34 | MC15: 10111.82 | MD15: 2567.72 | ME15: 8338.99 | MF15: 2194.57 | MG15: 8914.59 | MH15: 3262.88 | MI15: 27325.03 | MJ15: 2049.18 | MK15: 4580.21 | ML15: 18705.8 | MM15: 2966.7 | MN15: 4905.13 | MO15: 3313.66 | MP15: 10521.12 | MQ15: 2874.34 | MR15: 22511.12 | MS15: 9637.24 | MT15: 10402.48 | MU15: 24351.62 | MV15: 192.37 | MW15: 9469 | MX15: 5482.25 | MY15: 4035.58 | MZ15: 479.35 | NA15: 2959.93 | NB15: 14373.84 | NC15: 16604.4 | ND15: 27438.51 | NE15: 13562.91 | NF15: 22284.89 | NG15: 9771.36 | NH15: 13032.62 | NI15: 7518.34 | NJ15: 6114.3 | NK15: 6604.44 | NL15: 5694.81 | NM15: 3474.94 | NN15: 3511.2 | NO15: 27089.88 | NP15: 3715.13 | NQ15: 4612.11 | NR15: 1389.23 | NS15: 2904.34 | NT15: 3044.34 | NU15: 7742.72 | NV15: 3731.7 | NW15: 3571.88 | NX15: 9353.2 | NY15: 5488.53 | NZ15: 24215.03 | OA15: 2065.81 | OB15: 16946.52 | OC15: 3962.65 | OD15: 21551.4 | OE15: 16298.88 | OF15: 1098.56 | OG15: 12008.82 | OH15: 7172.3 | OI15: 16228.85 | OJ15: 5369.58 | OK15: 14326.31 | OL15: 1923.29 | OM15: 16087.13 | ON15: 2332.19 | OO15: 11177.53 | OP15: 5069.16 | OQ15: 2044.41 | OR15: 23159.23 | OS15: 3344.9 | OT15: 6427.45 | OU15: 6473.92 | OV15: 6172.3 | OW15: 8409.63 | OX15: 10380.72 | OY15: 1158.71 | OZ15: 4992.51 | PA15: 21278.56 | PB15: 3354.81 | PC15: 28120.1 | PD15: 15014.03 | PE15: 732.19 | PF15: 1273.61 | PG15: 6570.38 | PH15: 30296.43 | PI15: 15583.46 | PJ15: 7656.83 | PK15: 10626.78 | PL15: 20986.74 | PM15: 4262.18 | PN15: 2004.99 | PO15: 28163.3 | PP15: 11461.59 | PQ15: 5446.44 | PR15: 14362 | PS15: 2799.1 | PT15: 10934.34 | PU15: 9568.27 | PV15: 19357.29 | PW15: 14022.99 | PX15: 3911.27 | PY15: 3397.56 | PZ15: 5254.56 | QA15: 24054.57 | QB15: 18539.05 | QC15: 7027.99 | QD15: 19979.15 | QE15: 2633.24 | QF15: 13936.36 | QG15: 16180.04 | QH15: 14185.29 | QI15: 15416.8 | QJ15: 9330.09 | QK15: 1495.86 | QL15: 11573.53 | QM15: 22979.23 | QN15: 2748.46 | QO15: 6431.29 | QP15: 7403.3 | QQ15: 26654.75 | QR15: 6230.08 | QS15: 400.84 | QT15: 2683.62 | QU15: 2080.35 | QV15: 8807.36 | QW15: 447.52 | QX15: 1886.21 | QY15: 22638.24 | QZ15: 11933.05 | RA15: 14462.55 | RB15: 18740.41 | RC15: 1145.47 | RD15: 21493.16 | RE15: 11354.63 | RF15: 10893.61 | RG15: 1426.51 | RH15: 11990.35 | RI15: 5592.32 | RJ15: 5924.8 | RK15: 3187.82 | RL15: 2186.18 | RM15: 4309.5 | RN15: 9284.08 | RO15: 12164.54 | RP15: 1734.45 | RQ15: 26542.62 | RR15: 2201.23 | RS15: 6981.93 | RT15: 8803.65 | RU15: 281.8 | RV15: 19280.29 | RW15: 15893.14 | RX15: 3909.72 | RY15: 1557.8 | RZ15: 9765.19 | SA15: 2515.55 | SB15: 4787.52 | SC15: 5418.77 | SD15: 6437.75 | SE15: 15770.81 | SF15: 4695.08 | SG15: 1945.74
B19: Customer ID | C19: City
B20: 1270 | C20: =HLOOKUP(B20,A2:SG15,4,0) -> Bengaluru

Sheet Day812.10.26ind&match
A1: Order ID | B1: Customer ID | C1: Order Date | D1: Ship Date | E1: City | F1: State | G1: Sales Channel | H1: Payment Method | I1: Product Category | J1: Product Name | K1: Brand | L1: Units Sold | M1: Unit Price | N1: Discount % | O1: Net Sales | Q1: Serial no. | R1: value
A2: 10001 | B2: 1102 | C2: 45197 | D2: 45203 | E2: Chennai | F2: Delhi | G2: Mobile App | H2: Credit Card | I2: Home & Kitchen | J2: Mixer Grinder | K2: BrandA | L2: 7 | M2: 2843.87 | N2: 0 | O2: 19907.09 | Q2: 10 | R2: {=INDEX(A1:A501,Q2)} -> 10009
A3: 10002 | B3: 1435 | C3: 45199 | D3: 45203 | E3: Pune | F3: Tamil Nadu | G3: Website | H3: Debit Card | I3: Sports | J3: Football | K3: BrandD | L3: 9 | M3: 2525.23 | N3: 5 | O3: 21590.72
A4: 10003 | B4: 1860 | C4: 45109 | D4: 45114 | E4: Chennai | F4: West Bengal | G4: Marketplace | H4: Debit Card | I4: Fashion | J4: Sneakers | K4: BrandE | L4: 6 | M4: 3474.34 | N4: 15 | O4: 17719.13
A5: 10004 | B5: 1270 | C5: 45079 | D5: 45087 | E5: Bengaluru | F5: West Bengal | G5: Website | H5: Cash on Delivery | I5: Sports | J5: Yoga Mat | K5: BrandA | L5: 1 | M5: 1008.79 | N5: 15 | O5: 857.47 | Q5: Serial no. | R5: value
A6: 10005 | B6: 1106 | C6: 45241 | D6: 45244 | E6: Kolkata | F6: Karnataka | G6: Marketplace | H6: Credit Card | I6: Fashion | J6: Jacket | K6: BrandA | L6: 7 | M6: 3511.47 | N6: 20 | O6: 19664.23 | Q6: 5 | R6: {=INDEX(A1:O1,,Q6)} -> City
A7: 10006 | B7: 1071 | C7: 45260 | D7: 45263 | E7: Hyderabad | F7: Telangana | G7: Website | H7: Net Banking | I7: Home & Kitchen | J7: Bedsheet | K7: BrandE | L7: 3 | M7: 3189.55 | N7: 10 | O7: 8611.78
A8: 10007 | B8: 1700 | C8: 45050 | D8: 45054 | E8: Bengaluru | F8: Telangana | G8: Mobile App | H8: UPI | I8: Fashion | J8: Sneakers | K8: BrandC | L8: 5 | M8: 3030.42 | N8: 10 | O8: 13636.89
A9: 10008 | B9: 1020 | C9: 45040 | D9: 45041 | E9: Mumbai | F9: Delhi | G9: Website | H9: Credit Card | I9: Fashion | J9: Sneakers | K9: BrandB | L9: 4 | M9: 2310.83 | N9: 10 | O9: 8318.99 | Q9: row | R9: column | S9: value
A10: 10009 | B10: 1614 | C10: 45204 | D10: 45213 | E10: Chennai | F10: West Bengal | G10: Website | H10: Debit Card | I10: Fashion | J10: T-Shirt | K10: BrandD | L10: 5 | M10: 1098.04 | N10: 15 | O10: 4666.67 | Q10: 3 | R10: 2 | S10: {=INDEX(A1:O501,Q10,R10)} -> 1435
A11: 10010 | B11: 1121 | C11: 45139 | D11: 45147 | E11: Bengaluru | F11: Karnataka | G11: Website | H11: Cash on Delivery | I11: Electronics | J11: Headphones | K11: BrandB | L11: 5 | M11: 1780.66 | N11: 20 | O11: 7122.64 | V11: Sales Amt. | Y11: Sales Amt.
A12: 10011 | B12: 1466 | C12: 45098 | D12: 45106 | E12: Bengaluru | F12: Karnataka | G12: Mobile App | H12: Cash on Delivery | I12: Electronics | J12: Headphones | K12: BrandE | L12: 6 | M12: 3205.25 | N12: 0 | O12: 19231.5 | Q12: value | R12: position | V12: 5000 | Y12: 100
A13: 10012 | B13: 1214 | C13: 45214 | D13: 45220 | E13: Mumbai | F13: Tamil Nadu | G13: Website | H13: UPI | I13: Electronics | J13: Smartwatch | K13: BrandA | L13: 6 | M13: 272.35 | N13: 5 | O13: 1552.39 | Q13: unit price | R13: =MATCH(Q13,A1:O1,0) -> 13 | V13: 2000 | Y13: 1000
A14: 10013 | B14: 1330 | C14: 45100 | D14: 45107 | E14: Delhi | F14: Tamil Nadu | G14: Mobile App | H14: Cash on Delivery | I14: Home & Kitchen | J14: Bedsheet | K14: BrandA | L14: 8 | M14: 3160.9 | N14: 0 | O14: 25287.2 | V14: 1000 | Y14: 2000
A15: 10014 | B15: 1458 | C15: 45039 | D15: 45045 | E15: Kolkata | F15: Karnataka | G15: Marketplace | H15: Cash on Delivery | I15: Sports | J15: Yoga Mat | K15: BrandD | L15: 8 | M15: 1074.27 | N15: 15 | O15: 7305.04 | Q15: customer id | R15: order id | S15: product category | V15: 100 | Y15: 5000
A16: 10015 | B16: 1087 | C16: 45048 | D16: 45057 | E16: Hyderabad | F16: Tamil Nadu | G16: Website | H16: Credit Card | I16: Beauty | J16: Shampoo | K16: BrandA | L16: 9 | M16: 705.59 | N16: 10 | O16: 5715.28 | Q16: 1270 | R16: =INDEX(A1:A501,MATCH(Q16,B1:B501,0)) -> 10004 | S16: =INDEX(I1:I501,MATCH(Q16,B1:B501,0)) -> Sports
A17: 10016 | B17: 1372 | C17: 44958 | D17: 44961 | E17: Pune | F17: West Bengal | G17: Mobile App | H17: Net Banking | I17: Fashion | J17: Jacket | K17: BrandA | L17: 8 | M17: 595.45 | N17: 5 | O17: 4525.42
A18: 10017 | B18: 1099 | C18: 45148 | D18: 45151 | E18: Delhi | F18: Maharashtra | G18: Mobile App | H18: UPI | I18: Fashion | J18: Jacket | K18: BrandD | L18: 2 | M18: 254.91 | N18: 15 | O18: 433.35 | Q18: order id | R18: payment method | V18: value | W18: position | Y18: value | Z18: position
A19: 10018 | B19: 1871 | C19: 45045 | D19: 45048 | E19: Chennai | F19: West Bengal | G19: Website | H19: Credit Card | I19: Home & Kitchen | J19: Curtains | K19: BrandD | L19: 1 | M19: 2165.81 | N19: 15 | O19: 1840.94 | Q19: 10008 | R19: =INDEX(A1:O501,MATCH(Q19,A1:A501,0),MATCH(R18,A1:O1,0)) -> Credit Card | V19: 100 | W19: =MATCH(V19,V11:V15,-1) -> 5 | Y19: 4500 | Z19: =MATCH(Y19,Y12:Y15,1) -> 3
A20: 10019 | B20: 1663 | C20: 44965 | D20: 44968 | E20: Bengaluru | F20: Karnataka | G20: Marketplace | H20: Net Banking | I20: Fashion | J20: Jacket | K20: BrandE | L20: 2 | M20: 990.3 | N20: 15 | O20: 1683.51
A21: 10020 | B21: 1130 | C21: 45194 | D21: 45203 | E21: Mumbai | F21: Karnataka | G21: Mobile App | H21: Credit Card | I21: Electronics | J21: Smartwatch | K21: BrandA | L21: 2 | M21: 3959.31 | N21: 5 | O21: 7522.69
A22: 10021 | B22: 1661 | C22: 45159 | D22: 45163 | E22: Mumbai | F22: West Bengal | G22: Website | H22: Credit Card | I22: Beauty | J22: Lipstick | K22: BrandA | L22: 3 | M22: 2361.58 | N22: 5 | O22: 6730.5
A23: 10022 | B23: 1308 | C23: 44944 | D23: 44951 | E23: Kolkata | F23: Tamil Nadu | G23: Marketplace | H23: Cash on Delivery | I23: Books | J23: Fiction Novel | K23: BrandE | L23: 7 | M23: 680.86 | N23: 20 | O23: 3812.82
A24: 10023 | B24: 1769 | C24: 45075 | D24: 45084 | E24: Delhi | F24: Tamil Nadu | G24: Mobile App | H24: Net Banking | I24: Fashion | J24: Sneakers | K24: BrandC | L24: 2 | M24: 2801.74 | N24: 20 | O24: 4482.78
A25: 10024 | B25: 1343 | C25: 45075 | D25: 45082 | E25: Pune | F25: Telangana | G25: Mobile App | H25: UPI | I25: Electronics | J25: Smartwatch | K25: BrandC | L25: 1 | M25: 3606.31 | N25: 0 | O25: 3606.31
A26: 10025 | B26: 1491 | C26: 45052 | D26: 45061 | E26: Kolkata | F26: Karnataka | G26: Marketplace | H26: UPI | I26: Books | J26: Comics | K26: BrandC | L26: 6 | M26: 3018.94 | N26: 5 | O26: 17207.96
A27: 10026 | B27: 1413 | C27: 45228 | D27: 45231 | E27: Bengaluru | F27: Delhi | G27: Marketplace | H27: Net Banking | I27: Beauty | J27: Perfume | K27: BrandE | L27: 9 | M27: 444.29 | N27: 5 | O27: 3798.68
A28: 10027 | B28: 1805 | C28: 45286 | D28: 45290 | E28: Kolkata | F28: Telangana | G28: Website | H28: Cash on Delivery | I28: Books | J28: Fiction Novel | K28: BrandA | L28: 3 | M28: 3599.15 | N28: 5 | O28: 10257.58
A29: 10028 | B29: 1385 | C29: 45164 | D29: 45172 | E29: Hyderabad | F29: Tamil Nadu | G29: Website | H29: Debit Card | I29: Electronics | J29: Smartwatch | K29: BrandE | L29: 6 | M29: 3206.63 | N29: 20 | O29: 15391.82
A30: 10029 | B30: 1191 | C30: 45061 | D30: 45067 | E30: Mumbai | F30: West Bengal | G30: Mobile App | H30: Credit Card | I30: Sports | J30: Football | K30: BrandE | L30: 3 | M30: 759.47 | N30: 15 | O30: 1936.65
A31: 10030 | B31: 1955 | C31: 45077 | D31: 45082 | E31: Mumbai | F31: Tamil Nadu | G31: Marketplace | H31: Cash on Delivery | I31: Sports | J31: Cricket Bat | K31: BrandC | L31: 1 | M31: 349.38 | N31: 10 | O31: 314.44
... A501: 10500 | B501: 1569 | C501: 44972 | D501: 44977 | E501: Chennai | F501: Delhi | G501: Marketplace | H501: Net Banking | I501: Fashion | J501: Jeans | K501: BrandE | L501: 1 | M501: 2432.17 | N501: 20 | O501: 1945.74
A506: Order ID | B506: Customer ID | C506: Order Date | D506: Ship Date | E506: City | F506: State | G506: Sales Channel | H506: Payment Method | I506: Product Category | J506: Product Name | K506: Brand | L506: Units Sold | M506: Unit Price | N506: Discount % | O506: Net Sales
A507: 10498 | B507: {=INDEX(B1:O501,MATCH(A507,A1:A501,0),)} -> 1734 | C507: 45017 | D507: 45025 | E507: Mumbai | F507: Delhi | G507: Marketplace | H507: Credit Card | I507: Sports | J507: Yoga Mat | K507: BrandD | L507: 9 | M507: 2190.39 | N507: 20 | O507: 15770.81

Sheet Day9 13.10.26 X-lookup
A1: Order ID | B1: Customer ID | C1: Order Date | D1: Ship Date | E1: City | F1: State | G1: Sales Channel | H1: Payment Method | I1: Product Category | J1: Product Name | K1: Brand | L1: Units Sold | M1: Unit Price | N1: Discount % | O1: Net Sales | Q1: Order Date | R1: Order ID | T1: Order ID | U1: Net Sales
A2: 10001 | B2: 1102 | C2: 45197 | D2: 45203 | E2: Chennai | F2: Delhi | G2: Mobile App | H2: Credit Card | I2: Home & Kitchen | J2: Mixer Grinder | K2: BrandA | L2: 7 | M2: 2843.87 | N2: 0 | O2: 19907.09 | Q2: 45198 | R2: =_xlfn.XLOOKUP(Q2,C2:C501,A2:A501) -> 10462 | T2: 10001 | U2: =_xlfn.XLOOKUP(T2,A2:A501,O2:O501,"Not Found") -> 19907.09
A3: 10002 | B3: 1435 | C3: 45199 | D3: 45203 | E3: Pune | F3: Tamil Nadu | G3: Website | H3: Debit Card | I3: Sports | J3: Football | K3: BrandD | L3: 9 | M3: 2525.23 | N3: 5 | O3: 21590.72
A4: 10003 | B4: 1860 | C4: 45109 | D4: 45114 | E4: Chennai | F4: West Bengal | G4: Marketplace | H4: Debit Card | I4: Fashion | J4: Sneakers | K4: BrandE | L4: 6 | M4: 3474.34 | N4: 15 | O4: 17719.13 | Q4: Order ID | R4: Customer ID | S4: Order Date | T4: Ship Date | U4: City | V4: State | W4: Sales Channel | X4: Payment Method | Y4: Product Category | Z4: Product Name | AA4: Brand | AB4: Units Sold | AC4: Unit Price | AD4: Discount % | AE4: Net Sales
A5: 10004 | B5: 1270 | C5: 45079 | D5: 45087 | E5: Bengaluru | F5: West Bengal | G5: Website | H5: Cash on Delivery | I5: Sports | J5: Yoga Mat | K5: BrandA | L5: 1 | M5: 1008.79 | N5: 15 | O5: 857.47 | Q5: 10004 | R5: =_xlfn.XLOOKUP(Q5,A2:A501,B2:B501,"Not Found") -> 1270 | S5: =_xlfn.XLOOKUP(R5,B2:B501,C2:C501,"Not Found") -> 45079 | T5: =_xlfn.XLOOKUP(S5,C2:C501,D2:D501,"Not Found") -> 45087 | U5: =_xlfn.XLOOKUP(T5,D2:D501,E2:E501,"Not Found") -> Bengaluru | V5: =_xlfn.XLOOKUP(U5,E2:E501,F2:F501,"Not Found") -> West Bengal | W5: {=_xlfn.XLOOKUP(Q5,A2:A501,G2:O501)} -> Website | X5: Cash on Delivery | Y5: Sports | Z5: Yoga Mat | AA5: BrandA | AB5: 1 | AC5: 1008.79 | AD5: 15 | AE5: 857.47
A6: 10005 | B6: 1106 | C6: 45241 | D6: 45244 | E6: Kolkata | F6: Karnataka | G6: Marketplace | H6: Credit Card | I6: Fashion | J6: Jacket | K6: BrandA | L6: 7 | M6: 3511.47 | N6: 20 | O6: 19664.23
A7: 10006 | B7: 1071 | C7: 45260 | D7: 45263 | E7: Hyderabad | F7: Telangana | G7: Website | H7: Net Banking | I7: Home & Kitchen | J7: Bedsheet | K7: BrandE | L7: 3 | M7: 3189.55 | N7: 10 | O7: 8611.78 | Q7: Order ID | R7: City | S7: Units Sold
A8: 10007 | B8: 1700 | C8: 45050 | D8: 45054 | E8: Bengaluru | F8: Telangana | G8: Mobile App | H8: UPI | I8: Fashion | J8: Sneakers | K8: BrandC | L8: 5 | M8: 3030.42 | N8: 10 | O8: 13636.89 | Q8: 10010 | R8: {=_xlfn.XLOOKUP(Q8,A2:A501,CHOOSE({1,2},E2:E501,L2:L501))} -> Bengaluru | S8: 5
A9: 10008 | B9: 1020 | C9: 45040 | D9: 45041 | E9: Mumbai | F9: Delhi | G9: Website | H9: Credit Card | I9: Fashion | J9: Sneakers | K9: BrandB | L9: 4 | M9: 2310.83 | N9: 10 | O9: 8318.99
A10: 10009 | B10: 1614 | C10: 45204 | D10: 45213 | E10: Chennai | F10: West Bengal | G10: Website | H10: Debit Card | I10: Fashion | J10: T-Shirt | K10: BrandD | L10: 5 | M10: 1098.04 | N10: 15 | O10: 4666.67 | Q10: City | R10: Payment Method | S10: Net Sales
A11: 10010 | B11: 1121 | C11: 45139 | D11: 45147 | E11: Bengaluru | F11: Karnataka | G11: Website | H11: Cash on Delivery | I11: Electronics | J11: Headphones | K11: BrandB | L11: 5 | M11: 1780.66 | N11: 20 | O11: 7122.64 | Q11: Chennai | R11: Debit Card | S11: {=_xlfn.XLOOKUP(Q11&R11,E2:E501&H2:H501,O2:O501)} -> 17719.13
A12: 10011 | B12: 1466 | C12: 45098 | D12: 45106 | E12: Bengaluru | F12: Karnataka | G12: Mobile App | H12: Cash on Delivery | I12: Electronics | J12: Headphones | K12: BrandE | L12: 6 | M12: 3205.25 | N12: 0 | O12: 19231.5
A13: 10012 | B13: 1214 | C13: 45214 | D13: 45220 | E13: Mumbai | F13: Tamil Nadu | G13: Website | H13: UPI | I13: Electronics | J13: Smartwatch | K13: BrandA | L13: 6 | M13: 272.35 | N13: 5 | O13: 1552.39 | Q13: Customer ID | R13: 1663
A14: 10013 | B14: 1330 | C14: 45100 | D14: 45107 | E14: Delhi | F14: Tamil Nadu | G14: Mobile App | H14: Cash on Delivery | I14: Home & Kitchen | J14: Bedsheet | K14: BrandA | L14: 8 | M14: 3160.9 | N14: 0 | O14: 25287.2 | Q14: Order Date | R14: {=TRANSPOSE(_xlfn.XLOOKUP(R13,B2:B501,C2:O501))} -> 44965
A15: 10014 | B15: 1458 | C15: 45039 | D15: 45045 | E15: Kolkata | F15: Karnataka | G15: Marketplace | H15: Cash on Delivery | I15: Sports | J15: Yoga Mat | K15: BrandD | L15: 8 | M15: 1074.27 | N15: 15 | O15: 7305.04 | Q15: Ship Date | R15: 44968
A16: 10015 | B16: 1087 | C16: 45048 | D16: 45057 | E16: Hyderabad | F16: Tamil Nadu | G16: Website | H16: Credit Card | I16: Beauty | J16: Shampoo | K16: BrandA | L16: 9 | M16: 705.59 | N16: 10 | O16: 5715.28 | Q16: City | R16: Bengaluru
A17: 10016 | B17: 1372 | C17: 44958 | D17: 44961 | E17: Pune | F17: West Bengal | G17: Mobile App | H17: Net Banking | I17: Fashion | J17: Jacket | K17: BrandA | L17: 8 | M17: 595.45 | N17: 5 | O17: 4525.42 | Q17: State | R17: Karnataka
A18: 10017 | B18: 1099 | C18: 45148 | D18: 45151 | E18: Delhi | F18: Maharashtra | G18: Mobile App | H18: UPI | I18: Fashion | J18: Jacket | K18: BrandD | L18: 2 | M18: 254.91 | N18: 15 | O18: 433.35 | Q18: Sales Channel | R18: Marketplace
A19: 10018 | B19: 1871 | C19: 45045 | D19: 45048 | E19: Chennai | F19: West Bengal | G19: Website | H19: Credit Card | I19: Home & Kitchen | J19: Curtains | K19: BrandD | L19: 1 | M19: 2165.81 | N19: 15 | O19: 1840.94 | Q19: Payment Method | R19: Net Banking
A20: 10019 | B20: 1663 | C20: 44965 | D20: 44968 | E20: Bengaluru | F20: Karnataka | G20: Marketplace | H20: Net Banking | I20: Fashion | J20: Jacket | K20: BrandE | L20: 2 | M20: 990.3 | N20: 15 | O20: 1683.51 | Q20: Product Category | R20: Fashion
A21: 10020 | B21: 1130 | C21: 45194 | D21: 45203 | E21: Mumbai | F21: Karnataka | G21: Mobile App | H21: Credit Card | I21: Electronics | J21: Smartwatch | K21: BrandA | L21: 2 | M21: 3959.31 | N21: 5 | O21: 7522.69 | Q21: Product Name | R21: Jacket
A22: 10021 | B22: 1661 | C22: 45159 | D22: 45163 | E22: Mumbai | F22: West Bengal | G22: Website | H22: Credit Card | I22: Beauty | J22: Lipstick | K22: BrandA | L22: 3 | M22: 2361.58 | N22: 5 | O22: 6730.5 | Q22: Brand | R22: BrandE
A23: 10022 | B23: 1308 | C23: 44944 | D23: 44951 | E23: Kolkata | F23: Tamil Nadu | G23: Marketplace | H23: Cash on Delivery | I23: Books | J23: Fiction Novel | K23: BrandE | L23: 7 | M23: 680.86 | N23: 20 | O23: 3812.82 | Q23: Units Sold | R23: 2
A24: 10023 | B24: 1769 | C24: 45075 | D24: 45084 | E24: Delhi | F24: Tamil Nadu | G24: Mobile App | H24: Net Banking | I24: Fashion | J24: Sneakers | K24: BrandC | L24: 2 | M24: 2801.74 | N24: 20 | O24: 4482.78 | Q24: Unit Price | R24: 990.3
A25: 10024 | B25: 1343 | C25: 45075 | D25: 45082 | E25: Pune | F25: Telangana | G25: Mobile App | H25: UPI | I25: Electronics | J25: Smartwatch | K25: BrandC | L25: 1 | M25: 3606.31 | N25: 0 | O25: 3606.31 | Q25: Discount % | R25: 15
A26: 10025 | B26: 1491 | C26: 45052 | D26: 45061 | E26: Kolkata | F26: Karnataka | G26: Marketplace | H26: UPI | I26: Books | J26: Comics | K26: BrandC | L26: 6 | M26: 3018.94 | N26: 5 | O26: 17207.96 | Q26: Net Sales | R26: 1683.51
A27: 10026 | B27: 1413 | C27: 45228 | D27: 45231 | E27: Bengaluru | F27: Delhi | G27: Marketplace | H27: Net Banking | I27: Beauty | J27: Perfume | K27: BrandE | L27: 9 | M27: 444.29 | N27: 5 | O27: 3798.68
A28: 10027 | B28: 1805 | C28: 45286 | D28: 45290 | E28: Kolkata | F28: Telangana | G28: Website | H28: Cash on Delivery | I28: Books | J28: Fiction Novel | K28: BrandA | L28: 3 | M28: 3599.15 | N28: 5 | O28: 10257.58
A29: 10028 | B29: 1385 | C29: 45164 | D29: 45172 | E29: Hyderabad | F29: Tamil Nadu | G29: Website | H29: Debit Card | I29: Electronics | J29: Smartwatch | K29: BrandE | L29: 6 | M29: 3206.63 | N29: 20 | O29: 15391.82
A30: 10029 | B30: 1191 | C30: 45061 | D30: 45067 | E30: Mumbai | F30: West Bengal | G30: Mobile App | H30: Credit Card | I30: Sports | J30: Football | K30: BrandE | L30: 3 | M30: 759.47 | N30: 15 | O30: 1936.65
A31: 10030 | B31: 1955 | C31: 45077 | D31: 45082 | E31: Mumbai | F31: Tamil Nadu | G31: Marketplace | H31: Cash on Delivery | I31: Sports | J31: Cricket Bat | K31: BrandC | L31: 1 | M31: 349.38 | N31: 10 | O31: 314.44
A32: 10031 | B32: 1276 | C32: 45162 | D32: 45166 | E32: Chennai | F32: West Bengal | G32: Marketplace | H32: Net Banking | I32: Books | J32: Textbook | K32: BrandB | L32: 5 | M32: 2295.65 | N32: 20 | O32: 9182.6
A33: 10032 | B33: 1160 | C33: 45150 | D33: 45158 | E33: Chennai | F33: Telangana | G33: Marketplace | H33: Credit Card | I33: Home & Kitchen | J33: Bedsheet | K33: BrandA | L33: 4 | M33: 750.74 | N33: 5 | O33: 2852.81
A34: 10033 | B34: 1459 | C34: 45129 | D34: 45130 | E34: Pune | F34: Karnataka | G34: Mobile App | H34: UPI | I34: Books | J34: Comics | K34: BrandC | L34: 7 | M34: 3363.18 | N34: 20 | O34: 18833.81
A35: 10034 | B35: 1313 | C35: 45182 | D35: 45191 | E35: Bengaluru | F35: Tamil Nadu | G35: Marketplace | H35: Debit Card | I35: Fashion | J35: T-Shirt | K35: BrandB | L35: 6 | M35: 1529.59 | N35: 0 | O35: 9177.54
A36: 10035 | B36: 1021 | C36: 45012 | D36: 45013 | E36: Hyderabad | F36: West Bengal | G36: Marketplace | H36: UPI | I36: Fashion | J36: T-Shirt | K36: BrandB | L36: 7 | M36: 3664.64 | N36: 5 | O36: 24369.86
A37: 10036 | B37: 1252 | C37: 45076 | D37: 45084 | E37: Delhi | F37: Karnataka | G37: Mobile App | H37: Net Banking | I37: Sports | J37: Football | K37: BrandD | L37: 5 | M37: 2327.9 | N37: 0 | O37: 11639.5
A38: 10037 | B38: 1747 | C38: 45161 | D38: 45165 | E38: Kolkata | F38: Delhi | G38: Website | H38: Credit Card | I38: Home & Kitchen | J38: Curtains | K38: BrandA | L38: 4 | M38: 853.29 | N38: 5 | O38: 3242.5
